Workbook
Name Business​: Intelligence!#REF!
Name Business​: 'Intelligence OLD'!$AC$9:$AC$15
Name Business​: '4. VAS list'!$AL$8:$AL$14
Name DigitalAccessAndProtection: Intelligence!#REF!
Name DigitalAccessAndProtection: 'Intelligence OLD'!$Z$10:$Z$15
Name DigitalAccessAndProtection: '4. VAS list'!$AI$9:$AI$14
Name DigitalAccessAndProtection​: Intelligence!#REF!
Name DigitalAccessAndProtection​: 'Intelligence OLD'!$AB$9:$AB$14
Name DigitalAccessAndProtection​: '4. VAS list'!$AK$8:$AK$13
Name Financial​: Intelligence!#REF!
Name Financial​: 'Intelligence OLD'!$Y$9:$Y$11
Name Financial​: '4. VAS list'!$AH$8:$AH$10
Name Health: Intelligence!#REF!
Name Health: 'Intelligence OLD'!$U$10:$U$22
Name Health: '4. VAS list'!$AD$9:$AD$24
Name Health​: Intelligence!#REF!
Name Health​: 'Intelligence OLD'!$W$9:$W$22
Name Health​: '4. VAS list'!$AF$8:$AF$23
Name HomeAndFamily: Intelligence!#REF!
Name HomeAndFamily: 'Intelligence OLD'!$Y$10:$Y$16
Name HomeAndFamily: '4. VAS list'!$AH$9:$AH$16
Name HomeAndFamily​: Intelligence!#REF!
Name HomeAndFamily​: 'Intelligence OLD'!$AA$9:$AA$15
Name HomeAndFamily​: '4. VAS list'!$AJ$8:$AJ$14
Name LOB: Intelligence!#REF!
Name LOB: 'Intelligence OLD'!$V$9:$V$15
Name LOB: '4. VAS list'!$AE$8:$AE$14
Name Mobility​: Intelligence!#REF!
Name Mobility​: 'Intelligence OLD'!$Z$9:$Z$15
Name Mobility​: '4. VAS list'!$AI$8:$AI$14
Name Protection​: Intelligence!#REF!
Name Protection​: 'Intelligence OLD'!$X$9:$X$11
Name Protection​: '4. VAS list'!$AG$8:$AG$10
Name VasNAme: REPOSITORY!$A$3:$A$35

Sheet Home
J4: 🔍 View the pipeline (outputs)
C6: VALUE TREE | J6: 00 VAS comparison | M6: 02 VAS deep dive | P6: 03 Master Scoring
J7: Compare VAS lists between themselves | M7: Sumup of VAS data and next step suggestions | P7: Compare VAS against key criteria
C9: GENERALI VAS
J10: Explore > | M10: Explore > | P10: Explore >
C11: WHY IT EXISTS
C12: To create total clarity, consistency and visibility over the methodology we are using. | J12: 📊 Score the pipeline (inputs)
J14: 04 VAS list | M14: 04 Scoring sheets | P14: 05 Input GTM Strategy
J15: Add VAS that will be involved into analysis | M15: Score VAS individually, so that an average can be taken | P15: Add currently strategy of VAS
J17: Explore > | M17: Explore > | P17: Explore >
J19: 🧑‍🎓 Scoring guide (instructions)
J21: 06 Tool manual | M21: 07 Scoring criteria
J22: Step by step instructions on how to use this VAS prioritisation tool | M22: Find a breakdown of all the scoring criteria and weighting used to assess VAS
J24: Explore >

Sheet REPOSITORY
A2: VasNAme | B2: Description | C2: LOB | D2: Category | E2: Priority1 | F2: Priority2 | G2: Priority3 | H2: Priorirty4 | I2: Bundle/Unbundle | J2: PriceVisibility | K2: Direct/Tiered | L2: Digital/Physiscal | M2: Paid_Media | N2: Paid _Channel | O2: Organic Media | P2: Organic_Channel? | Q2: Owned_Media | R2: Owned_Channel | S2: Importance_ competitive | T2: Competitor_differentiation | U2: Profiled_Target | V2: Core_Business_Sales | W2: %Multiproduct | X2: Customer_base | Y2: Customer_acquisition_costs | Z2: Claim_costs | AA2: TOTAL_GrowCoreBusiness | AB2: Business_Risk | AC2: TOTAL_Business_Risk | AD2: Perceived_Value | AE2: Potential_Reach | AF2: TOTAL_Percived_Value | AG2: Improve_NPS | AH2: Retention | AI2: Customer_interactions | AJ2: Differentiation | AK2: Regulation | AL2: TOTAL_Execution
A3: =IF('4. VAS list'!B8="","",'4. VAS list'!B8) -> Telemedicine | B3: ='4. VAS list'!C8 -> Cover the costs of private healthcare, from diagnosis to treatment | C3: ='4. VAS list'!G8 -> DigitalAccessAndProtection​ | D3: ='4. VAS list'!H8 -> Practical guides / Prevention information​ | E3: ='4. VAS list'!I8 -> Core Business | F3: ='4. VAS list'!G8 -> DigitalAccessAndProtection​ | G3: ='4. VAS list'!H8 -> Practical guides / Prevention information​ | H3: ='4. VAS list'!I8 -> Core Business | I3: ='5. Input GTM Strategy '!E13 -> Bundle | J3: ='5. Input GTM Strategy '!F13 -> Hidden | K3: ='5. Input GTM Strategy '!H13 -> Third parties | L3: ='5. Input GTM Strategy '!I13 -> Physical | M3: ='5. Input GTM Strategy '!H13 -> Third parties | N3: ='5. Input GTM Strategy '!I13 -> Physical | O3: ='5. Input GTM Strategy '!K13 -> 2 | P3: ='5. Input GTM Strategy '!L13 -> Radio | Q3: ='5. Input GTM Strategy '!M13 -> 2 | R3: ='5. Input GTM Strategy '!N13 -> Social Media | S3: ='5. Input GTM Strategy '!R13 -> Medium Importance | T3: ='5. Input GTM Strategy '!S13 -> 0 | U3: ='5. Input GTM Strategy '!U13 -> High profilation | V3: ='1. Master scoring '!R14 -> 5 | W3: ='1. Master scoring '!S14 | X3: ='1. Master scoring '!T14 -> 4 | Y3: ='1. Master scoring '!U14 -> 5 | Z3: ='1. Master scoring '!V14 -> 2.3333333 | AA3: ='1. Master scoring '!W14 -> 1.0208333 | AB3: ='1. Master scoring '!X14 -> 4.3333333 | AC3: ='1. Master scoring '!Y14 -> 4.3333333 | ... AI3: ='1. Master scoring '!AE14 -> 5 | AJ3: ='1. Master scoring '!#REF! -> #REF! | AK3: ='1. Master scoring '!AF14 -> 5 | AL3: ='1. Master scoring '!AG14 -> 2.5
A4: =IF('4. VAS list'!B9="","",'4. VAS list'!B9) -> ID Theft | B4: ='4. VAS list'!C9 -> Cover the costs you might incur from being defrauded | C4: ='4. VAS list'!G9 -> Health​ | D4: ='4. VAS list'!H9 -> Medical & health specialist services​ | E4: ='4. VAS list'!I9 -> Core Business | F4: ='4. VAS list'!G9 -> Health​ | G4: ='4. VAS list'!H9 -> Medical & health specialist services​ | H4: ='4. VAS list'!I9 -> Core Business | I4: ='5. Input GTM Strategy '!E14 -> Standalone | J4: ='5. Input GTM Strategy '!F14 -> Visible | K4: ='5. Input GTM Strategy '!H14 -> Third parties | L4: ='5. Input GTM Strategy '!I14 -> Phygital | M4: ='5. Input GTM Strategy '!H14 -> Third parties | N4: ='5. Input GTM Strategy '!I14 -> Phygital | O4: ='5. Input GTM Strategy '!K14 -> 3 or more | P4: ='5. Input GTM Strategy '!L14 -> TV | Q4: ='5. Input GTM Strategy '!M14 -> 1 | R4: ='5. Input GTM Strategy '!N14 -> Web marketing | S4: ='5. Input GTM Strategy '!R14 -> High Importance | T4: ='5. Input GTM Strategy '!S14 -> 0 | U4: ='5. Input GTM Strategy '!U14 -> Medium Profilation | V4: ='1. Master scoring '!R15 -> 5 | W4: ='1. Master scoring '!S15 | X4: ='1. Master scoring '!T15 -> 2 | Y4: ='1. Master scoring '!U15 -> 5 | Z4: ='1. Master scoring '!V15 -> 2.3333333 | AA4: ='1. Master scoring '!W15 -> 0.89583333 | AB4: ='1. Master scoring '!X15 -> 4 | AC4: ='1. Master scoring '!Y15 -> 4 | ... AI4: ='1. Master scoring '!AE15 -> 5 | AJ4: ='1. Master scoring '!#REF! -> #REF! | AK4: ='1. Master scoring '!AF15 -> 4.3333333 | AL4: ='1. Master scoring '!AG15 -> 2.4166667
A5: =IF('4. VAS list'!B10="","",'4. VAS list'!B10) -> Vehicle Geolocation | B5: ='4. VAS list'!C10 -> Install an approved GPS tracking device and reduce vehicle insurance premium | C5: ='4. VAS list'!G10 -> Mobility​ | D5: ='4. VAS list'!H10 -> Mobility assistance (bikes, fines help)​ | E5: ='4. VAS list'!I10 -> Core Business | F5: ='4. VAS list'!G10 -> Mobility​ | G5: ='4. VAS list'!H10 -> Mobility assistance (bikes, fines help)​ | H5: ='4. VAS list'!I10 -> Core Business | I5: ='5. Input GTM Strategy '!E15 -> Standalone | J5: ='5. Input GTM Strategy '!F15 -> Hidden | K5: ='5. Input GTM Strategy '!H15 -> Tiered Network | L5: ='5. Input GTM Strategy '!I15 -> Physical | M5: ='5. Input GTM Strategy '!H15 -> Tiered Network | N5: ='5. Input GTM Strategy '!I15 -> Physical | O5: ='5. Input GTM Strategy '!K15 -> 1 | P5: ='5. Input GTM Strategy '!L15 -> Print media | Q5: ='5. Input GTM Strategy '!M15 -> 3 or more | R5: ='5. Input GTM Strategy '!N15 -> Social Media | S5: ='5. Input GTM Strategy '!R15 -> High Importance | T5: ='5. Input GTM Strategy '!S15 -> 0 | U5: ='5. Input GTM Strategy '!U15 -> High profilation | V5: ='1. Master scoring '!R16 -> 5 | W5: ='1. Master scoring '!S16 | X5: ='1. Master scoring '!T16 -> 2.6666667 | Y5: ='1. Master scoring '!U16 -> 4.3333333 | Z5: ='1. Master scoring '!V16 -> 3 | AA5: ='1. Master scoring '!W16 -> 0.9375 | AB5: ='1. Master scoring '!X16 -> 3.6666667 | AC5: ='1. Master scoring '!Y16 -> 3.6666667 | ... AI5: ='1. Master scoring '!AE16 -> 4.6666667 | AJ5: ='1. Master scoring '!#REF! -> #REF! | AK5: ='1. Master scoring '!AF16 -> 5 | AL5: ='1. Master scoring '!AG16 -> 2.2916667
A6: =IF('4. VAS list'!B11="","",'4. VAS list'!B11) -> Pet Care | B6: ='4. VAS list'!C11 -> Cover the cost of veterinary fees for illnesses or injuries | C6: ='4. VAS list'!G11 -> HomeAndFamily​ | D6: ='4. VAS list'!H11 -> Pet care​ | E6: ='4. VAS list'!I11 -> Core Business | F6: ='4. VAS list'!G11 -> HomeAndFamily​ | G6: ='4. VAS list'!H11 -> Pet care​ | H6: ='4. VAS list'!I11 -> Core Business | I6: ='5. Input GTM Strategy '!E16 -> Bundle | J6: ='5. Input GTM Strategy '!F16 -> Visible | K6: ='5. Input GTM Strategy '!H16 -> Tiered Network | L6: ='5. Input GTM Strategy '!I16 -> Digital | M6: ='5. Input GTM Strategy '!H16 -> Tiered Network | N6: ='5. Input GTM Strategy '!I16 -> Digital | O6: ='5. Input GTM Strategy '!K16 -> 3 or more | P6: ='5. Input GTM Strategy '!L16 -> Display | Q6: ='5. Input GTM Strategy '!M16 -> 1 | R6: ='5. Input GTM Strategy '!N16 -> Events | S6: ='5. Input GTM Strategy '!R16 -> Low Importance | T6: ='5. Input GTM Strategy '!S16 -> 0 | U6: ='5. Input GTM Strategy '!U16 -> Low Profilation | V6: ='1. Master scoring '!R17 -> 4.6666667 | W6: ='1. Master scoring '!S17 | X6: ='1. Master scoring '!T17 -> 2.3333333 | Y6: ='1. Master scoring '!U17 -> 4.3333333 | Z6: ='1. Master scoring '!V17 -> 3 | AA6: ='1. Master scoring '!W17 -> 0.89583333 | AB6: ='1. Master scoring '!X17 -> 3.3333333 | AC6: ='1. Master scoring '!Y17 -> 3.3333333 | ... AI6: ='1. Master scoring '!AE17 -> 4.6666667 | AJ6: ='1. Master scoring '!#REF! -> #REF! | AK6: ='1. Master scoring '!AF17 -> 4.3333333 | AL6: ='1. Master scoring '!AG17 -> 2.375
A7: =IF('4. VAS list'!B12="","",'4. VAS list'!B12) -> Road Assistance | B7: ='4. VAS list'!C12 -> Lorem ipsum | C7: ='4. VAS list'!G12 -> Mobility​ | D7: ='4. VAS list'!H12 -> Emergency response​ | E7: ='4. VAS list'!I12 -> Core Business | F7: ='4. VAS list'!G12 -> Mobility​ | G7: ='4. VAS list'!H12 -> Emergency response​ | H7: ='4. VAS list'!I12 -> Core Business | I7: ='5. Input GTM Strategy '!E17 -> Pack | J7: ='5. Input GTM Strategy '!F17 -> Hidden | K7: ='5. Input GTM Strategy '!H17 -> Both | L7: ='5. Input GTM Strategy '!I17 -> Digital | M7: ='5. Input GTM Strategy '!H17 -> Both | N7: ='5. Input GTM Strategy '!I17 -> Digital | O7: ='5. Input GTM Strategy '!K17 -> 1 | P7: ='5. Input GTM Strategy '!L17 -> TV | Q7: ='5. Input GTM Strategy '!M17 -> 3 or more | R7: ='5. Input GTM Strategy '!N17 -> Events | S7: ='5. Input GTM Strategy '!R17 -> Low Importance | T7: ='5. Input GTM Strategy '!S17 -> 0 | U7: ='5. Input GTM Strategy '!U17 -> Low Profilation | V7: ='1. Master scoring '!R18 -> 4 | W7: ='1. Master scoring '!S18 | X7: ='1. Master scoring '!T18 -> 2.6666667 | Y7: ='1. Master scoring '!U18 -> 3.6666667 | Z7: ='1. Master scoring '!V18 -> 3.6666667 | AA7: ='1. Master scoring '!W18 -> 0.875 | AB7: ='1. Master scoring '!X18 -> 3.6666667 | AC7: ='1. Master scoring '!Y18 -> 3.6666667 | ... AI7: ='1. Master scoring '!AE18 -> 4.3333333 | AJ7: ='1. Master scoring '!#REF! -> #REF! | AK7: ='1. Master scoring '!AF18 -> 3.3333333 | AL7: ='1. Master scoring '!AG18 -> 1.875
A8: =IF('4. VAS list'!B13="","",'4. VAS list'!B13) | B8: ='4. VAS list'!C13 -> 0 | C8: ='4. VAS list'!G13 -> 0 | D8: ='4. VAS list'!H13 -> 0 | E8: ='4. VAS list'!I13 -> 0 | F8: ='4. VAS list'!G13 -> 0 | G8: ='4. VAS list'!H13 -> 0 | H8: ='4. VAS list'!I13 -> 0 | I8: ='5. Input GTM Strategy '!E18 -> Bundle | J8: ='5. Input GTM Strategy '!F18 -> Visible | K8: ='5. Input GTM Strategy '!H18 -> Both | L8: ='5. Input GTM Strategy '!I18 -> Physical | M8: ='5. Input GTM Strategy '!H18 -> Both | N8: ='5. Input GTM Strategy '!I18 -> Physical | O8: ='5. Input GTM Strategy '!K18 -> 2 | P8: ='5. Input GTM Strategy '!L18 -> Print media | Q8: ='5. Input GTM Strategy '!M18 -> 1 | R8: ='5. Input GTM Strategy '!N18 -> Web marketing | S8: ='5. Input GTM Strategy '!R18 -> Medium Importance | T8: ='5. Input GTM Strategy '!S18 -> 0 | U8: ='5. Input GTM Strategy '!U18 -> Mass Market | V8: ='1. Master scoring '!R19 | W8: ='1. Master scoring '!S19 | X8: ='1. Master scoring '!T19 | Y8: ='1. Master scoring '!U19 | Z8: ='1. Master scoring '!V19 | AA8: ='1. Master scoring '!W19 | AB8: ='1. Master scoring '!X19 | AC8: ='1. Master scoring '!Y19 | ... AI8: ='1. Master scoring '!AE19 | AJ8: ='1. Master scoring '!#REF! -> #REF! | AK8: ='1. Master scoring '!AF19 | AL8: ='1. Master scoring '!AG19
A9: =IF('4. VAS list'!B14="","",'4. VAS list'!B14) | B9: ='4. VAS list'!C14 -> 0 | C9: ='4. VAS list'!G14 -> 0 | D9: ='4. VAS list'!H14 -> 0 | E9: ='4. VAS list'!I14 -> 0 | F9: ='4. VAS list'!G14 -> 0 | G9: ='4. VAS list'!H14 -> 0 | H9: ='4. VAS list'!I14 -> 0 | I9: ='5. Input GTM Strategy '!E19 -> 0 | J9: ='5. Input GTM Strategy '!F19 -> 0 | K9: ='5. Input GTM Strategy '!H19 -> 0 | L9: ='5. Input GTM Strategy '!I19 -> 0 | M9: ='5. Input GTM Strategy '!H19 -> 0 | N9: ='5. Input GTM Strategy '!I19 -> 0 | O9: ='5. Input GTM Strategy '!K19 -> 0 | P9: ='5. Input GTM Strategy '!L19 -> 0 | Q9: ='5. Input GTM Strategy '!M19 -> 0 | R9: ='5. Input GTM Strategy '!N19 -> 0 | S9: ='5. Input GTM Strategy '!R19 -> 0 | T9: ='5. Input GTM Strategy '!S19 -> 0 | U9: ='5. Input GTM Strategy '!U19 -> 0 | V9: ='1. Master scoring '!R20 | W9: ='1. Master scoring '!S20 | X9: ='1. Master scoring '!T20 -> 0 | Y9: ='1. Master scoring '!U20 -> 0 | Z9: ='1. Master scoring '!V20 -> 0 | AA9: ='1. Master scoring '!W20 | AB9: ='1. Master scoring '!X20 | AC9: ='1. Master scoring '!Y20 | ... AI9: ='1. Master scoring '!AE20 -> 0 | AJ9: ='1. Master scoring '!#REF! -> #REF! | AK9: ='1. Master scoring '!AF20 | AL9: ='1. Master scoring '!AG20
A10: =IF('4. VAS list'!B15="","",'4. VAS list'!B15) | B10: ='4. VAS list'!C15 -> 0 | C10: ='4. VAS list'!G15 -> 0 | D10: ='4. VAS list'!H15 -> 0 | E10: ='4. VAS list'!I15 -> 0 | F10: ='4. VAS list'!G15 -> 0 | G10: ='4. VAS list'!H15 -> 0 | H10: ='4. VAS list'!I15 -> 0 | I10: ='5. Input GTM Strategy '!E20 -> 0 | J10: ='5. Input GTM Strategy '!F20 -> 0 | K10: ='5. Input GTM Strategy '!H20 -> 0 | L10: ='5. Input GTM Strategy '!I20 -> 0 | M10: ='5. Input GTM Strategy '!H20 -> 0 | N10: ='5. Input GTM Strategy '!I20 -> 0 | O10: ='5. Input GTM Strategy '!K20 -> 0 | P10: ='5. Input GTM Strategy '!L20 -> 0 | Q10: ='5. Input GTM Strategy '!M20 -> 0 | R10: ='5. Input GTM Strategy '!N20 -> 0 | S10: ='5. Input GTM Strategy '!R20 -> 0 | T10: ='5. Input GTM Strategy '!S20 -> 0 | U10: ='5. Input GTM Strategy '!U20 -> 0 | V10: ='1. Master scoring '!R21 | W10: ='1. Master scoring '!S21 | X10: ='1. Master scoring '!T21 -> 0 | Y10: ='1. Master scoring '!U21 -> 0 | Z10: ='1. Master scoring '!V21 -> 0 | AA10: ='1. Master scoring '!W21 | AB10: ='1. Master scoring '!X21 | AC10: ='1. Master scoring '!Y21 | ... AI10: ='1. Master scoring '!AE21 -> 0 | AJ10: ='1. Master scoring '!#REF! -> #REF! | AK10: ='1. Master scoring '!AF21 | AL10: ='1. Master scoring '!AG21
A11: =IF('4. VAS list'!B16="","",'4. VAS list'!B16) | B11: ='4. VAS list'!C16 -> 0 | C11: ='4. VAS list'!G16 -> 0 | D11: ='4. VAS list'!H16 -> 0 | E11: ='4. VAS list'!F16 -> 0 | F11: ='4. VAS list'!G16 -> 0 | G11: ='4. VAS list'!H16 -> 0 | H11: ='4. VAS list'!I16 -> 0 | I11: ='5. Input GTM Strategy '!E21 -> 0 | J11: ='5. Input GTM Strategy '!F21 -> 0 | K11: ='5. Input GTM Strategy '!H21 -> 0 | L11: ='5. Input GTM Strategy '!I21 -> 0 | M11: ='5. Input GTM Strategy '!H21 -> 0 | N11: ='5. Input GTM Strategy '!I21 -> 0 | O11: ='5. Input GTM Strategy '!K21 -> 0 | P11: ='5. Input GTM Strategy '!L21 -> 0 | Q11: ='5. Input GTM Strategy '!M21 -> 0 | R11: ='5. Input GTM Strategy '!N21 -> 0 | S11: ='5. Input GTM Strategy '!R21 -> 0 | T11: ='5. Input GTM Strategy '!S21 -> 0 | U11: ='5. Input GTM Strategy '!U21 -> 0 | V11: ='1. Master scoring '!R22 | W11: ='1. Master scoring '!S22 | X11: ='1. Master scoring '!T22 -> 0 | Y11: ='1. Master scoring '!U22 -> 0 | Z11: ='1. Master scoring '!V22 -> 0 | AA11: ='1. Master scoring '!W22 | AB11: ='1. Master scoring '!X22 | AC11: ='1. Master scoring '!Y22 | ... AI11: ='1. Master scoring '!AE22 -> 0 | AJ11: ='1. Master scoring '!#REF! -> #REF! | AK11: ='1. Master scoring '!AF22 | AL11: ='1. Master scoring '!AG22
A12: =IF('4. VAS list'!B17="","",'4. VAS list'!B17) | B12: ='4. VAS list'!C17 -> 0 | C12: ='4. VAS list'!G17 -> 0 | D12: ='4. VAS list'!H17 -> 0 | E12: ='4. VAS list'!F17 -> 0 | F12: ='4. VAS list'!G17 -> 0 | G12: ='4. VAS list'!H17 -> 0 | H12: ='4. VAS list'!I17 -> 0 | I12: ='5. Input GTM Strategy '!E22 -> 0 | J12: ='5. Input GTM Strategy '!F22 -> 0 | K12: ='5. Input GTM Strategy '!H22 -> 0 | L12: ='5. Input GTM Strategy '!I22 -> 0 | M12: ='5. Input GTM Strategy '!H22 -> 0 | N12: ='5. Input GTM Strategy '!I22 -> 0 | O12: ='5. Input GTM Strategy '!K22 -> 0 | P12: ='5. Input GTM Strategy '!L22 -> 0 | Q12: ='5. Input GTM Strategy '!M22 -> 0 | R12: ='5. Input GTM Strategy '!N22 -> 0 | S12: ='5. Input GTM Strategy '!R22 -> 0 | T12: ='5. Input GTM Strategy '!S22 -> 0 | U12: ='5. Input GTM Strategy '!U22 -> 0 | V12: ='1. Master scoring '!R23 | W12: ='1. Master scoring '!S23 | X12: ='1. Master scoring '!T23 -> 0 | Y12: ='1. Master scoring '!U23 -> 0 | Z12: ='1. Master scoring '!V23 -> 0 | AA12: ='1. Master scoring '!W23 | AB12: ='1. Master scoring '!X23 | AC12: ='1. Master scoring '!Y23 | ... AI12: ='1. Master scoring '!AE23 -> 0 | AJ12: ='1. Master scoring '!#REF! -> #REF! | AK12: ='1. Master scoring '!AF23 | AL12: ='1. Master scoring '!AG23
A13: =IF('4. VAS list'!B18="","",'4. VAS list'!B18) | B13: ='4. VAS list'!C18 -> 0 | C13: ='4. VAS list'!G18 -> 0 | D13: ='4. VAS list'!E18 -> 0 | E13: ='4. VAS list'!F18 -> 0 | F13: ='4. VAS list'!G18 -> 0 | G13: ='4. VAS list'!H18 -> 0 | H13: ='4. VAS list'!I18 -> 0 | I13: ='5. Input GTM Strategy '!E23 -> 0 | J13: ='5. Input GTM Strategy '!F23 -> 0 | K13: ='5. Input GTM Strategy '!H23 -> 0 | L13: ='5. Input GTM Strategy '!I23 -> 0 | M13: ='5. Input GTM Strategy '!H23 -> 0 | N13: ='5. Input GTM Strategy '!I23 -> 0 | O13: ='5. Input GTM Strategy '!K23 -> 0 | P13: ='5. Input GTM Strategy '!L23 -> 0 | Q13: ='5. Input GTM Strategy '!M23 -> 0 | R13: ='5. Input GTM Strategy '!N23 -> 0 | S13: ='5. Input GTM Strategy '!R23 -> 0 | T13: ='5. Input GTM Strategy '!S23 -> 0 | U13: ='5. Input GTM Strategy '!U23 -> 0 | V13: ='1. Master scoring '!R24 | W13: ='1. Master scoring '!S24 | X13: ='1. Master scoring '!T24 -> 0 | Y13: ='1. Master scoring '!U24 -> 0 | Z13: ='1. Master scoring '!V24 -> 0 | AA13: ='1. Master scoring '!W24 | AB13: ='1. Master scoring '!X24 | AC13: ='1. Master scoring '!Y24 | ... AI13: ='1. Master scoring '!AE24 -> 0 | AJ13: ='1. Master scoring '!#REF! -> #REF! | AK13: ='1. Master scoring '!AF24 | AL13: ='1. Master scoring '!AG24
A14: =IF('4. VAS list'!B19="","",'4. VAS list'!B19) | B14: ='4. VAS list'!C19 -> 0 | C14: ='4. VAS list'!G19 -> 0 | D14: ='4. VAS list'!E19 -> 0 | E14: ='4. VAS list'!F19 -> 0 | F14: ='4. VAS list'!G19 -> 0 | G14: ='4. VAS list'!H19 -> 0 | H14: ='4. VAS list'!I19 -> 0 | I14: ='5. Input GTM Strategy '!E24 -> 0 | J14: ='5. Input GTM Strategy '!F24 -> 0 | K14: ='5. Input GTM Strategy '!H24 -> 0 | L14: ='5. Input GTM Strategy '!I24 -> 0 | M14: ='5. Input GTM Strategy '!H24 -> 0 | N14: ='5. Input GTM Strategy '!I24 -> 0 | O14: ='5. Input GTM Strategy '!K24 -> 0 | P14: ='5. Input GTM Strategy '!L24 -> 0 | Q14: ='5. Input GTM Strategy '!M24 -> 0 | R14: ='5. Input GTM Strategy '!N24 -> 0 | S14: ='5. Input GTM Strategy '!R24 -> 0 | T14: ='5. Input GTM Strategy '!S24 -> 0 | U14: ='5. Input GTM Strategy '!U24 -> 0 | V14: ='1. Master scoring '!R25 | W14: ='1. Master scoring '!S25 | X14: ='1. Master scoring '!T25 -> 0 | Y14: ='1. Master scoring '!U25 -> 0 | Z14: ='1. Master scoring '!V25 -> 0 | AA14: ='1. Master scoring '!W25 | AB14: ='1. Master scoring '!X25 | AC14: ='1. Master scoring '!Y25 | ... AI14: ='1. Master scoring '!AE25 -> 0 | AJ14: ='1. Master scoring '!#REF! -> #REF! | AK14: ='1. Master scoring '!AF25 | AL14: ='1. Master scoring '!AG25
A15: =IF('4. VAS list'!B20="","",'4. VAS list'!B20) | B15: ='4. VAS list'!C20 -> 0 | C15: ='4. VAS list'!D20 -> 0 | D15: ='4. VAS list'!E20 -> 0 | E15: ='4. VAS list'!F20 -> 0 | F15: ='4. VAS list'!G20 -> 0 | G15: ='4. VAS list'!H20 -> 0 | H15: ='4. VAS list'!I20 -> 0 | I15: ='5. Input GTM Strategy '!E25 -> 0 | J15: ='5. Input GTM Strategy '!F25 -> 0 | K15: ='5. Input GTM Strategy '!H25 -> 0 | L15: ='5. Input GTM Strategy '!I25 -> 0 | M15: ='5. Input GTM Strategy '!H25 -> 0 | N15: ='5. Input GTM Strategy '!I25 -> 0 | O15: ='5. Input GTM Strategy '!K25 -> 0 | P15: ='5. Input GTM Strategy '!L25 -> 0 | Q15: ='5. Input GTM Strategy '!M25 -> 0 | R15: ='5. Input GTM Strategy '!N25 -> 0 | S15: ='5. Input GTM Strategy '!R25 -> 0 | T15: ='5. Input GTM Strategy '!S25 -> 0 | U15: ='5. Input GTM Strategy '!U25 -> 0 | V15: ='1. Master scoring '!R26 | W15: ='1. Master scoring '!S26 | X15: ='1. Master scoring '!T26 -> 0 | Y15: ='1. Master scoring '!U26 -> 0 | Z15: ='1. Master scoring '!V26 -> 0 | AA15: ='1. Master scoring '!W26 | AB15: ='1. Master scoring '!X26 | AC15: ='1. Master scoring '!Y26 | ... AI15: ='1. Master scoring '!AE26 -> 0 | AJ15: ='1. Master scoring '!#REF! -> #REF! | AK15: ='1. Master scoring '!AF26 | AL15: ='1. Master scoring '!AG26
A16: =IF('4. VAS list'!B21="","",'4. VAS list'!B21) | B16: ='4. VAS list'!C21 -> 0 | C16: ='4. VAS list'!D21 -> 0 | D16: ='4. VAS list'!E21 -> 0 | E16: ='4. VAS list'!F21 -> 0 | F16: ='4. VAS list'!G21 -> 0 | G16: ='4. VAS list'!H21 -> 0 | H16: ='4. VAS list'!I21 -> 0 | I16: ='5. Input GTM Strategy '!E26 -> 0 | J16: ='5. Input GTM Strategy '!F26 -> 0 | K16: ='5. Input GTM Strategy '!H26 -> 0 | L16: ='5. Input GTM Strategy '!I26 -> 0 | M16: ='5. Input GTM Strategy '!H26 -> 0 | N16: ='5. Input GTM Strategy '!I26 -> 0 | O16: ='5. Input GTM Strategy '!K26 -> 0 | P16: ='5. Input GTM Strategy '!L26 -> 0 | Q16: ='5. Input GTM Strategy '!M26 -> 0 | R16: ='5. Input GTM Strategy '!N26 -> 0 | S16: ='5. Input GTM Strategy '!R26 -> 0 | T16: ='5. Input GTM Strategy '!S26 -> 0 | U16: ='5. Input GTM Strategy '!U26 -> 0 | V16: ='1. Master scoring '!R27 | W16: ='1. Master scoring '!S27 | X16: ='1. Master scoring '!T27 -> 0 | Y16: ='1. Master scoring '!U27 -> 0 | Z16: ='1. Master scoring '!V27 -> 0 | AA16: ='1. Master scoring '!W27 | AB16: ='1. Master scoring '!X27 | AC16: ='1. Master scoring '!Y27 | ... AI16: ='1. Master scoring '!AE27 -> 0 | AJ16: ='1. Master scoring '!#REF! -> #REF! | AK16: ='1. Master scoring '!AF27 | AL16: ='1. Master scoring '!AG27
A17: =IF('4. VAS list'!B22="","",'4. VAS list'!B22) | B17: ='4. VAS list'!C22 -> 0 | C17: ='4. VAS list'!D22 -> 0 | D17: ='4. VAS list'!E22 -> 0 | E17: ='4. VAS list'!F22 -> 0 | F17: ='4. VAS list'!G22 -> 0 | G17: ='4. VAS list'!H22 -> 0 | H17: ='4. VAS list'!I22 -> 0 | I17: ='5. Input GTM Strategy '!E27 -> 0 | J17: ='5. Input GTM Strategy '!F27 -> 0 | K17: ='5. Input GTM Strategy '!H27 -> 0 | L17: ='5. Input GTM Strategy '!I27 -> 0 | M17: ='5. Input GTM Strategy '!H27 -> 0 | N17: ='5. Input GTM Strategy '!I27 -> 0 | O17: ='5. Input GTM Strategy '!K27 -> 0 | P17: ='5. Input GTM Strategy '!L27 -> 0 | Q17: ='5. Input GTM Strategy '!M27 -> 0 | R17: ='5. Input GTM Strategy '!N27 -> 0 | S17: ='5. Input GTM Strategy '!R27 -> 0 | T17: ='5. Input GTM Strategy '!S27 -> 0 | U17: ='5. Input GTM Strategy '!U27 -> 0 | V17: ='1. Master scoring '!R28 | W17: ='1. Master scoring '!S28 | X17: ='1. Master scoring '!T28 -> 0 | Y17: ='1. Master scoring '!U28 -> 0 | Z17: ='1. Master scoring '!V28 -> 0 | AA17: ='1. Master scoring '!W28 | AB17: ='1. Master scoring '!X28 | AC17: ='1. Master scoring '!Y28 | ... AI17: ='1. Master scoring '!AE28 -> 0 | AJ17: ='1. Master scoring '!#REF! -> #REF! | AK17: ='1. Master scoring '!AF28 | AL17: ='1. Master scoring '!AG28
A18: =IF('4. VAS list'!B23="","",'4. VAS list'!B23) | B18: ='4. VAS list'!C23 -> 0 | C18: ='4. VAS list'!D23 -> 0 | D18: ='4. VAS list'!E23 -> 0 | E18: ='4. VAS list'!F23 -> 0 | F18: ='4. VAS list'!G23 -> 0 | G18: ='4. VAS list'!H23 -> 0 | H18: ='4. VAS list'!I23 -> 0 | I18: ='5. Input GTM Strategy '!E28 -> 0 | J18: ='5. Input GTM Strategy '!F28 -> 0 | K18: ='5. Input GTM Strategy '!H28 -> 0 | L18: ='5. Input GTM Strategy '!I28 -> 0 | M18: ='5. Input GTM Strategy '!H28 -> 0 | N18: ='5. Input GTM Strategy '!I28 -> 0 | O18: ='5. Input GTM Strategy '!K28 -> 0 | P18: ='5. Input GTM Strategy '!L28 -> 0 | Q18: ='5. Input GTM Strategy '!M28 -> 0 | R18: ='5. Input GTM Strategy '!N28 -> 0 | S18: ='5. Input GTM Strategy '!R28 -> 0 | T18: ='5. Input GTM Strategy '!S28 -> 0 | U18: ='5. Input GTM Strategy '!U28 -> 0 | V18: ='1. Master scoring '!R29 | W18: ='1. Master scoring '!S29 | X18: ='1. Master scoring '!T29 -> 0 | Y18: ='1. Master scoring '!U29 -> 0 | Z18: ='1. Master scoring '!V29 -> 0 | AA18: ='1. Master scoring '!W29 | AB18: ='1. Master scoring '!X29 | AC18: ='1. Master scoring '!Y29 | ... AI18: ='1. Master scoring '!AE29 -> 0 | AJ18: ='1. Master scoring '!#REF! -> #REF! | AK18: ='1. Master scoring '!AF29 | AL18: ='1. Master scoring '!AG29
A19: =IF('4. VAS list'!B24="","",'4. VAS list'!B24) | B19: ='4. VAS list'!C24 -> 0 | C19: ='4. VAS list'!D24 -> 0 | D19: ='4. VAS list'!E24 -> 0 | E19: ='4. VAS list'!F24 -> 0 | F19: ='4. VAS list'!G24 -> 0 | G19: ='4. VAS list'!H24 -> 0 | H19: ='4. VAS list'!I24 -> 0 | I19: ='5. Input GTM Strategy '!E29 -> 0 | J19: ='5. Input GTM Strategy '!F29 -> 0 | K19: ='5. Input GTM Strategy '!H29 -> 0 | L19: ='5. Input GTM Strategy '!I29 -> 0 | M19: ='5. Input GTM Strategy '!H29 -> 0 | N19: ='5. Input GTM Strategy '!I29 -> 0 | O19: ='5. Input GTM Strategy '!K29 -> 0 | P19: ='5. Input GTM Strategy '!L29 -> 0 | Q19: ='5. Input GTM Strategy '!M29 -> 0 | R19: ='5. Input GTM Strategy '!N29 -> 0 | S19: ='5. Input GTM Strategy '!R29 -> 0 | T19: ='5. Input GTM Strategy '!S29 -> 0 | U19: ='5. Input GTM Strategy '!U29 -> 0 | V19: ='1. Master scoring '!R30 | W19: ='1. Master scoring '!S30 | X19: ='1. Master scoring '!T30 -> 0 | Y19: ='1. Master scoring '!U30 -> 0 | Z19: ='1. Master scoring '!V30 -> 0 | AA19: ='1. Master scoring '!W30 | AB19: ='1. Master scoring '!X30 | AC19: ='1. Master scoring '!Y30 | ... AI19: ='1. Master scoring '!AE30 -> 0 | AJ19: ='1. Master scoring '!#REF! -> #REF! | AK19: ='1. Master scoring '!AF30 | AL19: ='1. Master scoring '!AG30
A20: =IF('4. VAS list'!B25="","",'4. VAS list'!B25) | B20: ='4. VAS list'!C25 -> 0 | C20: ='4. VAS list'!D25 -> 0 | D20: ='4. VAS list'!E25 -> 0 | E20: ='4. VAS list'!F25 -> 0 | F20: ='4. VAS list'!G25 -> 0 | G20: ='4. VAS list'!H25 -> 0 | H20: ='4. VAS list'!I25 -> 0 | I20: ='5. Input GTM Strategy '!E30 -> 0 | J20: ='5. Input GTM Strategy '!F30 -> 0 | K20: ='5. Input GTM Strategy '!H30 -> 0 | L20: ='5. Input GTM Strategy '!I30 -> 0 | M20: ='5. Input GTM Strategy '!H30 -> 0 | N20: ='5. Input GTM Strategy '!I30 -> 0 | O20: ='5. Input GTM Strategy '!K30 -> 0 | P20: ='5. Input GTM Strategy '!L30 -> 0 | Q20: ='5. Input GTM Strategy '!M30 -> 0 | R20: ='5. Input GTM Strategy '!N30 -> 0 | S20: ='5. Input GTM Strategy '!R30 -> 0 | T20: ='5. Input GTM Strategy '!S30 -> 0 | U20: ='5. Input GTM Strategy '!U30 -> 0 | V20: ='1. Master scoring '!R31 | W20: ='1. Master scoring '!S31 | X20: ='1. Master scoring '!T31 -> 0 | Y20: ='1. Master scoring '!U31 -> 0 | Z20: ='1. Master scoring '!V31 -> 0 | AA20: ='1. Master scoring '!W31 | AB20: ='1. Master scoring '!X31 | AC20: ='1. Master scoring '!Y31 | ... AI20: ='1. Master scoring '!AE31 -> 0 | AJ20: ='1. Master scoring '!#REF! -> #REF! | AK20: ='1. Master scoring '!AF31 | AL20: ='1. Master scoring '!AG31
A21: =IF('4. VAS list'!B26="","",'4. VAS list'!B26) | B21: ='4. VAS list'!C26 -> 0 | C21: ='4. VAS list'!D26 -> 0 | D21: ='4. VAS list'!E26 -> 0 | E21: ='4. VAS list'!F26 -> 0 | F21: ='4. VAS list'!G26 -> 0 | G21: ='4. VAS list'!H26 -> 0 | H21: ='4. VAS list'!I26 -> 0 | I21: ='5. Input GTM Strategy '!E31 -> 0 | J21: ='5. Input GTM Strategy '!F31 -> 0 | K21: ='5. Input GTM Strategy '!H31 -> 0 | L21: ='5. Input GTM Strategy '!I31 -> 0 | M21: ='5. Input GTM Strategy '!H31 -> 0 | N21: ='5. Input GTM Strategy '!I31 -> 0 | O21: ='5. Input GTM Strategy '!K31 -> 0 | P21: ='5. Input GTM Strategy '!L31 -> 0 | Q21: ='5. Input GTM Strategy '!M31 -> 0 | R21: ='5. Input GTM Strategy '!N31 -> 0 | S21: ='5. Input GTM Strategy '!R31 -> 0 | T21: ='5. Input GTM Strategy '!S31 -> 0 | U21: ='5. Input GTM Strategy '!U31 -> 0 | V21: ='1. Master scoring '!R32 -> 0 | W21: ='1. Master scoring '!S32 -> 0 | X21: ='1. Master scoring '!T32 -> 0 | Y21: ='1. Master scoring '!U32 -> 0 | Z21: ='1. Master scoring '!V32 -> 0 | AA21: ='1. Master scoring '!W32 -> 0 | AB21: ='1. Master scoring '!X32 -> 0 | AC21: ='1. Master scoring '!Y32 -> 0 | ... AI21: ='1. Master scoring '!AE32 -> 0 | AJ21: ='1. Master scoring '!#REF! -> #REF! | AK21: ='1. Master scoring '!AF32 -> 0 | AL21: ='1. Master scoring '!AG32 -> 0
A22: =IF('4. VAS list'!B27="","",'4. VAS list'!B27) | B22: ='4. VAS list'!C27 -> 0 | C22: ='4. VAS list'!D27 -> 0 | D22: ='4. VAS list'!E27 -> 0 | E22: ='4. VAS list'!F27 -> 0 | F22: ='4. VAS list'!G27 -> 0 | G22: ='4. VAS list'!H27 -> 0 | H22: ='4. VAS list'!I27 -> 0 | I22: ='5. Input GTM Strategy '!E32 -> 0 | J22: ='5. Input GTM Strategy '!F32 -> 0 | K22: ='5. Input GTM Strategy '!H32 -> 0 | L22: ='5. Input GTM Strategy '!I32 -> 0 | M22: ='5. Input GTM Strategy '!H32 -> 0 | N22: ='5. Input GTM Strategy '!I32 -> 0 | O22: ='5. Input GTM Strategy '!K32 -> 0 | P22: ='5. Input GTM Strategy '!L32 -> 0 | Q22: ='5. Input GTM Strategy '!M32 -> 0 | R22: ='5. Input GTM Strategy '!N32 -> 0 | S22: ='5. Input GTM Strategy '!R32 -> 0 | T22: ='5. Input GTM Strategy '!S32 -> 0 | U22: ='5. Input GTM Strategy '!U32 -> 0 | V22: ='1. Master scoring '!R33 -> 0 | W22: ='1. Master scoring '!S33 -> 0 | X22: ='1. Master scoring '!T33 -> 0 | Y22: ='1. Master scoring '!U33 -> 0 | Z22: ='1. Master scoring '!V33 -> 0 | AA22: ='1. Master scoring '!W33 -> 0 | AB22: ='1. Master scoring '!X33 -> 0 | AC22: ='1. Master scoring '!Y33 -> 0 | ... AI22: ='1. Master scoring '!AE33 -> 0 | AJ22: ='1. Master scoring '!#REF! -> #REF! | AK22: ='1. Master scoring '!AF33 -> 0 | AL22: ='1. Master scoring '!AG33 -> 0
A23: =IF('4. VAS list'!B28="","",'4. VAS list'!B28) | B23: ='4. VAS list'!C28 -> 0 | C23: ='4. VAS list'!D28 -> 0 | D23: ='4. VAS list'!E28 -> 0 | E23: ='4. VAS list'!F28 -> 0 | F23: ='4. VAS list'!G28 -> 0 | G23: ='4. VAS list'!H28 -> 0 | H23: ='4. VAS list'!I28 -> 0 | I23: ='5. Input GTM Strategy '!E33 -> 0 | J23: ='5. Input GTM Strategy '!F33 -> 0 | K23: ='5. Input GTM Strategy '!H33 -> 0 | L23: ='5. Input GTM Strategy '!I33 -> 0 | M23: ='5. Input GTM Strategy '!H33 -> 0 | N23: ='5. Input GTM Strategy '!I33 -> 0 | O23: ='5. Input GTM Strategy '!K33 -> 0 | P23: ='5. Input GTM Strategy '!L33 -> 0 | Q23: ='5. Input GTM Strategy '!M33 -> 0 | R23: ='5. Input GTM Strategy '!N33 -> 0 | S23: ='5. Input GTM Strategy '!R33 -> 0 | T23: ='5. Input GTM Strategy '!S33 -> 0 | U23: ='5. Input GTM Strategy '!U33 -> 0 | V23: ='1. Master scoring '!R34 -> 0 | W23: ='1. Master scoring '!S34 -> 0 | X23: ='1. Master scoring '!T34 -> 0 | Y23: ='1. Master scoring '!U34 -> 0 | Z23: ='1. Master scoring '!V34 -> 0 | AA23: ='1. Master scoring '!W34 -> 0 | AB23: ='1. Master scoring '!X34 -> 0 | AC23: ='1. Master scoring '!Y34 -> 0 | ... AI23: ='1. Master scoring '!AE34 -> 0 | AJ23: ='1. Master scoring '!#REF! -> #REF! | AK23: ='1. Master scoring '!AF34 -> 0 | AL23: ='1. Master scoring '!AG34 -> 0
A24: =IF('4. VAS list'!B29="","",'4. VAS list'!B29) | B24: ='4. VAS list'!C29 -> 0 | C24: ='4. VAS list'!D29 -> 0 | D24: ='4. VAS list'!E29 -> 0 | E24: ='4. VAS list'!F29 -> 0 | F24: ='4. VAS list'!G29 -> 0 | G24: ='4. VAS list'!H29 -> 0 | H24: ='4. VAS list'!I29 -> 0 | I24: ='5. Input GTM Strategy '!E34 -> 0 | J24: ='5. Input GTM Strategy '!F34 -> 0 | K24: ='5. Input GTM Strategy '!H34 -> 0 | L24: ='5. Input GTM Strategy '!I34 -> 0 | M24: ='5. Input GTM Strategy '!H34 -> 0 | N24: ='5. Input GTM Strategy '!I34 -> 0 | O24: ='5. Input GTM Strategy '!K34 -> 0 | P24: ='5. Input GTM Strategy '!L34 -> 0 | Q24: ='5. Input GTM Strategy '!M34 -> 0 | R24: ='5. Input GTM Strategy '!N34 -> 0 | S24: ='5. Input GTM Strategy '!R34 -> 0 | T24: ='5. Input GTM Strategy '!S34 -> 0 | U24: ='5. Input GTM Strategy '!U34 -> 0 | V24: ='1. Master scoring '!R35 -> 0 | W24: ='1. Master scoring '!S35 -> 0 | X24: ='1. Master scoring '!T35 -> 0 | Y24: ='1. Master scoring '!U35 -> 0 | Z24: ='1. Master scoring '!V35 -> 0 | AA24: ='1. Master scoring '!W35 -> 0 | AB24: ='1. Master scoring '!X35 -> 0 | AC24: ='1. Master scoring '!Y35 -> 0 | ... AI24: ='1. Master scoring '!AE35 -> 0 | AJ24: ='1. Master scoring '!#REF! -> #REF! | AK24: ='1. Master scoring '!AF35 -> 0 | AL24: ='1. Master scoring '!AG35 -> 0
A25: =IF('4. VAS list'!B30="","",'4. VAS list'!B30) | B25: ='4. VAS list'!C30 -> 0 | C25: ='4. VAS list'!D30 -> 0 | D25: ='4. VAS list'!E30 -> 0 | E25: ='4. VAS list'!F30 -> 0 | F25: ='4. VAS list'!G30 -> 0 | G25: ='4. VAS list'!H30 -> 0 | H25: ='4. VAS list'!I30 -> 0 | I25: ='5. Input GTM Strategy '!E35 -> 0 | J25: ='5. Input GTM Strategy '!F35 -> 0 | K25: ='5. Input GTM Strategy '!H35 -> 0 | L25: ='5. Input GTM Strategy '!I35 -> 0 | M25: ='5. Input GTM Strategy '!H35 -> 0 | N25: ='5. Input GTM Strategy '!I35 -> 0 | O25: ='5. Input GTM Strategy '!K35 -> 0 | P25: ='5. Input GTM Strategy '!L35 -> 0 | Q25: ='5. Input GTM Strategy '!M35 -> 0 | R25: ='5. Input GTM Strategy '!N35 -> 0 | S25: ='5. Input GTM Strategy '!R35 -> 0 | T25: ='5. Input GTM Strategy '!S35 -> 0 | U25: ='5. Input GTM Strategy '!U35 -> 0 | V25: ='1. Master scoring '!R36 -> 0 | W25: ='1. Master scoring '!S36 -> 0 | X25: ='1. Master scoring '!T36 -> 0 | Y25: ='1. Master scoring '!U36 -> 0 | Z25: ='1. Master scoring '!V36 -> 0 | AA25: ='1. Master scoring '!W36 -> 0 | AB25: ='1. Master scoring '!X36 -> 0 | AC25: ='1. Master scoring '!Y36 -> 0 | ... AI25: ='1. Master scoring '!AE36 -> 0 | AJ25: ='1. Master scoring '!#REF! -> #REF! | AK25: ='1. Master scoring '!AF36 -> 0 | AL25: ='1. Master scoring '!AG36 -> 0
A26: =IF('4. VAS list'!B31="","",'4. VAS list'!B31) | B26: ='4. VAS list'!C31 -> 0 | C26: ='4. VAS list'!D31 -> 0 | D26: ='4. VAS list'!E31 -> 0 | E26: ='4. VAS list'!F31 -> 0 | F26: ='4. VAS list'!G31 -> 0 | G26: ='4. VAS list'!H31 -> 0 | H26: ='4. VAS list'!I31 -> 0 | I26: ='5. Input GTM Strategy '!E36 -> 0 | J26: ='5. Input GTM Strategy '!F36 -> 0 | K26: ='5. Input GTM Strategy '!H36 -> 0 | L26: ='5. Input GTM Strategy '!I36 -> 0 | M26: ='5. Input GTM Strategy '!H36 -> 0 | N26: ='5. Input GTM Strategy '!I36 -> 0 | O26: ='5. Input GTM Strategy '!K36 -> 0 | P26: ='5. Input GTM Strategy '!L36 -> 0 | Q26: ='5. Input GTM Strategy '!M36 -> 0 | R26: ='5. Input GTM Strategy '!N36 -> 0 | S26: ='5. Input GTM Strategy '!R36 -> 0 | T26: ='5. Input GTM Strategy '!S36 -> 0 | U26: ='5. Input GTM Strategy '!U36 -> 0 | V26: ='1. Master scoring '!R37 -> 0 | W26: ='1. Master scoring '!S37 -> 0 | X26: ='1. Master scoring '!T37 -> 0 | Y26: ='1. Master scoring '!U37 -> 0 | Z26: ='1. Master scoring '!V37 -> 0 | AA26: ='1. Master scoring '!W37 -> 0 | AB26: ='1. Master scoring '!X37 -> 0 | AC26: ='1. Master scoring '!Y37 -> 0 | ... AI26: ='1. Master scoring '!AE37 -> 0 | AJ26: ='1. Master scoring '!#REF! -> #REF! | AK26: ='1. Master scoring '!AF37 -> 0 | AL26: ='1. Master scoring '!AG37 -> 0
... A35: =IF('4. VAS list'!B40="","",'4. VAS list'!B40) | B35: ='4. VAS list'!C40 -> 0 | C35: ='4. VAS list'!D40 -> 0 | D35: ='4. VAS list'!E40 -> 0 | E35: ='4. VAS list'!F40 -> 0 | F35: ='4. VAS list'!G40 -> 0 | G35: ='4. VAS list'!H40 -> 0 | H35: ='4. VAS list'!I40 -> 0 | I35: ='5. Input GTM Strategy '!E45 -> 0 | J35: ='5. Input GTM Strategy '!F45 -> 0 | K35: ='5. Input GTM Strategy '!H45 -> 0 | L35: ='5. Input GTM Strategy '!I45 -> 0 | M35: ='5. Input GTM Strategy '!H45 -> 0 | N35: ='5. Input GTM Strategy '!I45 -> 0 | O35: ='5. Input GTM Strategy '!K45 -> 0 | P35: ='5. Input GTM Strategy '!L45 -> 0 | Q35: ='5. Input GTM Strategy '!M45 -> 0 | R35: ='5. Input GTM Strategy '!N45 -> 0 | S35: ='5. Input GTM Strategy '!R45 -> 0 | T35: ='5. Input GTM Strategy '!S45 -> 0 | U35: ='5. Input GTM Strategy '!U45 -> 0 | V35: ='1. Master scoring '!R46 -> 0 | W35: ='1. Master scoring '!S46 -> 0 | X35: ='1. Master scoring '!T46 -> 0 | Y35: ='1. Master scoring '!U46 -> 0 | Z35: ='1. Master scoring '!V46 -> 0 | AA35: ='1. Master scoring '!W46 -> 0 | AB35: ='1. Master scoring '!X46 -> 0 | AC35: ='1. Master scoring '!Y46 -> 0 | ... AI35: ='1. Master scoring '!AE46 -> 0 | AJ35: ='1. Master scoring '!#REF! -> #REF! | AK35: ='1. Master scoring '!AF46 -> 0 | AL35: ='1. Master scoring '!AG46 -> 0

Sheet 1. Master scoring 
B2: Master scoring
B3: Detailed visualization of all added VAS
C7: MANUAL INPUT | I7: MANUAL/AUTOMATED INPUT. | O7: AUTOMATED.
C8: OVERVIEW | I8: Priority | O8: Score | R8: Scoring criteria (av.)
O9: Scoring | R9: Grow core Business Margin | X9: Commercial Viability | Z9: Customer Desirability | AC9: Execution | AH9: Price VS Costs | AL9: EXTRA INFORMATION | AN9: Resources
C10: VAS | D10: Description | E10: LOB | F10: Category | J10: Core Business | K10: Commercial Viability | L10: Execution | M10: Customer Desirability | O10: Overall Score | P10: Rank | R10: Core Business Sales | S10: % Multiproduct | T10: Customer base | U10: Customer acquisition costs | V10: Claim costs | W10: TOTAL | X10: Business Risk | Y10: TOTAL | Z10: Perceived Value | AA10: Potential Reach | AB10: TOTAL | AC10: Improve NPS | AD10: Retention | AE10: Increase customers' interactions (TP) | AF10: Regulation | AG10: TOTAL | AH10: Insurance Price | AI10: Insurance Cost | AJ10: TOTAL | AL10: Additional notes | AN10: Are there relevant research materials?
O11: =IFERROR(AVERAGEIF($C14:$C130,"<>",O14:O130),"") -> 3.8598485 | P11: - | R11: =IFERROR(AVERAGEIF($C14:$C130,"<>",R14:R130),"") -> 4.7333333 | S11: =IFERROR(AVERAGEIF($C14:$C130,"<>",S14:S130),"") | T11: =IFERROR(AVERAGEIF($C14:$C130,"<>",T14:T130),"") -> 2.7333333 | U11: =IFERROR(AVERAGEIF($C14:$C130,"<>",U14:U130),"") -> 4.4666667 | V11: =IFERROR(AVERAGEIF($C14:$C130,"<>",V14:V130),"") -> 2.8666667 | W11: =IFERROR(AVERAGEIF($C14:$C130,"<>",W14:W130),"") -> 0.925 | X11: =IFERROR(AVERAGEIF($C14:$C130,"<>",X14:X130),"") -> 3.8 | Y11: =IFERROR(AVERAGEIF($C14:$C130,"<>",Y14:Y130),"") -> 3.8 | ... AJ11: =IFERROR(AVERAGEIF($C14:$C130,"<>",AJ14:AJ130),"")
C12: What is the name of the VAS? | D12: Brief description of VAS | E12: Which strategic pillar does this VAS fall under? | F12: If 'Net new', can the feature be grouped into a broader area or pain point? | L12: Does this feature meet the requirements for its opportunity type? See 'Scoring criteria' for minimum requirement details | O12: Overall score. | P12: Rank | R12: How are VAS' revenues contributing to the company performance? | S12: How much this VAS improve sales of other products/services? | T12: How many customers are acquired thanks to this VAS? | U12: How much the VAS contribute to reduce the cost of acquisition of a single customer? | V12: How much the VAS contribute to reduce the cost of single claim? | W12: Overall Business Margin score | X12: How expose are we to this VAS considering: reputation, financial and customer relation? | Y12: Overall Commercial Viability score | Z12: How much value would this feature deliver to customers? | AA12: What is the total number of customers (i.e. market size) we could realistically offer this feature to? | AB12: Overall Customer Desirability score | AC12: What is the customers' satisfaction (NPS) related to the service? | AD12: Percentage of customer that are actively using the service. | AE12: How often the customer interact with the VAS? | AF12: How complex or restrictive is the regulatory environment for this VAS? | AG12: Overall Execution Feasibility score | AH12: Price of the insurance for the customer | AI12: Cost of the insurance for the company | AJ12: Overall Execution Feasibility score | AL12: What was the outcome of review? Are there agreed next steps to be aware of? | AN12: Materials #1 | AO12: Materials #2 | AP12: Materials #3
C13: Automated. | D13: Automated. | E13: Automated. | F13: Automated. | J13: Automated. | K13: Automated. | L13: Automated. | M13: Automated. | O13: Automated. | P13: Automated. | R13: 5: Very high impact 4: High impact 3: Some impact 2: Low impact 1: No impact | S13: 5: Very high impact 4: High impact 3: Some impact 2: Low impact 1: No impact | T13: 5: Large Amount 4: A lot 3: Some 2: Few 1: No client | U13: 5: High Contribution 4: Moderate contribution 3: Medium contribution 2: Low contribution 1: Very low contribution | V13: 5: High Contribution 4: Moderate contribution 3: Medium contribution 2: Low contribution 1: Very low contribution | W13: Automated. | X13: 5: Very Low Risk 4: Low Risk 3: Medium Risk 2: Moderate Risk 1: High Risk | Y13: Automated. | Z13: 5: Very high value 4: High value 3: Some value 2: Low value 1: No value | AA13: 5: Mass market 4: Large reach 3: Solid reach 2: Niche segment 1: Very niche segment | AB13: Automated. | AC13: 5: from 9 to 10 4: from 7 to 8 3: from 6 to 5 2: from 3 to 4 1: from 1 to 2 | AD13: 5: More than X% 4: Between X% and X% 3 Between X% and X% 2: Between X% and X% 1: Less than X% | AE13: 5: more than six times a year 4: six times a year 3: four a year 2: twice a year 1: once a year | AF13: 5: No red tape 4: Low regulation 3: Some regulation 2: Highly regulated 1: Very highly regulated | AG13: Automated. | AH13: Value | AI13: Value | AJ13: Overall Execution Feasibility score | AL13: Manual | AN13: Manual | AO13: Manual | AP13: Manual
C14: ='4. VAS list'!B8 -> Telemedicine | D14: =IF('4. VAS list'!C8="","",'4. VAS list'!C8) -> Cover the costs of private healthcare, from diagnosis to treatment | E14: =IF('4. VAS list'!G8="","",'4. VAS list'!G8) -> DigitalAccessAndProtection​ | F14: =IF('4. VAS list'!H8="","",'4. VAS list'!H8) -> Practical guides / Prevention information​ | J14: {=_xlfn.IFNA(_xlfn.IFS('4. VAS list'!$I8='1. Master scoring '!$J$10,1,'4. VAS list'!$J8='1. Master scoring '!$J$10,2,'4. VAS list'!$K8='1. Master scoring '!$J$10,3,'4. VAS list'!$L8='1. Master scoring '!$J$10,4),"Completare")} -> 1 | K14: {=_xlfn.IFNA(_xlfn.IFS('4. VAS list'!$I8='1. Master scoring '!$K$10,1,'4. VAS list'!$J8='1. Master scoring '!$K$10,2,'4. VAS list'!$K8='1. Master scoring '!$K$10,3,'4. VAS list'!$L8='1. Master scoring '!$K$10,4),"Completare")} -> 2 | L14: {=_xlfn.IFNA(_xlfn.IFS('4. VAS list'!$I8='1. Master scoring '!$L$10,1,'4. VAS list'!$J8='1. Master scoring '!$L$10,2,'4. VAS list'!$K8='1. Master scoring '!$L$10,3,'4. VAS list'!$L8='1. Master scoring '!$L$10,4),"Completare")} -> 3 | M14: {=_xlfn.IFNA(_xlfn.IFS('4. VAS list'!$I8='1. Master scoring '!$M$10,1,'4. VAS list'!$J8='1. Master scoring '!$M$10,2,'4. VAS list'!$K8='1. Master scoring '!$M$10,3,'4. VAS list'!$L8='1. Master scoring '!$M$10,4),"Completare")} -> 4 | O14: =IFERROR(AVERAGE(R14:W14,X14:X14,Z14:Z14,AC14:AF14),"") -> 4.2443182 | P14: =IFERROR(RANK(O14,$O$14:$O$128,0)+COUNTIF($O$14:O14,#REF!)," ") -> 1 | R14: =IFERROR(AVERAGE('4a. Scorer 1'!F13,'4b. Scorer 2'!F13,'4c. Scorer 3'!F13)," ") -> 5 | S14: =IFERROR(AVERAGE('4a. Scorer 1'!G13,'4b. Scorer 2'!G13,'4c. Scorer 3'!G13)," ") | T14: =IFERROR(AVERAGE('4a. Scorer 1'!H13,'4b. Scorer 2'!H13,'4c. Scorer 3'!H13)," ") -> 4 | U14: =IFERROR(AVERAGE('4a. Scorer 1'!I13,'4b. Scorer 2'!I13,'4c. Scorer 3'!I13)," ") -> 5 | V14: =IFERROR(AVERAGE('4a. Scorer 1'!J13,'4b. Scorer 2'!J13,'4c. Scorer 3'!J13)," ") -> 2.3333333 | W14: =IFERROR(AVERAGE(R14:V14)*(J14/MAX(J14:M14)),"") -> 1.0208333 | X14: =IFERROR(AVERAGE('4a. Scorer 1'!L13,'4b. Scorer 2'!L13,'4c. Scorer 3'!L13)," ") -> 4.3333333 | Y14: =IFERROR(AVERAGE(X14:X14)*(M14/MAX(J14:M14)),"") -> 4.3333333 | Z14: =IFERROR(AVERAGE('4a. Scorer 1'!N13,'4b. Scorer 2'!N13,'4c. Scorer 3'!N13)," ") -> 5 | AA14: =IFERROR(AVERAGE('4a. Scorer 1'!O13,'4b. Scorer 2'!O13,'4c. Scorer 3'!O13)," ") -> 5 | AB14: =IFERROR(AVERAGE(Z14:Z14)*(L14/MAX(J14:M14)),"") -> 3.75 | AC14: =IFERROR(AVERAGE('4a. Scorer 1'!Q13,'4b. Scorer 2'!Q13,'4c. Scorer 3'!Q13)," ") -> 5 | AD14: =IFERROR(AVERAGE('4a. Scorer 1'!R13,'4b. Scorer 2'!R13,'4c. Scorer 3'!R13)," ") -> 5 | AE14: =IFERROR(AVERAGE('4a. Scorer 1'!S13,'4b. Scorer 2'!S13,'4c. Scorer 3'!S13)," ") -> 5 | AF14: =IFERROR(AVERAGE('4a. Scorer 1'!T13,'4b. Scorer 2'!T13,'4c. Scorer 3'!T13)," ") -> 5 | AG14: =IFERROR(AVERAGE(AC14:AF14)*(K14/MAX(J14:M14)),"") -> 2.5 | AH14: =IFERROR(AVERAGE('4a. Scorer 1'!V13,'4b. Scorer 2'!V13,'4c. Scorer 3'!V13)," ") -> 2.6666667 | AI14: =IFERROR(AVERAGE('4a. Scorer 1'!W13,'4b. Scorer 2'!W13,'4c. Scorer 3'!W13)," ") -> 4 | AL14: Deprioritised based on lack of clear customer need/potential partners
C15: ='4. VAS list'!B9 -> ID Theft | D15: =IF('4. VAS list'!C9="","",'4. VAS list'!C9) -> Cover the costs you might incur from being defrauded | E15: =IF('4. VAS list'!G9="","",'4. VAS list'!G9) -> Health​ | F15: =IF('4. VAS list'!H9="","",'4. VAS list'!H9) -> Medical & health specialist services​ | J15: {=_xlfn.IFNA(_xlfn.IFS('4. VAS list'!$I9='1. Master scoring '!$J$10,1,'4. VAS list'!$J9='1. Master scoring '!$J$10,2,'4. VAS list'!$K9='1. Master scoring '!$J$10,3,'4. VAS list'!$L9='1. Master scoring '!$J$10,4),"Completare")} -> 1 | K15: {=_xlfn.IFNA(_xlfn.IFS('4. VAS list'!$I9='1. Master scoring '!$K$10,1,'4. VAS list'!$J9='1. Master scoring '!$K$10,2,'4. VAS list'!$K9='1. Master scoring '!$K$10,3,'4. VAS list'!$L9='1. Master scoring '!$K$10,4),"Completare")} -> 2 | L15: {=_xlfn.IFNA(_xlfn.IFS('4. VAS list'!$I9='1. Master scoring '!$L$10,1,'4. VAS list'!$J9='1. Master scoring '!$L$10,2,'4. VAS list'!$K9='1. Master scoring '!$L$10,3,'4. VAS list'!$L9='1. Master scoring '!$L$10,4),"Completare")} -> 3 | M15: {=_xlfn.IFNA(_xlfn.IFS('4. VAS list'!$I9='1. Master scoring '!$M$10,1,'4. VAS list'!$J9='1. Master scoring '!$M$10,2,'4. VAS list'!$K9='1. Master scoring '!$M$10,3,'4. VAS list'!$L9='1. Master scoring '!$M$10,4),"Completare")} -> 4 | O15: =IFERROR(AVERAGE(R15:W15,X15:X15,Z15:Z15,AC15:AF15),"") -> 3.9299242 | P15: =IFERROR(RANK(O15,$O$14:$O$128,0)+COUNTIF($O$14:O15,#REF!)," ") -> 2 | R15: =IFERROR(AVERAGE('4a. Scorer 1'!F14,'4b. Scorer 2'!F14,'4c. Scorer 3'!F14)," ") -> 5 | S15: =IFERROR(AVERAGE('4a. Scorer 1'!G14,'4b. Scorer 2'!G14,'4c. Scorer 3'!G14)," ") | T15: =IFERROR(AVERAGE('4a. Scorer 1'!H14,'4b. Scorer 2'!H14,'4c. Scorer 3'!H14)," ") -> 2 | U15: =IFERROR(AVERAGE('4a. Scorer 1'!I14,'4b. Scorer 2'!I14,'4c. Scorer 3'!I14)," ") -> 5 | V15: =IFERROR(AVERAGE('4a. Scorer 1'!J14,'4b. Scorer 2'!J14,'4c. Scorer 3'!J14)," ") -> 2.3333333 | W15: =IFERROR(AVERAGE(R15:V15)*(J15/MAX(J15:M15)),"") -> 0.89583333 | X15: =IFERROR(AVERAGE('4a. Scorer 1'!L14,'4b. Scorer 2'!L14,'4c. Scorer 3'!L14)," ") -> 4 | Y15: =IFERROR(AVERAGE(X15:X15)*(M15/MAX(J15:M15)),"") -> 4 | Z15: =IFERROR(AVERAGE('4a. Scorer 1'!N14,'4b. Scorer 2'!N14,'4c. Scorer 3'!N14)," ") -> 4.6666667 | AA15: =IFERROR(AVERAGE('4a. Scorer 1'!O14,'4b. Scorer 2'!O14,'4c. Scorer 3'!O14)," ") -> 4 | AB15: =IFERROR(AVERAGE(Z15:Z15)*(L15/MAX(J15:M15)),"") -> 3.5 | AC15: =IFERROR(AVERAGE('4a. Scorer 1'!Q14,'4b. Scorer 2'!Q14,'4c. Scorer 3'!Q14)," ") -> 5 | AD15: =IFERROR(AVERAGE('4a. Scorer 1'!R14,'4b. Scorer 2'!R14,'4c. Scorer 3'!R14)," ") -> 5 | AE15: =IFERROR(AVERAGE('4a. Scorer 1'!S14,'4b. Scorer 2'!S14,'4c. Scorer 3'!S14)," ") -> 5 | AF15: =IFERROR(AVERAGE('4a. Scorer 1'!T14,'4b. Scorer 2'!T14,'4c. Scorer 3'!T14)," ") -> 4.3333333 | AG15: =IFERROR(AVERAGE(AC15:AF15)*(K15/MAX(J15:M15)),"") -> 2.4166667 | AH15: =IFERROR(AVERAGE('4a. Scorer 1'!V14,'4b. Scorer 2'!V14,'4c. Scorer 3'!V14)," ") -> 1 | AI15: =IFERROR(AVERAGE('4a. Scorer 1'!W14,'4b. Scorer 2'!W14,'4c. Scorer 3'!W14)," ") -> 3 | AL15: Progressed for business casing
C16: ='4. VAS list'!B10 -> Vehicle Geolocation | D16: =IF('4. VAS list'!C10="","",'4. VAS list'!C10) -> Install an approved GPS tracking device and reduce vehicle insurance premium | E16: =IF('4. VAS list'!G10="","",'4. VAS list'!G10) -> Mobility​ | F16: =IF('4. VAS list'!H10="","",'4. VAS list'!H10) -> Mobility assistance (bikes, fines help)​ | J16: {=_xlfn.IFNA(_xlfn.IFS('4. VAS list'!$I10='1. Master scoring '!$J$10,1,'4. VAS list'!$J10='1. Master scoring '!$J$10,2,'4. VAS list'!$K10='1. Master scoring '!$J$10,3,'4. VAS list'!$L10='1. Master scoring '!$J$10,4),"Completare")} -> 1 | K16: {=_xlfn.IFNA(_xlfn.IFS('4. VAS list'!$I10='1. Master scoring '!$K$10,1,'4. VAS list'!$J10='1. Master scoring '!$K$10,2,'4. VAS list'!$K10='1. Master scoring '!$K$10,3,'4. VAS list'!$L10='1. Master scoring '!$K$10,4),"Completare")} -> 2 | L16: {=_xlfn.IFNA(_xlfn.IFS('4. VAS list'!$I10='1. Master scoring '!$L$10,1,'4. VAS list'!$J10='1. Master scoring '!$L$10,2,'4. VAS list'!$K10='1. Master scoring '!$L$10,3,'4. VAS list'!$L10='1. Master scoring '!$L$10,4),"Completare")} -> 3 | M16: {=_xlfn.IFNA(_xlfn.IFS('4. VAS list'!$I10='1. Master scoring '!$M$10,1,'4. VAS list'!$J10='1. Master scoring '!$M$10,2,'4. VAS list'!$K10='1. Master scoring '!$M$10,3,'4. VAS list'!$L10='1. Master scoring '!$M$10,4),"Completare")} -> 4 | O16: =IFERROR(AVERAGE(R16:W16,X16:X16,Z16:Z16,AC16:AF16),"") -> 3.8731061 | P16: =IFERROR(RANK(O16,$O$14:$O$128,0)+COUNTIF($O$14:O16,#REF!)," ") -> 3 | R16: =IFERROR(AVERAGE('4a. Scorer 1'!F15,'4b. Scorer 2'!F15,'4c. Scorer 3'!F15)," ") -> 5 | S16: =IFERROR(AVERAGE('4a. Scorer 1'!G15,'4b. Scorer 2'!G15,'4c. Scorer 3'!G15)," ") | T16: =IFERROR(AVERAGE('4a. Scorer 1'!H15,'4b. Scorer 2'!H15,'4c. Scorer 3'!H15)," ") -> 2.6666667 | U16: =IFERROR(AVERAGE('4a. Scorer 1'!I15,'4b. Scorer 2'!I15,'4c. Scorer 3'!I15)," ") -> 4.3333333 | V16: =IFERROR(AVERAGE('4a. Scorer 1'!J15,'4b. Scorer 2'!J15,'4c. Scorer 3'!J15)," ") -> 3 | W16: =IFERROR(AVERAGE(R16:V16)*(J16/MAX(J16:M16)),"") -> 0.9375 | X16: =IFERROR(AVERAGE('4a. Scorer 1'!L15,'4b. Scorer 2'!L15,'4c. Scorer 3'!L15)," ") -> 3.6666667 | Y16: =IFERROR(AVERAGE(X16:X16)*(M16/MAX(J16:M16)),"") -> 3.6666667 | Z16: =IFERROR(AVERAGE('4a. Scorer 1'!N15,'4b. Scorer 2'!N15,'4c. Scorer 3'!N15)," ") -> 4.6666667 | AA16: =IFERROR(AVERAGE('4a. Scorer 1'!O15,'4b. Scorer 2'!O15,'4c. Scorer 3'!O15)," ") -> 4.6666667 | AB16: =IFERROR(AVERAGE(Z16:Z16)*(L16/MAX(J16:M16)),"") -> 3.5 | AC16: =IFERROR(AVERAGE('4a. Scorer 1'!Q15,'4b. Scorer 2'!Q15,'4c. Scorer 3'!Q15)," ") -> 4 | AD16: =IFERROR(AVERAGE('4a. Scorer 1'!R15,'4b. Scorer 2'!R15,'4c. Scorer 3'!R15)," ") -> 4.6666667 | AE16: =IFERROR(AVERAGE('4a. Scorer 1'!S15,'4b. Scorer 2'!S15,'4c. Scorer 3'!S15)," ") -> 4.6666667 | AF16: =IFERROR(AVERAGE('4a. Scorer 1'!T15,'4b. Scorer 2'!T15,'4c. Scorer 3'!T15)," ") -> 5 | AG16: =IFERROR(AVERAGE(AC16:AF16)*(K16/MAX(J16:M16)),"") -> 2.2916667 | AH16: =IFERROR(AVERAGE('4a. Scorer 1'!V15,'4b. Scorer 2'!V15,'4c. Scorer 3'!V15)," ") -> 1 | AI16: =IFERROR(AVERAGE('4a. Scorer 1'!W15,'4b. Scorer 2'!W15,'4c. Scorer 3'!W15)," ") -> 3 | AL16: Previously assessed; depriortised based on financial risk/lack of clear upside
C17: ='4. VAS list'!B11 -> Pet Care | D17: =IF('4. VAS list'!C11="","",'4. VAS list'!C11) -> Cover the cost of veterinary fees for illnesses or injuries | E17: =IF('4. VAS list'!G11="","",'4. VAS list'!G11) -> HomeAndFamily​ | F17: =IF('4. VAS list'!H11="","",'4. VAS list'!H11) -> Pet care​ | J17: {=_xlfn.IFNA(_xlfn.IFS('4. VAS list'!$I11='1. Master scoring '!$J$10,1,'4. VAS list'!$J11='1. Master scoring '!$J$10,2,'4. VAS list'!$K11='1. Master scoring '!$J$10,3,'4. VAS list'!$L11='1. Master scoring '!$J$10,4),"")} -> 1 | K17: {=_xlfn.IFNA(_xlfn.IFS('4. VAS list'!$I11='1. Master scoring '!$K$10,1,'4. VAS list'!$J11='1. Master scoring '!$K$10,2,'4. VAS list'!$K11='1. Master scoring '!$K$10,3,'4. VAS list'!$L11='1. Master scoring '!$K$10,4),"Completare")} -> 2 | L17: {=_xlfn.IFNA(_xlfn.IFS('4. VAS list'!$I11='1. Master scoring '!$L$10,1,'4. VAS list'!$J11='1. Master scoring '!$L$10,2,'4. VAS list'!$K11='1. Master scoring '!$L$10,3,'4. VAS list'!$L11='1. Master scoring '!$L$10,4),"Completare")} -> 3 | M17: {=_xlfn.IFNA(_xlfn.IFS('4. VAS list'!$I11='1. Master scoring '!$M$10,1,'4. VAS list'!$J11='1. Master scoring '!$M$10,2,'4. VAS list'!$K11='1. Master scoring '!$M$10,3,'4. VAS list'!$L11='1. Master scoring '!$M$10,4),"Completare")} -> 4 | O17: =IFERROR(AVERAGE(R17:W17,X17:X17,Z17:Z17,AC17:AF17),"") -> 3.7784091 | P17: =IFERROR(RANK(O17,$O$14:$O$128,0)+COUNTIF($O$14:O17,#REF!)," ") -> 4 | R17: =IFERROR(AVERAGE('4a. Scorer 1'!F16,'4b. Scorer 2'!F16,'4c. Scorer 3'!F16)," ") -> 4.6666667 | S17: =IFERROR(AVERAGE('4a. Scorer 1'!G16,'4b. Scorer 2'!G16,'4c. Scorer 3'!G16)," ") | T17: =IFERROR(AVERAGE('4a. Scorer 1'!H16,'4b. Scorer 2'!H16,'4c. Scorer 3'!H16)," ") -> 2.3333333 | U17: =IFERROR(AVERAGE('4a. Scorer 1'!I16,'4b. Scorer 2'!I16,'4c. Scorer 3'!I16)," ") -> 4.3333333 | V17: =IFERROR(AVERAGE('4a. Scorer 1'!J16,'4b. Scorer 2'!J16,'4c. Scorer 3'!J16)," ") -> 3 | W17: =IFERROR(AVERAGE(R17:V17)*(J17/MAX(J17:M17)),"") -> 0.89583333 | X17: =IFERROR(AVERAGE('4a. Scorer 1'!L16,'4b. Scorer 2'!L16,'4c. Scorer 3'!L16)," ") -> 3.3333333 | Y17: =IFERROR(AVERAGE(X17:X17)*(M17/MAX(J17:M17)),"") -> 3.3333333 | Z17: =IFERROR(AVERAGE('4a. Scorer 1'!N16,'4b. Scorer 2'!N16,'4c. Scorer 3'!N16)," ") -> 4 | AA17: =IFERROR(AVERAGE('4a. Scorer 1'!O16,'4b. Scorer 2'!O16,'4c. Scorer 3'!O16)," ") -> 4.3333333 | AB17: =IFERROR(AVERAGE(Z17:Z17)*(L17/MAX(J17:M17)),"") -> 3 | AC17: =IFERROR(AVERAGE('4a. Scorer 1'!Q16,'4b. Scorer 2'!Q16,'4c. Scorer 3'!Q16)," ") -> 5 | AD17: =IFERROR(AVERAGE('4a. Scorer 1'!R16,'4b. Scorer 2'!R16,'4c. Scorer 3'!R16)," ") -> 5 | AE17: =IFERROR(AVERAGE('4a. Scorer 1'!S16,'4b. Scorer 2'!S16,'4c. Scorer 3'!S16)," ") -> 4.6666667 | AF17: =IFERROR(AVERAGE('4a. Scorer 1'!T16,'4b. Scorer 2'!T16,'4c. Scorer 3'!T16)," ") -> 4.3333333 | AG17: =IFERROR(AVERAGE(AC17:AF17)*(K17/MAX(J17:M17)),"") -> 2.375 | AH17: =IFERROR(AVERAGE('4a. Scorer 1'!V16,'4b. Scorer 2'!V16,'4c. Scorer 3'!V16)," ") -> 1 | AI17: =IFERROR(AVERAGE('4a. Scorer 1'!W16,'4b. Scorer 2'!W16,'4c. Scorer 3'!W16)," ") -> 3
C18: ='4. VAS list'!B12 -> Road Assistance | D18: =IF('4. VAS list'!C12="","",'4. VAS list'!C12) -> Lorem ipsum | E18: =IF('4. VAS list'!G12="","",'4. VAS list'!G12) -> Mobility​ | F18: =IF('4. VAS list'!H12="","",'4. VAS list'!H12) -> Emergency response​ | J18: {=_xlfn.IFNA(_xlfn.IFS('4. VAS list'!$I12='1. Master scoring '!$J$10,1,'4. VAS list'!$J12='1. Master scoring '!$J$10,2,'4. VAS list'!$K12='1. Master scoring '!$J$10,3,'4. VAS list'!$L12='1. Master scoring '!$J$10,4),"")} -> 1 | K18: {=_xlfn.IFNA(_xlfn.IFS('4. VAS list'!$I12='1. Master scoring '!$K$10,1,'4. VAS list'!$J12='1. Master scoring '!$K$10,2,'4. VAS list'!$K12='1. Master scoring '!$K$10,3,'4. VAS list'!$L12='1. Master scoring '!$K$10,4),"")} -> 2 | L18: {=_xlfn.IFNA(_xlfn.IFS('4. VAS list'!$I12='1. Master scoring '!$L$10,1,'4. VAS list'!$J12='1. Master scoring '!$L$10,2,'4. VAS list'!$K12='1. Master scoring '!$L$10,3,'4. VAS list'!$L12='1. Master scoring '!$L$10,4),"")} -> 3 | M18: {=_xlfn.IFNA(_xlfn.IFS('4. VAS list'!$I12='1. Master scoring '!$M$10,1,'4. VAS list'!$J12='1. Master scoring '!$M$10,2,'4. VAS list'!$K12='1. Master scoring '!$M$10,3,'4. VAS list'!$L12='1. Master scoring '!$M$10,4),"")} -> 4 | O18: =IFERROR(AVERAGE(R18:W18,X18:X18,Z18:Z18,AC18:AF18),"") -> 3.4734848 | P18: =IFERROR(RANK(O18,$O$14:$O$128,0)+COUNTIF($O$14:O18,#REF!)," ") -> 5 | R18: =IFERROR(AVERAGE('4a. Scorer 1'!F17,'4b. Scorer 2'!F17,'4c. Scorer 3'!F17)," ") -> 4 | S18: =IFERROR(AVERAGE('4a. Scorer 1'!G17,'4b. Scorer 2'!G17,'4c. Scorer 3'!G17)," ") | T18: =IFERROR(AVERAGE('4a. Scorer 1'!H17,'4b. Scorer 2'!H17,'4c. Scorer 3'!H17)," ") -> 2.6666667 | U18: =IFERROR(AVERAGE('4a. Scorer 1'!I17,'4b. Scorer 2'!I17,'4c. Scorer 3'!I17)," ") -> 3.6666667 | V18: =IFERROR(AVERAGE('4a. Scorer 1'!J17,'4b. Scorer 2'!J17,'4c. Scorer 3'!J17)," ") -> 3.6666667 | W18: =IFERROR(AVERAGE(R18:V18)*(J18/MAX(J18:M18)),"") -> 0.875 | X18: =IFERROR(AVERAGE('4a. Scorer 1'!L17,'4b. Scorer 2'!L17,'4c. Scorer 3'!L17)," ") -> 3.6666667 | Y18: =IFERROR(AVERAGE(X18:X18)*(M18/MAX(J18:M18)),"") -> 3.6666667 | Z18: =IFERROR(AVERAGE('4a. Scorer 1'!N17,'4b. Scorer 2'!N17,'4c. Scorer 3'!N17)," ") -> 4.6666667 | AA18: =IFERROR(AVERAGE('4a. Scorer 1'!O17,'4b. Scorer 2'!O17,'4c. Scorer 3'!O17)," ") -> 3.6666667 | AB18: =IFERROR(AVERAGE(Z18:Z18)*(L18/MAX(J18:M18)),"") -> 3.5 | AC18: =IFERROR(AVERAGE('4a. Scorer 1'!Q17,'4b. Scorer 2'!Q17,'4c. Scorer 3'!Q17)," ") -> 4 | AD18: =IFERROR(AVERAGE('4a. Scorer 1'!R17,'4b. Scorer 2'!R17,'4c. Scorer 3'!R17)," ") -> 3.3333333 | AE18: =IFERROR(AVERAGE('4a. Scorer 1'!S17,'4b. Scorer 2'!S17,'4c. Scorer 3'!S17)," ") -> 4.3333333 | AF18: =IFERROR(AVERAGE('4a. Scorer 1'!T17,'4b. Scorer 2'!T17,'4c. Scorer 3'!T17)," ") -> 3.3333333 | AG18: =IFERROR(AVERAGE(AC18:AF18)*(K18/MAX(J18:M18)),"") -> 1.875 | AH18: =IFERROR(AVERAGE('4a. Scorer 1'!V17,'4b. Scorer 2'!V17,'4c. Scorer 3'!V17)," ") -> 1 | AI18: =IFERROR(AVERAGE('4a. Scorer 1'!W17,'4b. Scorer 2'!W17,'4c. Scorer 3'!W17)," ") -> 3
C19: =IF(ISBLANK('4. VAS list'!B13),"",'4. VAS list'!B13) | E19: =IF('4. VAS list'!G13="","",'4. VAS list'!G13) | F19: =IF('4. VAS list'!H13="","",'4. VAS list'!H13) | J19: {=_xlfn.IFNA(_xlfn.IFS('4. VAS list'!$I13='1. Master scoring '!$J$10,1,'4. VAS list'!$J13='1. Master scoring '!$J$10,2,'4. VAS list'!$K13='1. Master scoring '!$J$10,3,'4. VAS list'!$L13='1. Master scoring '!$J$10,4),"")} | K19: {=_xlfn.IFNA(_xlfn.IFS('4. VAS list'!$I13='1. Master scoring '!$K$10,1,'4. VAS list'!$J13='1. Master scoring '!$K$10,2,'4. VAS list'!$K13='1. Master scoring '!$K$10,3,'4. VAS list'!$L13='1. Master scoring '!$K$10,4),"")} | L19: {=_xlfn.IFNA(_xlfn.IFS('4. VAS list'!$I13='1. Master scoring '!$L$10,1,'4. VAS list'!$J13='1. Master scoring '!$L$10,2,'4. VAS list'!$K13='1. Master scoring '!$L$10,3,'4. VAS list'!$L13='1. Master scoring '!$L$10,4),"")} | M19: {=_xlfn.IFNA(_xlfn.IFS('4. VAS list'!$I13='1. Master scoring '!$M$10,1,'4. VAS list'!$J13='1. Master scoring '!$M$10,2,'4. VAS list'!$K13='1. Master scoring '!$M$10,3,'4. VAS list'!$L13='1. Master scoring '!$M$10,4),"")} | O19: =IFERROR(AVERAGE(R19:W19,X19:X19,Z19:Z19,AC19:AF19),"") | P19: =IFERROR(RANK(O19,$O$14:$O$128,0)+COUNTIF($O$14:O19,#REF!)," ") | R19: =IFERROR(AVERAGE('4a. Scorer 1'!F18,'4b. Scorer 2'!F18,'4c. Scorer 3'!F18)," ") | S19: =IFERROR(AVERAGE('4a. Scorer 1'!G18,'4b. Scorer 2'!G18,'4c. Scorer 3'!G18)," ") | T19: =IFERROR(AVERAGE('4a. Scorer 1'!H18,'4b. Scorer 2'!H18,'4c. Scorer 3'!H18)," ") | U19: =IFERROR(AVERAGE('4a. Scorer 1'!I18,'4b. Scorer 2'!I18,'4c. Scorer 3'!I18)," ") | V19: =IFERROR(AVERAGE('4a. Scorer 1'!J18,'4b. Scorer 2'!J18,'4c. Scorer 3'!J18)," ") | W19: =IFERROR(AVERAGE(R19:V19)*(J19/MAX(J19:M19)),"") | X19: =IFERROR(AVERAGE('4a. Scorer 1'!L18,'4b. Scorer 2'!L18,'4c. Scorer 3'!L18)," ") | Y19: =IFERROR(AVERAGE(X19:X19)*(M19/MAX(J19:M19)),"") | Z19: =IFERROR(AVERAGE('4a. Scorer 1'!N18,'4b. Scorer 2'!N18,'4c. Scorer 3'!N18)," ") | AA19: =IFERROR(AVERAGE('4a. Scorer 1'!O18,'4b. Scorer 2'!O18,'4c. Scorer 3'!O18)," ") | AC19: =IFERROR(AVERAGE('4a. Scorer 1'!Q18,'4b. Scorer 2'!Q18,'4c. Scorer 3'!Q18)," ") | AD19: =IFERROR(AVERAGE('4a. Scorer 1'!R18,'4b. Scorer 2'!R18,'4c. Scorer 3'!R18)," ") | AE19: =IFERROR(AVERAGE('4a. Scorer 1'!S18,'4b. Scorer 2'!S18,'4c. Scorer 3'!S18)," ") | AF19: =IFERROR(AVERAGE('4a. Scorer 1'!T18,'4b. Scorer 2'!T18,'4c. Scorer 3'!T18)," ") | AG19: =IFERROR(AVERAGE(AC19:AF19)*(K19/MAX(J19:M19)),"") | AH19: =IFERROR(AVERAGE('4a. Scorer 1'!V18,'4b. Scorer 2'!V18,'4c. Scorer 3'!V18)," ") | AI19: =IFERROR(AVERAGE('4a. Scorer 1'!W18,'4b. Scorer 2'!W18,'4c. Scorer 3'!W18)," ")
C20: =IF(ISBLANK('4. VAS list'!B14),"",'4. VAS list'!B14) | D20: =IF('4. VAS list'!C13="","",'4. VAS list'!C13) | E20: =IF('4. VAS list'!G14="","",'4. VAS list'!G14) | F20: =IF('4. VAS list'!H14="","",'4. VAS list'!H14) | J20: {=_xlfn.IFNA(_xlfn.IFS('4. VAS list'!$I14='1. Master scoring '!$J$10,1,'4. VAS list'!$J14='1. Master scoring '!$J$10,2,'4. VAS list'!$K14='1. Master scoring '!$J$10,3,'4. VAS list'!$L14='1. Master scoring '!$J$10,4),"")} | K20: {=_xlfn.IFNA(_xlfn.IFS('4. VAS list'!$I14='1. Master scoring '!$K$10,1,'4. VAS list'!$J14='1. Master scoring '!$K$10,2,'4. VAS list'!$K14='1. Master scoring '!$K$10,3,'4. VAS list'!$L14='1. Master scoring '!$K$10,4),"")} | L20: {=_xlfn.IFNA(_xlfn.IFS('4. VAS list'!$I14='1. Master scoring '!$L$10,1,'4. VAS list'!$J14='1. Master scoring '!$L$10,2,'4. VAS list'!$K14='1. Master scoring '!$L$10,3,'4. VAS list'!$L14='1. Master scoring '!$L$10,4),"")} | M20: {=_xlfn.IFNA(_xlfn.IFS('4. VAS list'!$I14='1. Master scoring '!$M$10,1,'4. VAS list'!$J14='1. Master scoring '!$M$10,2,'4. VAS list'!$K14='1. Master scoring '!$M$10,3,'4. VAS list'!$L14='1. Master scoring '!$M$10,4),"")} | O20: =IFERROR(AVERAGE(R20:W20,X20:X20,Z20:Z20,AC20:AF20),"") | P20: =IFERROR(RANK(O20,$O$14:$O$128,0)+COUNTIF($O$14:O20,#REF!)," ") | R20: =IFERROR(AVERAGE('4a. Scorer 1'!F19,'4b. Scorer 2'!F19,'4c. Scorer 3'!F19)," ") | S20: =IFERROR(AVERAGE('4a. Scorer 1'!G19,'4b. Scorer 2'!G19,'4c. Scorer 3'!G19)," ") | W20: =IFERROR(AVERAGE(R20:V20)*(J20/MAX(J20:M20)),"") | X20: =IFERROR(AVERAGE('4a. Scorer 1'!L19,'4b. Scorer 2'!L19,'4c. Scorer 3'!L19)," ") | Y20: =IFERROR(AVERAGE(X20:X20)*(M20/MAX(J20:M20)),"") | Z20: =IFERROR(AVERAGE('4a. Scorer 1'!N19,'4b. Scorer 2'!N19,'4c. Scorer 3'!N19)," ") | AA20: =IFERROR(AVERAGE('4a. Scorer 1'!#REF!,'4b. Scorer 2'!#REF!,'4c. Scorer 3'!#REF!)," ") | AF20: =IFERROR(AVERAGE('4a. Scorer 1'!#REF!,'4b. Scorer 2'!S19,'4c. Scorer 3'!S19)," ") | AG20: =IFERROR(AVERAGE(AC20:AF20)*(K20/MAX(J20:M20)),"") | AH20: =IFERROR(AVERAGE('4a. Scorer 1'!V19,'4b. Scorer 2'!V19,'4c. Scorer 3'!V19)," ") | AI20: =IFERROR(AVERAGE('4a. Scorer 1'!W19,'4b. Scorer 2'!W19,'4c. Scorer 3'!W19)," ")
C21: =IF(ISBLANK('4. VAS list'!B15),"",'4. VAS list'!B15) | D21: =IF('4. VAS list'!C15="","",'4. VAS list'!C15) | E21: =IF('4. VAS list'!G15="","",'4. VAS list'!G15) | F21: =IF('4. VAS list'!H15="","",'4. VAS list'!H15) | J21: {=_xlfn.IFNA(_xlfn.IFS('4. VAS list'!$I15='1. Master scoring '!$J$10,1,'4. VAS list'!$J15='1. Master scoring '!$J$10,2,'4. VAS list'!$K15='1. Master scoring '!$J$10,3,'4. VAS list'!$L15='1. Master scoring '!$J$10,4),"")} | K21: {=_xlfn.IFNA(_xlfn.IFS('4. VAS list'!$I15='1. Master scoring '!$K$10,1,'4. VAS list'!$J15='1. Master scoring '!$K$10,2,'4. VAS list'!$K15='1. Master scoring '!$K$10,3,'4. VAS list'!$L15='1. Master scoring '!$K$10,4),"")} | L21: {=_xlfn.IFNA(_xlfn.IFS('4. VAS list'!$I15='1. Master scoring '!$L$10,1,'4. VAS list'!$J15='1. Master scoring '!$L$10,2,'4. VAS list'!$K15='1. Master scoring '!$L$10,3,'4. VAS list'!$L15='1. Master scoring '!$L$10,4),"")} | M21: {=_xlfn.IFNA(_xlfn.IFS('4. VAS list'!$I15='1. Master scoring '!$M$10,1,'4. VAS list'!$J15='1. Master scoring '!$M$10,2,'4. VAS list'!$K15='1. Master scoring '!$M$10,3,'4. VAS list'!$L15='1. Master scoring '!$M$10,4),"")} | O21: =IFERROR(AVERAGE(R21:W21,X21:X21,Z21:Z21,AC21:AF21),"") | P21: =IFERROR(RANK(O21,$O$14:$O$128,0)+COUNTIF($O$14:O21,#REF!)," ") | R21: =IFERROR(AVERAGE('4a. Scorer 1'!F20,'4b. Scorer 2'!F20,'4c. Scorer 3'!F20)," ") | S21: =IFERROR(AVERAGE('4a. Scorer 1'!G20,'4b. Scorer 2'!G20,'4c. Scorer 3'!G20)," ") | W21: =IFERROR(AVERAGE(R21:V21)*(J21/MAX(J21:M21)),"") | X21: =IFERROR(AVERAGE('4a. Scorer 1'!L20,'4b. Scorer 2'!L20,'4c. Scorer 3'!L20)," ") | Y21: =IFERROR(AVERAGE(X21:X21)*(M21/MAX(J21:M21)),"") | Z21: =IFERROR(AVERAGE('4a. Scorer 1'!N20,'4b. Scorer 2'!N20,'4c. Scorer 3'!N20)," ") | AA21: =IFERROR(AVERAGE('4a. Scorer 1'!#REF!,'4b. Scorer 2'!#REF!,'4c. Scorer 3'!#REF!)," ") | AF21: =IFERROR(AVERAGE('4a. Scorer 1'!#REF!,'4b. Scorer 2'!S20,'4c. Scorer 3'!S20)," ") | AG21: =IFERROR(AVERAGE(AC21:AF21)*(K21/MAX(J21:M21)),"") | AH21: =IFERROR(AVERAGE('4a. Scorer 1'!V20,'4b. Scorer 2'!V20,'4c. Scorer 3'!V20)," ") | AI21: =IFERROR(AVERAGE('4a. Scorer 1'!W20,'4b. Scorer 2'!W20,'4c. Scorer 3'!W20)," ")
C22: =IF(ISBLANK('4. VAS list'!B16),"",'4. VAS list'!B16) | D22: =IF('4. VAS list'!C16="","",'4. VAS list'!C16) | E22: =IF('4. VAS list'!G16="","",'4. VAS list'!G16) | F22: =IF('4. VAS list'!H16="","",'4. VAS list'!H16) | J22: {=_xlfn.IFNA(_xlfn.IFS('4. VAS list'!$I16='1. Master scoring '!$J$10,1,'4. VAS list'!$J16='1. Master scoring '!$J$10,2,'4. VAS list'!$K16='1. Master scoring '!$J$10,3,'4. VAS list'!$L16='1. Master scoring '!$J$10,4),"")} | K22: {=_xlfn.IFNA(_xlfn.IFS('4. VAS list'!$I16='1. Master scoring '!$K$10,1,'4. VAS list'!$J16='1. Master scoring '!$K$10,2,'4. VAS list'!$K16='1. Master scoring '!$K$10,3,'4. VAS list'!$L16='1. Master scoring '!$K$10,4),"")} | L22: {=_xlfn.IFNA(_xlfn.IFS('4. VAS list'!$I16='1. Master scoring '!$L$10,1,'4. VAS list'!$J16='1. Master scoring '!$L$10,2,'4. VAS list'!$K16='1. Master scoring '!$L$10,3,'4. VAS list'!$L16='1. Master scoring '!$L$10,4),"")} | M22: {=_xlfn.IFNA(_xlfn.IFS('4. VAS list'!$I16='1. Master scoring '!$M$10,1,'4. VAS list'!$J16='1. Master scoring '!$M$10,2,'4. VAS list'!$K16='1. Master scoring '!$M$10,3,'4. VAS list'!$L16='1. Master scoring '!$M$10,4),"")} | O22: =IFERROR(AVERAGE(R22:W22,X22:X22,Z22:Z22,AC22:AF22),"") | P22: =IFERROR(RANK(O22,$O$14:$O$128,0)+COUNTIF($O$14:O22,#REF!)," ") | R22: =IFERROR(AVERAGE('4a. Scorer 1'!F21,'4b. Scorer 2'!F21,'4c. Scorer 3'!F21)," ") | S22: =IFERROR(AVERAGE('4a. Scorer 1'!G21,'4b. Scorer 2'!G21,'4c. Scorer 3'!G21)," ") | W22: =IFERROR(AVERAGE(R22:V22)*(J22/MAX(J22:M22)),"") | X22: =IFERROR(AVERAGE('4a. Scorer 1'!L21,'4b. Scorer 2'!L21,'4c. Scorer 3'!L21)," ") | Y22: =IFERROR(AVERAGE(X22:X22)*(M22/MAX(J22:M22)),"") | Z22: =IFERROR(AVERAGE('4a. Scorer 1'!N21,'4b. Scorer 2'!N21,'4c. Scorer 3'!N21)," ") | AA22: =IFERROR(AVERAGE('4a. Scorer 1'!#REF!,'4b. Scorer 2'!#REF!,'4c. Scorer 3'!#REF!)," ") | AF22: =IFERROR(AVERAGE('4a. Scorer 1'!#REF!,'4b. Scorer 2'!S21,'4c. Scorer 3'!S21)," ") | AG22: =IFERROR(AVERAGE(AC22:AF22)*(K22/MAX(J22:M22)),"") | AH22: =IFERROR(AVERAGE('4a. Scorer 1'!V21,'4b. Scorer 2'!V21,'4c. Scorer 3'!V21)," ") | AI22: =IFERROR(AVERAGE('4a. Scorer 1'!W21,'4b. Scorer 2'!W21,'4c. Scorer 3'!W21)," ")
C23: =IF(ISBLANK('4. VAS list'!B17),"",'4. VAS list'!B17) | D23: =IF('4. VAS list'!C17="","",'4. VAS list'!C17) | E23: =IF('4. VAS list'!G17="","",'4. VAS list'!G17) | F23: =IF('4. VAS list'!H17="","",'4. VAS list'!H17) | J23: {=_xlfn.IFNA(_xlfn.IFS('4. VAS list'!$I17='1. Master scoring '!$J$10,1,'4. VAS list'!$J17='1. Master scoring '!$J$10,2,'4. VAS list'!$K17='1. Master scoring '!$J$10,3,'4. VAS list'!$L17='1. Master scoring '!$J$10,4),"")} | K23: {=_xlfn.IFNA(_xlfn.IFS('4. VAS list'!$I17='1. Master scoring '!$K$10,1,'4. VAS list'!$J17='1. Master scoring '!$K$10,2,'4. VAS list'!$K17='1. Master scoring '!$K$10,3,'4. VAS list'!$L17='1. Master scoring '!$K$10,4),"")} | L23: {=_xlfn.IFNA(_xlfn.IFS('4. VAS list'!$I17='1. Master scoring '!$L$10,1,'4. VAS list'!$J17='1. Master scoring '!$L$10,2,'4. VAS list'!$K17='1. Master scoring '!$L$10,3,'4. VAS list'!$L17='1. Master scoring '!$L$10,4),"")} | M23: {=_xlfn.IFNA(_xlfn.IFS('4. VAS list'!$I17='1. Master scoring '!$M$10,1,'4. VAS list'!$J17='1. Master scoring '!$M$10,2,'4. VAS list'!$K17='1. Master scoring '!$M$10,3,'4. VAS list'!$L17='1. Master scoring '!$M$10,4),"")} | O23: =IFERROR(AVERAGE(R23:W23,X23:X23,Z23:Z23,AC23:AF23),"") | P23: =IFERROR(RANK(O23,$O$14:$O$128,0)+COUNTIF($O$14:O23,#REF!)," ") | R23: =IFERROR(AVERAGE('4a. Scorer 1'!F22,'4b. Scorer 2'!F22,'4c. Scorer 3'!F22)," ") | S23: =IFERROR(AVERAGE('4a. Scorer 1'!G22,'4b. Scorer 2'!G22,'4c. Scorer 3'!G22)," ") | W23: =IFERROR(AVERAGE(R23:V23)*(J23/MAX(J23:M23)),"") | X23: =IFERROR(AVERAGE('4a. Scorer 1'!L22,'4b. Scorer 2'!L22,'4c. Scorer 3'!L22)," ") | Y23: =IFERROR(AVERAGE(X23:X23)*(M23/MAX(J23:M23)),"") | Z23: =IFERROR(AVERAGE('4a. Scorer 1'!N22,'4b. Scorer 2'!N22,'4c. Scorer 3'!N22)," ") | AA23: =IFERROR(AVERAGE('4a. Scorer 1'!#REF!,'4b. Scorer 2'!#REF!,'4c. Scorer 3'!#REF!)," ") | AF23: =IFERROR(AVERAGE('4a. Scorer 1'!#REF!,'4b. Scorer 2'!S22,'4c. Scorer 3'!S22)," ") | AG23: =IFERROR(AVERAGE(AC23:AF23)*(K23/MAX(J23:M23)),"") | AH23: =IFERROR(AVERAGE('4a. Scorer 1'!V22,'4b. Scorer 2'!V22,'4c. Scorer 3'!V22)," ") | AI23: =IFERROR(AVERAGE('4a. Scorer 1'!W22,'4b. Scorer 2'!W22,'4c. Scorer 3'!W22)," ")
C24: =IF(ISBLANK('4. VAS list'!B18),"",'4. VAS list'!B18) | D24: =IF('4. VAS list'!C18="","",'4. VAS list'!C18) | E24: =IF('4. VAS list'!G18="","",'4. VAS list'!G18) | F24: =IF('4. VAS list'!H18="","",'4. VAS list'!H18) | J24: {=_xlfn.IFNA(_xlfn.IFS('4. VAS list'!$I18='1. Master scoring '!$J$10,1,'4. VAS list'!$J18='1. Master scoring '!$J$10,2,'4. VAS list'!$K18='1. Master scoring '!$J$10,3,'4. VAS list'!$L18='1. Master scoring '!$J$10,4),"")} | K24: {=_xlfn.IFNA(_xlfn.IFS('4. VAS list'!$I18='1. Master scoring '!$K$10,1,'4. VAS list'!$J18='1. Master scoring '!$K$10,2,'4. VAS list'!$K18='1. Master scoring '!$K$10,3,'4. VAS list'!$L18='1. Master scoring '!$K$10,4),"")} | L24: {=_xlfn.IFNA(_xlfn.IFS('4. VAS list'!$I18='1. Master scoring '!$L$10,1,'4. VAS list'!$J18='1. Master scoring '!$L$10,2,'4. VAS list'!$K18='1. Master scoring '!$L$10,3,'4. VAS list'!$L18='1. Master scoring '!$L$10,4),"")} | M24: {=_xlfn.IFNA(_xlfn.IFS('4. VAS list'!$I18='1. Master scoring '!$M$10,1,'4. VAS list'!$J18='1. Master scoring '!$M$10,2,'4. VAS list'!$K18='1. Master scoring '!$M$10,3,'4. VAS list'!$L18='1. Master scoring '!$M$10,4),"")} | O24: =IFERROR(AVERAGE(R24:W24,X24:X24,Z24:Z24,AC24:AF24),"") | P24: =IFERROR(RANK(O24,$O$14:$O$128,0)+COUNTIF($O$14:O24,#REF!)," ") | R24: =IFERROR(AVERAGE('4a. Scorer 1'!F23,'4b. Scorer 2'!F23,'4c. Scorer 3'!F23)," ") | S24: =IFERROR(AVERAGE('4a. Scorer 1'!G23,'4b. Scorer 2'!G23,'4c. Scorer 3'!G23)," ") | W24: =IFERROR(AVERAGE(R24:V24)*(J24/MAX(J24:M24)),"") | X24: =IFERROR(AVERAGE('4a. Scorer 1'!L23,'4b. Scorer 2'!L23,'4c. Scorer 3'!L23)," ") | Y24: =IFERROR(AVERAGE(X24:X24)*(M24/MAX(J24:M24)),"") | Z24: =IFERROR(AVERAGE('4a. Scorer 1'!N23,'4b. Scorer 2'!N23,'4c. Scorer 3'!N23)," ") | AA24: =IFERROR(AVERAGE('4a. Scorer 1'!#REF!,'4b. Scorer 2'!#REF!,'4c. Scorer 3'!#REF!)," ") | AF24: =IFERROR(AVERAGE('4a. Scorer 1'!#REF!,'4b. Scorer 2'!S23,'4c. Scorer 3'!S23)," ") | AG24: =IFERROR(AVERAGE(AC24:AF24)*(K24/MAX(J24:M24)),"") | AH24: =IFERROR(AVERAGE('4a. Scorer 1'!V23,'4b. Scorer 2'!V23,'4c. Scorer 3'!V23)," ") | AI24: =IFERROR(AVERAGE('4a. Scorer 1'!W23,'4b. Scorer 2'!W23,'4c. Scorer 3'!W23)," ")
C25: =IF(ISBLANK('4. VAS list'!B19),"",'4. VAS list'!B19) | D25: =IF('4. VAS list'!C19="","",'4. VAS list'!C19) | E25: =IF('4. VAS list'!G19="","",'4. VAS list'!G19) | F25: =IF('4. VAS list'!H19="","",'4. VAS list'!H19) | J25: {=_xlfn.IFNA(_xlfn.IFS('4. VAS list'!$I19='1. Master scoring '!$J$10,1,'4. VAS list'!$J19='1. Master scoring '!$J$10,2,'4. VAS list'!$K19='1. Master scoring '!$J$10,3,'4. VAS list'!$L19='1. Master scoring '!$J$10,4),"")} | K25: {=_xlfn.IFNA(_xlfn.IFS('4. VAS list'!$I19='1. Master scoring '!$K$10,1,'4. VAS list'!$J19='1. Master scoring '!$K$10,2,'4. VAS list'!$K19='1. Master scoring '!$K$10,3,'4. VAS list'!$L19='1. Master scoring '!$K$10,4),"")} | L25: {=_xlfn.IFNA(_xlfn.IFS('4. VAS list'!$I19='1. Master scoring '!$L$10,1,'4. VAS list'!$J19='1. Master scoring '!$L$10,2,'4. VAS list'!$K19='1. Master scoring '!$L$10,3,'4. VAS list'!$L19='1. Master scoring '!$L$10,4),"")} | M25: {=_xlfn.IFNA(_xlfn.IFS('4. VAS list'!$I19='1. Master scoring '!$M$10,1,'4. VAS list'!$J19='1. Master scoring '!$M$10,2,'4. VAS list'!$K19='1. Master scoring '!$M$10,3,'4. VAS list'!$L19='1. Master scoring '!$M$10,4),"")} | O25: =IFERROR(AVERAGE(R25:W25,X25:X25,Z25:Z25,AC25:AF25),"") | P25: =IFERROR(RANK(O25,$O$14:$O$128,0)+COUNTIF($O$14:O25,#REF!)," ") | R25: =IFERROR(AVERAGE('4a. Scorer 1'!F24,'4b. Scorer 2'!F24,'4c. Scorer 3'!F24)," ") | S25: =IFERROR(AVERAGE('4a. Scorer 1'!G24,'4b. Scorer 2'!G24,'4c. Scorer 3'!G24)," ") | W25: =IFERROR(AVERAGE(R25:V25)*(J25/MAX(J25:M25)),"") | X25: =IFERROR(AVERAGE('4a. Scorer 1'!L24,'4b. Scorer 2'!L24,'4c. Scorer 3'!L24)," ") | Y25: =IFERROR(AVERAGE(X25:X25)*(M25/MAX(J25:M25)),"") | Z25: =IFERROR(AVERAGE('4a. Scorer 1'!N24,'4b. Scorer 2'!N24,'4c. Scorer 3'!N24)," ") | AA25: =IFERROR(AVERAGE('4a. Scorer 1'!#REF!,'4b. Scorer 2'!#REF!,'4c. Scorer 3'!#REF!)," ") | AF25: =IFERROR(AVERAGE('4a. Scorer 1'!#REF!,'4b. Scorer 2'!S24,'4c. Scorer 3'!S24)," ") | AG25: =IFERROR(AVERAGE(AC25:AF25)*(K25/MAX(J25:M25)),"") | AH25: =IFERROR(AVERAGE('4a. Scorer 1'!V24,'4b. Scorer 2'!V24,'4c. Scorer 3'!V24)," ") | AI25: =IFERROR(AVERAGE('4a. Scorer 1'!W24,'4b. Scorer 2'!W24,'4c. Scorer 3'!W24)," ")
C26: =IF(ISBLANK('4. VAS list'!B20),"",'4. VAS list'!B20) | D26: =IF('4. VAS list'!C20="","",'4. VAS list'!C20) | E26: =IF('4. VAS list'!G20="","",'4. VAS list'!G20) | F26: =IF('4. VAS list'!H20="","",'4. VAS list'!H20) | J26: {=_xlfn.IFNA(_xlfn.IFS('4. VAS list'!$I20='1. Master scoring '!$J$10,1,'4. VAS list'!$J20='1. Master scoring '!$J$10,2,'4. VAS list'!$K20='1. Master scoring '!$J$10,3,'4. VAS list'!$L20='1. Master scoring '!$J$10,4),"")} | K26: {=_xlfn.IFNA(_xlfn.IFS('4. VAS list'!$I20='1. Master scoring '!$K$10,1,'4. VAS list'!$J20='1. Master scoring '!$K$10,2,'4. VAS list'!$K20='1. Master scoring '!$K$10,3,'4. VAS list'!$L20='1. Master scoring '!$K$10,4),"")} | L26: {=_xlfn.IFNA(_xlfn.IFS('4. VAS list'!$I20='1. Master scoring '!$L$10,1,'4. VAS list'!$J20='1. Master scoring '!$L$10,2,'4. VAS list'!$K20='1. Master scoring '!$L$10,3,'4. VAS list'!$L20='1. Master scoring '!$L$10,4),"")} | M26: {=_xlfn.IFNA(_xlfn.IFS('4. VAS list'!$I20='1. Master scoring '!$M$10,1,'4. VAS list'!$J20='1. Master scoring '!$M$10,2,'4. VAS list'!$K20='1. Master scoring '!$M$10,3,'4. VAS list'!$L20='1. Master scoring '!$M$10,4),"")} | O26: =IFERROR(AVERAGE(R26:W26,X26:X26,Z26:Z26,AC26:AF26),"") | P26: =IFERROR(RANK(O26,$O$14:$O$128,0)+COUNTIF($O$14:O26,#REF!)," ") | R26: =IFERROR(AVERAGE('4a. Scorer 1'!F25,'4b. Scorer 2'!F25,'4c. Scorer 3'!F25)," ") | S26: =IFERROR(AVERAGE('4a. Scorer 1'!G25,'4b. Scorer 2'!G25,'4c. Scorer 3'!G25)," ") | W26: =IFERROR(AVERAGE(R26:V26)*(J26/MAX(J26:M26)),"") | X26: =IFERROR(AVERAGE('4a. Scorer 1'!L25,'4b. Scorer 2'!L25,'4c. Scorer 3'!L25)," ") | Y26: =IFERROR(AVERAGE(X26:X26)*(M26/MAX(J26:M26)),"") | Z26: =IFERROR(AVERAGE('4a. Scorer 1'!N25,'4b. Scorer 2'!N25,'4c. Scorer 3'!N25)," ") | AA26: =IFERROR(AVERAGE('4a. Scorer 1'!#REF!,'4b. Scorer 2'!#REF!,'4c. Scorer 3'!#REF!)," ") | AF26: =IFERROR(AVERAGE('4a. Scorer 1'!#REF!,'4b. Scorer 2'!S25,'4c. Scorer 3'!S25)," ") | AG26: =IFERROR(AVERAGE(AC26:AF26)*(K26/MAX(J26:M26)),"") | AH26: =IFERROR(AVERAGE('4a. Scorer 1'!V25,'4b. Scorer 2'!V25,'4c. Scorer 3'!V25)," ") | AI26: =IFERROR(AVERAGE('4a. Scorer 1'!W25,'4b. Scorer 2'!W25,'4c. Scorer 3'!W25)," ")
C27: =IF(ISBLANK('4. VAS list'!B21),"",'4. VAS list'!B21) | D27: =IF('4. VAS list'!C21="","",'4. VAS list'!C21) | E27: =IF('4. VAS list'!G21="","",'4. VAS list'!G21) | F27: =IF('4. VAS list'!H21="","",'4. VAS list'!H21) | J27: {=_xlfn.IFNA(_xlfn.IFS('4. VAS list'!$I21='1. Master scoring '!$J$10,1,'4. VAS list'!$J21='1. Master scoring '!$J$10,2,'4. VAS list'!$K21='1. Master scoring '!$J$10,3,'4. VAS list'!$L21='1. Master scoring '!$J$10,4),"")} | K27: {=_xlfn.IFNA(_xlfn.IFS('4. VAS list'!$I21='1. Master scoring '!$K$10,1,'4. VAS list'!$J21='1. Master scoring '!$K$10,2,'4. VAS list'!$K21='1. Master scoring '!$K$10,3,'4. VAS list'!$L21='1. Master scoring '!$K$10,4),"")} | L27: {=_xlfn.IFNA(_xlfn.IFS('4. VAS list'!$I21='1. Master scoring '!$L$10,1,'4. VAS list'!$J21='1. Master scoring '!$L$10,2,'4. VAS list'!$K21='1. Master scoring '!$L$10,3,'4. VAS list'!$L21='1. Master scoring '!$L$10,4),"")} | M27: {=_xlfn.IFNA(_xlfn.IFS('4. VAS list'!$I21='1. Master scoring '!$M$10,1,'4. VAS list'!$J21='1. Master scoring '!$M$10,2,'4. VAS list'!$K21='1. Master scoring '!$M$10,3,'4. VAS list'!$L21='1. Master scoring '!$M$10,4),"")} | O27: =IFERROR(AVERAGE(R27:W27,X27:X27,Z27:Z27,AC27:AF27),"") | P27: =IFERROR(RANK(O27,$O$14:$O$128,0)+COUNTIF($O$14:O27,#REF!)," ") | R27: =IFERROR(AVERAGE('4a. Scorer 1'!F26,'4b. Scorer 2'!F26,'4c. Scorer 3'!F26)," ") | S27: =IFERROR(AVERAGE('4a. Scorer 1'!G26,'4b. Scorer 2'!G26,'4c. Scorer 3'!G26)," ") | W27: =IFERROR(AVERAGE(R27:V27)*(J27/MAX(J27:M27)),"") | X27: =IFERROR(AVERAGE('4a. Scorer 1'!L26,'4b. Scorer 2'!L26,'4c. Scorer 3'!L26)," ") | Y27: =IFERROR(AVERAGE(X27:X27)*(M27/MAX(J27:M27)),"") | Z27: =IFERROR(AVERAGE('4a. Scorer 1'!N26,'4b. Scorer 2'!N26,'4c. Scorer 3'!N26)," ") | AA27: =IFERROR(AVERAGE('4a. Scorer 1'!#REF!,'4b. Scorer 2'!#REF!,'4c. Scorer 3'!#REF!)," ") | AF27: =IFERROR(AVERAGE('4a. Scorer 1'!#REF!,'4b. Scorer 2'!S26,'4c. Scorer 3'!S26)," ") | AG27: =IFERROR(AVERAGE(AC27:AF27)*(K27/MAX(J27:M27)),"") | AH27: =IFERROR(AVERAGE('4a. Scorer 1'!V26,'4b. Scorer 2'!V26,'4c. Scorer 3'!V26)," ") | AI27: =IFERROR(AVERAGE('4a. Scorer 1'!W26,'4b. Scorer 2'!W26,'4c. Scorer 3'!W26)," ")
C28: =IF(ISBLANK('4. VAS list'!B22),"",'4. VAS list'!B22) | D28: =IF('4. VAS list'!C22="","",'4. VAS list'!C22) | E28: =IF('4. VAS list'!G22="","",'4. VAS list'!G22) | F28: =IF('4. VAS list'!H22="","",'4. VAS list'!H22) | J28: {=_xlfn.IFNA(_xlfn.IFS('4. VAS list'!$I22='1. Master scoring '!$J$10,1,'4. VAS list'!$J22='1. Master scoring '!$J$10,2,'4. VAS list'!$K22='1. Master scoring '!$J$10,3,'4. VAS list'!$L22='1. Master scoring '!$J$10,4),"")} | K28: {=_xlfn.IFNA(_xlfn.IFS('4. VAS list'!$I22='1. Master scoring '!$K$10,1,'4. VAS list'!$J22='1. Master scoring '!$K$10,2,'4. VAS list'!$K22='1. Master scoring '!$K$10,3,'4. VAS list'!$L22='1. Master scoring '!$K$10,4),"")} | L28: {=_xlfn.IFNA(_xlfn.IFS('4. VAS list'!$I22='1. Master scoring '!$L$10,1,'4. VAS list'!$J22='1. Master scoring '!$L$10,2,'4. VAS list'!$K22='1. Master scoring '!$L$10,3,'4. VAS list'!$L22='1. Master scoring '!$L$10,4),"")} | M28: {=_xlfn.IFNA(_xlfn.IFS('4. VAS list'!$I22='1. Master scoring '!$M$10,1,'4. VAS list'!$J22='1. Master scoring '!$M$10,2,'4. VAS list'!$K22='1. Master scoring '!$M$10,3,'4. VAS list'!$L22='1. Master scoring '!$M$10,4),"")} | O28: =IFERROR(AVERAGE(R28:W28,X28:X28,Z28:Z28,AC28:AF28),"") | P28: =IFERROR(RANK(O28,$O$14:$O$128,0)+COUNTIF($O$14:O28,#REF!)," ") | R28: =IFERROR(AVERAGE('4a. Scorer 1'!F27,'4b. Scorer 2'!F27,'4c. Scorer 3'!F27)," ") | S28: =IFERROR(AVERAGE('4a. Scorer 1'!G27,'4b. Scorer 2'!G27,'4c. Scorer 3'!G27)," ") | W28: =IFERROR(AVERAGE(R28:V28)*(J28/MAX(J28:M28)),"") | X28: =IFERROR(AVERAGE('4a. Scorer 1'!L27,'4b. Scorer 2'!L27,'4c. Scorer 3'!L27)," ") | Y28: =IFERROR(AVERAGE(X28:X28)*(M28/MAX(J28:M28)),"") | Z28: =IFERROR(AVERAGE('4a. Scorer 1'!N27,'4b. Scorer 2'!N27,'4c. Scorer 3'!N27)," ") | AA28: =IFERROR(AVERAGE('4a. Scorer 1'!#REF!,'4b. Scorer 2'!#REF!,'4c. Scorer 3'!#REF!)," ") | AF28: =IFERROR(AVERAGE('4a. Scorer 1'!#REF!,'4b. Scorer 2'!S27,'4c. Scorer 3'!S27)," ") | AG28: =IFERROR(AVERAGE(AC28:AF28)*(K28/MAX(J28:M28)),"") | AH28: =IFERROR(AVERAGE('4a. Scorer 1'!V27,'4b. Scorer 2'!V27,'4c. Scorer 3'!V27)," ") | AI28: =IFERROR(AVERAGE('4a. Scorer 1'!W27,'4b. Scorer 2'!W27,'4c. Scorer 3'!W27)," ")
C29: =IF(ISBLANK('4. VAS list'!B23),"",'4. VAS list'!B23) | D29: =IF('4. VAS list'!C23="","",'4. VAS list'!C23) | E29: =IF('4. VAS list'!G23="","",'4. VAS list'!G23) | F29: =IF('4. VAS list'!H23="","",'4. VAS list'!H23) | J29: {=_xlfn.IFNA(_xlfn.IFS('4. VAS list'!$I23='1. Master scoring '!$J$10,1,'4. VAS list'!$J23='1. Master scoring '!$J$10,2,'4. VAS list'!$K23='1. Master scoring '!$J$10,3,'4. VAS list'!$L23='1. Master scoring '!$J$10,4),"")} | K29: {=_xlfn.IFNA(_xlfn.IFS('4. VAS list'!$I23='1. Master scoring '!$K$10,1,'4. VAS list'!$J23='1. Master scoring '!$K$10,2,'4. VAS list'!$K23='1. Master scoring '!$K$10,3,'4. VAS list'!$L23='1. Master scoring '!$K$10,4),"")} | L29: {=_xlfn.IFNA(_xlfn.IFS('4. VAS list'!$I23='1. Master scoring '!$L$10,1,'4. VAS list'!$J23='1. Master scoring '!$L$10,2,'4. VAS list'!$K23='1. Master scoring '!$L$10,3,'4. VAS list'!$L23='1. Master scoring '!$L$10,4),"")} | M29: {=_xlfn.IFNA(_xlfn.IFS('4. VAS list'!$I23='1. Master scoring '!$M$10,1,'4. VAS list'!$J23='1. Master scoring '!$M$10,2,'4. VAS list'!$K23='1. Master scoring '!$M$10,3,'4. VAS list'!$L23='1. Master scoring '!$M$10,4),"")} | O29: =IFERROR(AVERAGE(R29:W29,X29:X29,Z29:Z29,AC29:AF29),"") | P29: =IFERROR(RANK(O29,$O$14:$O$128,0)+COUNTIF($O$14:O29,#REF!)," ") | R29: =IFERROR(AVERAGE('4a. Scorer 1'!F28,'4b. Scorer 2'!F28,'4c. Scorer 3'!F28)," ") | S29: =IFERROR(AVERAGE('4a. Scorer 1'!G28,'4b. Scorer 2'!G28,'4c. Scorer 3'!G28)," ") | W29: =IFERROR(AVERAGE(R29:V29)*(J29/MAX(J29:M29)),"") | X29: =IFERROR(AVERAGE('4a. Scorer 1'!L28,'4b. Scorer 2'!L28,'4c. Scorer 3'!L28)," ") | Y29: =IFERROR(AVERAGE(X29:X29)*(M29/MAX(J29:M29)),"") | Z29: =IFERROR(AVERAGE('4a. Scorer 1'!N28,'4b. Scorer 2'!N28,'4c. Scorer 3'!N28)," ") | AA29: =IFERROR(AVERAGE('4a. Scorer 1'!#REF!,'4b. Scorer 2'!#REF!,'4c. Scorer 3'!#REF!)," ") | AF29: =IFERROR(AVERAGE('4a. Scorer 1'!#REF!,'4b. Scorer 2'!S28,'4c. Scorer 3'!S28)," ") | AG29: =IFERROR(AVERAGE(AC29:AF29)*(K29/MAX(J29:M29)),"") | AH29: =IFERROR(AVERAGE('4a. Scorer 1'!V28,'4b. Scorer 2'!V28,'4c. Scorer 3'!V28)," ") | AI29: =IFERROR(AVERAGE('4a. Scorer 1'!W28,'4b. Scorer 2'!W28,'4c. Scorer 3'!W28)," ")
C30: =IF(ISBLANK('4. VAS list'!B24),"",'4. VAS list'!B24) | D30: =IF('4. VAS list'!C24="","",'4. VAS list'!C24) | E30: =IF('4. VAS list'!G24="","",'4. VAS list'!G24) | F30: =IF('4. VAS list'!H24="","",'4. VAS list'!H24) | J30: {=_xlfn.IFNA(_xlfn.IFS('4. VAS list'!$I24='1. Master scoring '!$J$10,1,'4. VAS list'!$J24='1. Master scoring '!$J$10,2,'4. VAS list'!$K24='1. Master scoring '!$J$10,3,'4. VAS list'!$L24='1. Master scoring '!$J$10,4),"")} | K30: {=_xlfn.IFNA(_xlfn.IFS('4. VAS list'!$I24='1. Master scoring '!$K$10,1,'4. VAS list'!$J24='1. Master scoring '!$K$10,2,'4. VAS list'!$K24='1. Master scoring '!$K$10,3,'4. VAS list'!$L24='1. Master scoring '!$K$10,4),"")} | L30: {=_xlfn.IFNA(_xlfn.IFS('4. VAS list'!$I24='1. Master scoring '!$L$10,1,'4. VAS list'!$J24='1. Master scoring '!$L$10,2,'4. VAS list'!$K24='1. Master scoring '!$L$10,3,'4. VAS list'!$L24='1. Master scoring '!$L$10,4),"")} | M30: {=_xlfn.IFNA(_xlfn.IFS('4. VAS list'!$I24='1. Master scoring '!$M$10,1,'4. VAS list'!$J24='1. Master scoring '!$M$10,2,'4. VAS list'!$K24='1. Master scoring '!$M$10,3,'4. VAS list'!$L24='1. Master scoring '!$M$10,4),"")} | O30: =IFERROR(AVERAGE(R30:W30,X30:X30,Z30:Z30,AC30:AF30),"") | P30: =IFERROR(RANK(O30,$O$14:$O$128,0)+COUNTIF($O$14:O30,#REF!)," ") | R30: =IFERROR(AVERAGE('4a. Scorer 1'!F29,'4b. Scorer 2'!F29,'4c. Scorer 3'!F29)," ") | S30: =IFERROR(AVERAGE('4a. Scorer 1'!G29,'4b. Scorer 2'!G29,'4c. Scorer 3'!G29)," ") | W30: =IFERROR(AVERAGE(R30:V30)*(J30/MAX(J30:M30)),"") | X30: =IFERROR(AVERAGE('4a. Scorer 1'!L29,'4b. Scorer 2'!L29,'4c. Scorer 3'!L29)," ") | Y30: =IFERROR(AVERAGE(X30:X30)*(M30/MAX(J30:M30)),"") | Z30: =IFERROR(AVERAGE('4a. Scorer 1'!N29,'4b. Scorer 2'!N29,'4c. Scorer 3'!N29)," ") | AA30: =IFERROR(AVERAGE('4a. Scorer 1'!#REF!,'4b. Scorer 2'!#REF!,'4c. Scorer 3'!#REF!)," ") | AF30: =IFERROR(AVERAGE('4a. Scorer 1'!#REF!,'4b. Scorer 2'!S29,'4c. Scorer 3'!S29)," ") | AG30: =IFERROR(AVERAGE(AC30:AF30)*(K30/MAX(J30:M30)),"") | AI30: =IFERROR(AVERAGE('4a. Scorer 1'!W29,'4b. Scorer 2'!W29,'4c. Scorer 3'!W29)," ")
C31: =IF(ISBLANK('4. VAS list'!B25),"",'4. VAS list'!B25) | D31: =IF('4. VAS list'!C25="","",'4. VAS list'!C25) | E31: =IF('4. VAS list'!G25="","",'4. VAS list'!G25) | F31: =IF('4. VAS list'!H25="","",'4. VAS list'!H25) | J31: {=_xlfn.IFNA(_xlfn.IFS('4. VAS list'!$I25='1. Master scoring '!$J$10,1,'4. VAS list'!$J25='1. Master scoring '!$J$10,2,'4. VAS list'!$K25='1. Master scoring '!$J$10,3,'4. VAS list'!$L25='1. Master scoring '!$J$10,4),"")} | K31: {=_xlfn.IFNA(_xlfn.IFS('4. VAS list'!$I25='1. Master scoring '!$K$10,1,'4. VAS list'!$J25='1. Master scoring '!$K$10,2,'4. VAS list'!$K25='1. Master scoring '!$K$10,3,'4. VAS list'!$L25='1. Master scoring '!$K$10,4),"")} | L31: {=_xlfn.IFNA(_xlfn.IFS('4. VAS list'!$I25='1. Master scoring '!$L$10,1,'4. VAS list'!$J25='1. Master scoring '!$L$10,2,'4. VAS list'!$K25='1. Master scoring '!$L$10,3,'4. VAS list'!$L25='1. Master scoring '!$L$10,4),"")} | M31: {=_xlfn.IFNA(_xlfn.IFS('4. VAS list'!$I25='1. Master scoring '!$M$10,1,'4. VAS list'!$J25='1. Master scoring '!$M$10,2,'4. VAS list'!$K25='1. Master scoring '!$M$10,3,'4. VAS list'!$L25='1. Master scoring '!$M$10,4),"")} | O31: =IFERROR(AVERAGE(R31:W31,X31:X31,Z31:Z31,AC31:AF31),"") | P31: =IFERROR(RANK(O31,$O$14:$O$128,0)+COUNTIF($O$14:O31,#REF!)," ") | R31: =IFERROR(AVERAGE('4a. Scorer 1'!F30,'4b. Scorer 2'!F30,'4c. Scorer 3'!F30)," ") | S31: =IFERROR(AVERAGE('4a. Scorer 1'!G30,'4b. Scorer 2'!G30,'4c. Scorer 3'!G30)," ") | W31: =IFERROR(AVERAGE(R31:V31)*(J31/MAX(J31:M31)),"") | X31: =IFERROR(AVERAGE('4a. Scorer 1'!L30,'4b. Scorer 2'!L30,'4c. Scorer 3'!L30)," ") | Y31: =IFERROR(AVERAGE(X31:X31)*(M31/MAX(J31:M31)),"") | Z31: =IFERROR(AVERAGE('4a. Scorer 1'!N30,'4b. Scorer 2'!N30,'4c. Scorer 3'!N30)," ") | AA31: =IFERROR(AVERAGE('4a. Scorer 1'!#REF!,'4b. Scorer 2'!#REF!,'4c. Scorer 3'!#REF!)," ") | AF31: =IFERROR(AVERAGE('4a. Scorer 1'!#REF!,'4b. Scorer 2'!S30,'4c. Scorer 3'!S30)," ") | AG31: =IFERROR(AVERAGE(AC31:AF31)*(K31/MAX(J31:M31)),"") | AI31: =IFERROR(AVERAGE('4a. Scorer 1'!W30,'4b. Scorer 2'!W30,'4c. Scorer 3'!W30)," ")
D32: =IF('4. VAS list'!C26="","",'4. VAS list'!C26) | E32: =IF('4. VAS list'!G26="","",'4. VAS list'!G26) | F32: =IF('4. VAS list'!H26="","",'4. VAS list'!H26) | J32: {=_xlfn.IFNA(_xlfn.IFS('4. VAS list'!$I26='1. Master scoring '!$J$10,1,'4. VAS list'!$J26='1. Master scoring '!$J$10,2,'4. VAS list'!$K26='1. Master scoring '!$J$10,3,'4. VAS list'!$L26='1. Master scoring '!$J$10,4),"")} | M32: {=_xlfn.IFNA(_xlfn.IFS('4. VAS list'!$I26='1. Master scoring '!$M$10,1,'4. VAS list'!$J26='1. Master scoring '!$M$10,2,'4. VAS list'!$K26='1. Master scoring '!$M$10,3,'4. VAS list'!$L26='1. Master scoring '!$M$10,4),"")}
D33: =IF('4. VAS list'!C27="","",'4. VAS list'!C27) | E33: =IF('4. VAS list'!G27="","",'4. VAS list'!G27) | F33: =IF('4. VAS list'!H27="","",'4. VAS list'!H27)
D34: =IF('4. VAS list'!C28="","",'4. VAS list'!C28) | E34: =IF('4. VAS list'!G28="","",'4. VAS list'!G28) | F34: =IF('4. VAS list'!H28="","",'4. VAS list'!H28)
D35: =IF('4. VAS list'!C29="","",'4. VAS list'!C29) | E35: =IF('4. VAS list'!G29="","",'4. VAS list'!G29) | F35: =IF('4. VAS list'!H29="","",'4. VAS list'!H29)
D36: =IF('4. VAS list'!C30="","",'4. VAS list'!C30) | E36: =IF('4. VAS list'!G30="","",'4. VAS list'!G30) | F36: =IF('4. VAS list'!H30="","",'4. VAS list'!H30)
D37: =IF('4. VAS list'!C31="","",'4. VAS list'!C31) | E37: =IF('4. VAS list'!G31="","",'4. VAS list'!G31) | F37: =IF('4. VAS list'!H31="","",'4. VAS list'!H31)
D38: =IF('4. VAS list'!C32="","",'4. VAS list'!C32) | E38: =IF('4. VAS list'!G32="","",'4. VAS list'!G32) | F38: =IF('4. VAS list'!H32="","",'4. VAS list'!H32)
D39: =IF('4. VAS list'!C33="","",'4. VAS list'!C33) | E39: =IF('4. VAS list'!G33="","",'4. VAS list'!G33) | F39: =IF('4. VAS list'!H33="","",'4. VAS list'!H33)
D40: =IF('4. VAS list'!C34="","",'4. VAS list'!C34) | E40: =IF('4. VAS list'!G34="","",'4. VAS list'!G34) | F40: =IF('4. VAS list'!H34="","",'4. VAS list'!H34)
D41: =IF('4. VAS list'!C35="","",'4. VAS list'!C35) | E41: =IF('4. VAS list'!G35="","",'4. VAS list'!G35) | F41: =IF('4. VAS list'!H35="","",'4. VAS list'!H35)
D42: =IF('4. VAS list'!C36="","",'4. VAS list'!C36) | E42: =IF('4. VAS list'!G36="","",'4. VAS list'!G36) | F42: =IF('4. VAS list'!H36="","",'4. VAS list'!H36)
D43: =IF('4. VAS list'!C37="","",'4. VAS list'!C37) | E43: =IF('4. VAS list'!G37="","",'4. VAS list'!G37) | F43: =IF('4. VAS list'!H37="","",'4. VAS list'!H37)
D44: =IF('4. VAS list'!C38="","",'4. VAS list'!C38) | E44: =IF('4. VAS list'!G38="","",'4. VAS list'!G38) | F44: =IF('4. VAS list'!H38="","",'4. VAS list'!H38)
D45: =IF('4. VAS list'!C39="","",'4. VAS list'!C39) | E45: =IF('4. VAS list'!G39="","",'4. VAS list'!G39) | F45: =IF('4. VAS list'!H39="","",'4. VAS list'!H39)
L73: =IF(G73="","",IF(AND(G73="Quick win",W74>'7. Scoring criteria'!$C$45,AG73>'7. Scoring criteria'!$F$45),"Yes",IF(AND(G73="Big bet",W73>'7. Scoring criteria'!$C$46,Y73>'7. Scoring criteria'!$D$46),"Yes",IF(AND(G73="Big bet",W73>'7. Scoring criteria'!$C$46,AB73>'7. Scoring criteria'!$E$46),"Yes",IF(AND(G73="Long shot",Y73>'7. Scoring criteria'!$D$47,AB73>'7. Scoring criteria'!$E$47),"Yes","No"))))) | O73: =IFERROR(AVERAGE(R73:W73,X73:X73,Z73:Z73,AC73:AF73),"") | P73: =IFERROR(RANK(O73,$O$14:$O$128,0)+COUNTIF($O$14:O73,#REF!)," ") | R73: =IFERROR(AVERAGE('4a. Scorer 1'!F72,'4b. Scorer 2'!F72,'4c. Scorer 3'!F72)," ") | W73: =IFERROR(AVERAGE(T73:V73),"") | X73: =IFERROR(AVERAGE('4a. Scorer 1'!#REF!,'4b. Scorer 2'!M72,'4c. Scorer 3'!#REF!)," ") | Y73: =IFERROR(AVERAGE(X73:X73),"") | Z73: =IFERROR(AVERAGE('4a. Scorer 1'!N72,'4b. Scorer 2'!N72,'4c. Scorer 3'!N72)," ") | AA73: =IFERROR(AVERAGE('4a. Scorer 1'!#REF!,'4b. Scorer 2'!#REF!,'4c. Scorer 3'!#REF!)," ") | AB73: =IFERROR(AVERAGE(Z73:Z73),"") | AF73: =IFERROR(AVERAGE('4a. Scorer 1'!#REF!,'4b. Scorer 2'!S72,'4c. Scorer 3'!S72)," ") | AG73: =IFERROR(AVERAGE(AC73:AF73),"")
L74: =IF(G74="","",IF(AND(G74="Quick win",W75>'7. Scoring criteria'!$C$45,AG74>'7. Scoring criteria'!$F$45),"Yes",IF(AND(G74="Big bet",W74>'7. Scoring criteria'!$C$46,Y74>'7. Scoring criteria'!$D$46),"Yes",IF(AND(G74="Big bet",W74>'7. Scoring criteria'!$C$46,AB74>'7. Scoring criteria'!$E$46),"Yes",IF(AND(G74="Long shot",Y74>'7. Scoring criteria'!$D$47,AB74>'7. Scoring criteria'!$E$47),"Yes","No"))))) | O74: =IFERROR(AVERAGE(R74:W74,X74:X74,Z74:Z74,AC74:AF74),"") | P74: =IFERROR(RANK(O74,$O$14:$O$128,0)+COUNTIF($O$14:O74,#REF!)," ") | R74: =IFERROR(AVERAGE('4a. Scorer 1'!F73,'4b. Scorer 2'!F73,'4c. Scorer 3'!F73)," ") | W74: =IFERROR(AVERAGE(T74:V74),"") | X74: =IFERROR(AVERAGE('4a. Scorer 1'!#REF!,'4b. Scorer 2'!M73,'4c. Scorer 3'!#REF!)," ") | Y74: =IFERROR(AVERAGE(X74:X74),"") | Z74: =IFERROR(AVERAGE('4a. Scorer 1'!N73,'4b. Scorer 2'!N73,'4c. Scorer 3'!N73)," ") | AA74: =IFERROR(AVERAGE('4a. Scorer 1'!#REF!,'4b. Scorer 2'!#REF!,'4c. Scorer 3'!#REF!)," ") | AB74: =IFERROR(AVERAGE(Z74:Z74),"") | AF74: =IFERROR(AVERAGE('4a. Scorer 1'!#REF!,'4b. Scorer 2'!S73,'4c. Scorer 3'!S73)," ") | AG74: =IFERROR(AVERAGE(AC74:AF74),"")
L75: =IF(G75="","",IF(AND(G75="Quick win",W76>'7. Scoring criteria'!$C$45,AG75>'7. Scoring criteria'!$F$45),"Yes",IF(AND(G75="Big bet",W75>'7. Scoring criteria'!$C$46,Y75>'7. Scoring criteria'!$D$46),"Yes",IF(AND(G75="Big bet",W75>'7. Scoring criteria'!$C$46,AB75>'7. Scoring criteria'!$E$46),"Yes",IF(AND(G75="Long shot",Y75>'7. Scoring criteria'!$D$47,AB75>'7. Scoring criteria'!$E$47),"Yes","No"))))) | O75: =IFERROR(AVERAGE(R75:W75,X75:X75,Z75:Z75,AC75:AF75),"") | P75: =IFERROR(RANK(O75,$O$14:$O$128,0)+COUNTIF($O$14:O75,#REF!)," ") | R75: =IFERROR(AVERAGE('4a. Scorer 1'!F74,'4b. Scorer 2'!F74,'4c. Scorer 3'!F74)," ") | W75: =IFERROR(AVERAGE(T75:V75),"") | X75: =IFERROR(AVERAGE('4a. Scorer 1'!#REF!,'4b. Scorer 2'!M74,'4c. Scorer 3'!#REF!)," ") | Y75: =IFERROR(AVERAGE(X75:X75),"") | Z75: =IFERROR(AVERAGE('4a. Scorer 1'!N74,'4b. Scorer 2'!N74,'4c. Scorer 3'!N74)," ") | AA75: =IFERROR(AVERAGE('4a. Scorer 1'!#REF!,'4b. Scorer 2'!#REF!,'4c. Scorer 3'!#REF!)," ") | AB75: =IFERROR(AVERAGE(Z75:Z75),"") | AF75: =IFERROR(AVERAGE('4a. Scorer 1'!#REF!,'4b. Scorer 2'!S74,'4c. Scorer 3'!S74)," ") | AG75: =IFERROR(AVERAGE(AC75:AF75),"")
L76: =IF(G76="","",IF(AND(G76="Quick win",W77>'7. Scoring criteria'!$C$45,AG76>'7. Scoring criteria'!$F$45),"Yes",IF(AND(G76="Big bet",W76>'7. Scoring criteria'!$C$46,Y76>'7. Scoring criteria'!$D$46),"Yes",IF(AND(G76="Big bet",W76>'7. Scoring criteria'!$C$46,AB76>'7. Scoring criteria'!$E$46),"Yes",IF(AND(G76="Long shot",Y76>'7. Scoring criteria'!$D$47,AB76>'7. Scoring criteria'!$E$47),"Yes","No"))))) | O76: =IFERROR(AVERAGE(R76:W76,X76:X76,Z76:Z76,AC76:AF76),"") | P76: =IFERROR(RANK(O76,$O$14:$O$128,0)+COUNTIF($O$14:O76,#REF!)," ") | R76: =IFERROR(AVERAGE('4a. Scorer 1'!F75,'4b. Scorer 2'!F75,'4c. Scorer 3'!F75)," ") | W76: =IFERROR(AVERAGE(T76:V76),"") | X76: =IFERROR(AVERAGE('4a. Scorer 1'!#REF!,'4b. Scorer 2'!M75,'4c. Scorer 3'!#REF!)," ") | Y76: =IFERROR(AVERAGE(X76:X76),"") | Z76: =IFERROR(AVERAGE('4a. Scorer 1'!N75,'4b. Scorer 2'!N75,'4c. Scorer 3'!N75)," ") | AA76: =IFERROR(AVERAGE('4a. Scorer 1'!#REF!,'4b. Scorer 2'!#REF!,'4c. Scorer 3'!#REF!)," ") | AB76: =IFERROR(AVERAGE(Z76:Z76),"") | AF76: =IFERROR(AVERAGE('4a. Scorer 1'!#REF!,'4b. Scorer 2'!S75,'4c. Scorer 3'!S75)," ") | AG76: =IFERROR(AVERAGE(AC76:AF76),"")
L77: =IF(G77="","",IF(AND(G77="Quick win",W78>'7. Scoring criteria'!$C$45,AG77>'7. Scoring criteria'!$F$45),"Yes",IF(AND(G77="Big bet",W77>'7. Scoring criteria'!$C$46,Y77>'7. Scoring criteria'!$D$46),"Yes",IF(AND(G77="Big bet",W77>'7. Scoring criteria'!$C$46,AB77>'7. Scoring criteria'!$E$46),"Yes",IF(AND(G77="Long shot",Y77>'7. Scoring criteria'!$D$47,AB77>'7. Scoring criteria'!$E$47),"Yes","No"))))) | O77: =IFERROR(AVERAGE(R77:W77,X77:X77,Z77:Z77,AC77:AF77),"") | P77: =IFERROR(RANK(O77,$O$14:$O$128,0)+COUNTIF($O$14:O77,#REF!)," ") | R77: =IFERROR(AVERAGE('4a. Scorer 1'!F76,'4b. Scorer 2'!F76,'4c. Scorer 3'!F76)," ") | W77: =IFERROR(AVERAGE(T77:V77),"") | X77: =IFERROR(AVERAGE('4a. Scorer 1'!#REF!,'4b. Scorer 2'!M76,'4c. Scorer 3'!#REF!)," ") | Y77: =IFERROR(AVERAGE(X77:X77),"") | Z77: =IFERROR(AVERAGE('4a. Scorer 1'!N76,'4b. Scorer 2'!N76,'4c. Scorer 3'!N76)," ") | AA77: =IFERROR(AVERAGE('4a. Scorer 1'!#REF!,'4b. Scorer 2'!#REF!,'4c. Scorer 3'!#REF!)," ") | AB77: =IFERROR(AVERAGE(Z77:Z77),"") | AF77: =IFERROR(AVERAGE('4a. Scorer 1'!#REF!,'4b. Scorer 2'!S76,'4c. Scorer 3'!S76)," ") | AG77: =IFERROR(AVERAGE(AC77:AF77),"")
L78: =IF(G78="","",IF(AND(G78="Quick win",W79>'7. Scoring criteria'!$C$45,AG78>'7. Scoring criteria'!$F$45),"Yes",IF(AND(G78="Big bet",W78>'7. Scoring criteria'!$C$46,Y78>'7. Scoring criteria'!$D$46),"Yes",IF(AND(G78="Big bet",W78>'7. Scoring criteria'!$C$46,AB78>'7. Scoring criteria'!$E$46),"Yes",IF(AND(G78="Long shot",Y78>'7. Scoring criteria'!$D$47,AB78>'7. Scoring criteria'!$E$47),"Yes","No"))))) | O78: =IFERROR(AVERAGE(R78:W78,X78:X78,Z78:Z78,AC78:AF78),"") | P78: =IFERROR(RANK(O78,$O$14:$O$128,0)+COUNTIF($O$14:O78,#REF!)," ") | R78: =IFERROR(AVERAGE('4a. Scorer 1'!F77,'4b. Scorer 2'!F77,'4c. Scorer 3'!F77)," ") | W78: =IFERROR(AVERAGE(T78:V78),"") | X78: =IFERROR(AVERAGE('4a. Scorer 1'!#REF!,'4b. Scorer 2'!M77,'4c. Scorer 3'!#REF!)," ") | Y78: =IFERROR(AVERAGE(X78:X78),"") | Z78: =IFERROR(AVERAGE('4a. Scorer 1'!N77,'4b. Scorer 2'!N77,'4c. Scorer 3'!N77)," ") | AA78: =IFERROR(AVERAGE('4a. Scorer 1'!#REF!,'4b. Scorer 2'!#REF!,'4c. Scorer 3'!#REF!)," ") | AB78: =IFERROR(AVERAGE(Z78:Z78),"") | AF78: =IFERROR(AVERAGE('4a. Scorer 1'!#REF!,'4b. Scorer 2'!S77,'4c. Scorer 3'!S77)," ") | AG78: =IFERROR(AVERAGE(AC78:AF78),"")
L79: =IF(G79="","",IF(AND(G79="Quick win",W80>'7. Scoring criteria'!$C$45,AG79>'7. Scoring criteria'!$F$45),"Yes",IF(AND(G79="Big bet",W79>'7. Scoring criteria'!$C$46,Y79>'7. Scoring criteria'!$D$46),"Yes",IF(AND(G79="Big bet",W79>'7. Scoring criteria'!$C$46,AB79>'7. Scoring criteria'!$E$46),"Yes",IF(AND(G79="Long shot",Y79>'7. Scoring criteria'!$D$47,AB79>'7. Scoring criteria'!$E$47),"Yes","No"))))) | O79: =IFERROR(AVERAGE(R79:W79,X79:X79,Z79:Z79,AC79:AF79),"") | P79: =IFERROR(RANK(O79,$O$14:$O$128,0)+COUNTIF($O$14:O79,#REF!)," ") | R79: =IFERROR(AVERAGE('4a. Scorer 1'!F78,'4b. Scorer 2'!F78,'4c. Scorer 3'!F78)," ") | W79: =IFERROR(AVERAGE(T79:V79),"") | X79: =IFERROR(AVERAGE('4a. Scorer 1'!#REF!,'4b. Scorer 2'!M78,'4c. Scorer 3'!#REF!)," ") | Y79: =IFERROR(AVERAGE(X79:X79),"") | Z79: =IFERROR(AVERAGE('4a. Scorer 1'!N78,'4b. Scorer 2'!N78,'4c. Scorer 3'!N78)," ") | AA79: =IFERROR(AVERAGE('4a. Scorer 1'!#REF!,'4b. Scorer 2'!#REF!,'4c. Scorer 3'!#REF!)," ") | AB79: =IFERROR(AVERAGE(Z79:Z79),"") | AF79: =IFERROR(AVERAGE('4a. Scorer 1'!#REF!,'4b. Scorer 2'!S78,'4c. Scorer 3'!S78)," ") | AG79: =IFERROR(AVERAGE(AC79:AF79),"")
L80: =IF(G80="","",IF(AND(G80="Quick win",W81>'7. Scoring criteria'!$C$45,AG80>'7. Scoring criteria'!$F$45),"Yes",IF(AND(G80="Big bet",W80>'7. Scoring criteria'!$C$46,Y80>'7. Scoring criteria'!$D$46),"Yes",IF(AND(G80="Big bet",W80>'7. Scoring criteria'!$C$46,AB80>'7. Scoring criteria'!$E$46),"Yes",IF(AND(G80="Long shot",Y80>'7. Scoring criteria'!$D$47,AB80>'7. Scoring criteria'!$E$47),"Yes","No"))))) | O80: =IFERROR(AVERAGE(R80:W80,X80:X80,Z80:Z80,AC80:AF80),"") | P80: =IFERROR(RANK(O80,$O$14:$O$128,0)+COUNTIF($O$14:O80,#REF!)," ") | R80: =IFERROR(AVERAGE('4a. Scorer 1'!F79,'4b. Scorer 2'!F79,'4c. Scorer 3'!F79)," ") | W80: =IFERROR(AVERAGE(T80:V80),"") | X80: =IFERROR(AVERAGE('4a. Scorer 1'!#REF!,'4b. Scorer 2'!M79,'4c. Scorer 3'!#REF!)," ") | Y80: =IFERROR(AVERAGE(X80:X80),"") | Z80: =IFERROR(AVERAGE('4a. Scorer 1'!N79,'4b. Scorer 2'!N79,'4c. Scorer 3'!N79)," ") | AA80: =IFERROR(AVERAGE('4a. Scorer 1'!#REF!,'4b. Scorer 2'!#REF!,'4c. Scorer 3'!#REF!)," ") | AB80: =IFERROR(AVERAGE(Z80:Z80),"") | AF80: =IFERROR(AVERAGE('4a. Scorer 1'!#REF!,'4b. Scorer 2'!S79,'4c. Scorer 3'!S79)," ") | AG80: =IFERROR(AVERAGE(AC80:AF80),"")
L81: =IF(G81="","",IF(AND(G81="Quick win",W82>'7. Scoring criteria'!$C$45,AG81>'7. Scoring criteria'!$F$45),"Yes",IF(AND(G81="Big bet",W81>'7. Scoring criteria'!$C$46,Y81>'7. Scoring criteria'!$D$46),"Yes",IF(AND(G81="Big bet",W81>'7. Scoring criteria'!$C$46,AB81>'7. Scoring criteria'!$E$46),"Yes",IF(AND(G81="Long shot",Y81>'7. Scoring criteria'!$D$47,AB81>'7. Scoring criteria'!$E$47),"Yes","No"))))) | O81: =IFERROR(AVERAGE(R81:W81,X81:X81,Z81:Z81,AC81:AF81),"") | P81: =IFERROR(RANK(O81,$O$14:$O$128,0)+COUNTIF($O$14:O81,#REF!)," ") | R81: =IFERROR(AVERAGE('4a. Scorer 1'!F80,'4b. Scorer 2'!F80,'4c. Scorer 3'!F80)," ") | W81: =IFERROR(AVERAGE(T81:V81),"") | X81: =IFERROR(AVERAGE('4a. Scorer 1'!#REF!,'4b. Scorer 2'!M80,'4c. Scorer 3'!#REF!)," ") | Y81: =IFERROR(AVERAGE(X81:X81),"") | Z81: =IFERROR(AVERAGE('4a. Scorer 1'!N80,'4b. Scorer 2'!N80,'4c. Scorer 3'!N80)," ") | AA81: =IFERROR(AVERAGE('4a. Scorer 1'!#REF!,'4b. Scorer 2'!#REF!,'4c. Scorer 3'!#REF!)," ") | AB81: =IFERROR(AVERAGE(Z81:Z81),"") | AF81: =IFERROR(AVERAGE('4a. Scorer 1'!#REF!,'4b. Scorer 2'!S80,'4c. Scorer 3'!S80)," ") | AG81: =IFERROR(AVERAGE(AC81:AF81),"")
L82: =IF(G82="","",IF(AND(G82="Quick win",W83>'7. Scoring criteria'!$C$45,AG82>'7. Scoring criteria'!$F$45),"Yes",IF(AND(G82="Big bet",W82>'7. Scoring criteria'!$C$46,Y82>'7. Scoring criteria'!$D$46),"Yes",IF(AND(G82="Big bet",W82>'7. Scoring criteria'!$C$46,AB82>'7. Scoring criteria'!$E$46),"Yes",IF(AND(G82="Long shot",Y82>'7. Scoring criteria'!$D$47,AB82>'7. Scoring criteria'!$E$47),"Yes","No"))))) | O82: =IFERROR(AVERAGE(R82:W82,X82:X82,Z82:Z82,AC82:AF82),"") | P82: =IFERROR(RANK(O82,$O$14:$O$128,0)+COUNTIF($O$14:O82,#REF!)," ") | R82: =IFERROR(AVERAGE('4a. Scorer 1'!F81,'4b. Scorer 2'!F81,'4c. Scorer 3'!F81)," ") | W82: =IFERROR(AVERAGE(T82:V82),"") | X82: =IFERROR(AVERAGE('4a. Scorer 1'!#REF!,'4b. Scorer 2'!M81,'4c. Scorer 3'!#REF!)," ") | Y82: =IFERROR(AVERAGE(X82:X82),"") | Z82: =IFERROR(AVERAGE('4a. Scorer 1'!N81,'4b. Scorer 2'!N81,'4c. Scorer 3'!N81)," ") | AA82: =IFERROR(AVERAGE('4a. Scorer 1'!#REF!,'4b. Scorer 2'!#REF!,'4c. Scorer 3'!#REF!)," ") | AB82: =IFERROR(AVERAGE(Z82:Z82),"") | AF82: =IFERROR(AVERAGE('4a. Scorer 1'!#REF!,'4b. Scorer 2'!S81,'4c. Scorer 3'!S81)," ") | AG82: =IFERROR(AVERAGE(AC82:AF82),"")
L83: =IF(G83="","",IF(AND(G83="Quick win",W84>'7. Scoring criteria'!$C$45,AG83>'7. Scoring criteria'!$F$45),"Yes",IF(AND(G83="Big bet",W83>'7. Scoring criteria'!$C$46,Y83>'7. Scoring criteria'!$D$46),"Yes",IF(AND(G83="Big bet",W83>'7. Scoring criteria'!$C$46,AB83>'7. Scoring criteria'!$E$46),"Yes",IF(AND(G83="Long shot",Y83>'7. Scoring criteria'!$D$47,AB83>'7. Scoring criteria'!$E$47),"Yes","No"))))) | O83: =IFERROR(AVERAGE(R83:W83,X83:X83,Z83:Z83,AC83:AF83),"") | P83: =IFERROR(RANK(O83,$O$14:$O$128,0)+COUNTIF($O$14:O83,#REF!)," ") | R83: =IFERROR(AVERAGE('4a. Scorer 1'!F82,'4b. Scorer 2'!F82,'4c. Scorer 3'!F82)," ") | W83: =IFERROR(AVERAGE(T83:V83),"") | X83: =IFERROR(AVERAGE('4a. Scorer 1'!#REF!,'4b. Scorer 2'!M82,'4c. Scorer 3'!#REF!)," ") | Y83: =IFERROR(AVERAGE(X83:X83),"") | Z83: =IFERROR(AVERAGE('4a. Scorer 1'!N82,'4b. Scorer 2'!N82,'4c. Scorer 3'!N82)," ") | AA83: =IFERROR(AVERAGE('4a. Scorer 1'!#REF!,'4b. Scorer 2'!#REF!,'4c. Scorer 3'!#REF!)," ") | AB83: =IFERROR(AVERAGE(Z83:Z83),"") | AF83: =IFERROR(AVERAGE('4a. Scorer 1'!#REF!,'4b. Scorer 2'!S82,'4c. Scorer 3'!S82)," ") | AG83: =IFERROR(AVERAGE(AC83:AF83),"")
L84: =IF(G84="","",IF(AND(G84="Quick win",W85>'7. Scoring criteria'!$C$45,AG84>'7. Scoring criteria'!$F$45),"Yes",IF(AND(G84="Big bet",W84>'7. Scoring criteria'!$C$46,Y84>'7. Scoring criteria'!$D$46),"Yes",IF(AND(G84="Big bet",W84>'7. Scoring criteria'!$C$46,AB84>'7. Scoring criteria'!$E$46),"Yes",IF(AND(G84="Long shot",Y84>'7. Scoring criteria'!$D$47,AB84>'7. Scoring criteria'!$E$47),"Yes","No"))))) | O84: =IFERROR(AVERAGE(R84:W84,X84:X84,Z84:Z84,AC84:AF84),"") | P84: =IFERROR(RANK(O84,$O$14:$O$128,0)+COUNTIF($O$14:O84,#REF!)," ") | R84: =IFERROR(AVERAGE('4a. Scorer 1'!F83,'4b. Scorer 2'!F83,'4c. Scorer 3'!F83)," ") | W84: =IFERROR(AVERAGE(T84:V84),"") | X84: =IFERROR(AVERAGE('4a. Scorer 1'!#REF!,'4b. Scorer 2'!M83,'4c. Scorer 3'!#REF!)," ") | Y84: =IFERROR(AVERAGE(X84:X84),"") | Z84: =IFERROR(AVERAGE('4a. Scorer 1'!N83,'4b. Scorer 2'!N83,'4c. Scorer 3'!N83)," ") | AA84: =IFERROR(AVERAGE('4a. Scorer 1'!#REF!,'4b. Scorer 2'!#REF!,'4c. Scorer 3'!#REF!)," ") | AB84: =IFERROR(AVERAGE(Z84:Z84),"") | AF84: =IFERROR(AVERAGE('4a. Scorer 1'!#REF!,'4b. Scorer 2'!S83,'4c. Scorer 3'!S83)," ") | AG84: =IFERROR(AVERAGE(AC84:AF84),"")
... L86: =IF(G86="","",IF(AND(G86="Quick win",W87>'7. Scoring criteria'!$C$45,AG86>'7. Scoring criteria'!$F$45),"Yes",IF(AND(G86="Big bet",W86>'7. Scoring criteria'!$C$46,Y86>'7. Scoring criteria'!$D$46),"Yes",IF(AND(G86="Big bet",W86>'7. Scoring criteria'!$C$46,AB86>'7. Scoring criteria'!$E$46),"Yes",IF(AND(G86="Long shot",Y86>'7. Scoring criteria'!$D$47,AB86>'7. Scoring criteria'!$E$47),"Yes","No"))))) | O86: =IFERROR(AVERAGE(R86:W86,X86:X86,Z86:Z86,AC86:AF86),"") | P86: =IFERROR(RANK(O86,$O$14:$O$128,0)+COUNTIF($O$14:O86,#REF!)," ") | R86: =IFERROR(AVERAGE('4a. Scorer 1'!F85,'4b. Scorer 2'!F85,'4c. Scorer 3'!F85)," ") | W86: =IFERROR(AVERAGE(T86:V86),"") | X86: =IFERROR(AVERAGE('4a. Scorer 1'!#REF!,'4b. Scorer 2'!M85,'4c. Scorer 3'!#REF!)," ") | Y86: =IFERROR(AVERAGE(X86:X86),"") | Z86: =IFERROR(AVERAGE('4a. Scorer 1'!N85,'4b. Scorer 2'!N85,'4c. Scorer 3'!N85)," ") | AA86: =IFERROR(AVERAGE('4a. Scorer 1'!#REF!,'4b. Scorer 2'!#REF!,'4c. Scorer 3'!#REF!)," ") | AB86: =IFERROR(AVERAGE(Z86:Z86),"") | AF86: =IFERROR(AVERAGE('4a. Scorer 1'!#REF!,'4b. Scorer 2'!S85,'4c. Scorer 3'!S85)," ") | AG86: =IFERROR(AVERAGE(AC86:AF86),"")
L87: =IF(G87="","",IF(AND(G87="Quick win",W87>'7. Scoring criteria'!$C$45,AG87>'7. Scoring criteria'!F121),"Yes",IF(AND(G87="Big bet",W87>'7. Scoring criteria'!$C$46,Y87>'7. Scoring criteria'!$D$46,AB87>'7. Scoring criteria'!$E$46),"Yes",IF(AND(G87="Long shot",Y87>'7. Scoring criteria'!$D$47,AB87>'7. Scoring criteria'!$E$47),"Yes","No")))) | O87: =IFERROR(AVERAGE(R87:W87,X87:X87,Z87:Z87,AC87:AF87),"") | P87: =IFERROR(RANK(O87,$O$14:$O$128,0)+COUNTIF($O$14:O87,#REF!)," ") | R87: =IFERROR(AVERAGE('4a. Scorer 1'!F86,'4b. Scorer 2'!F86,'4c. Scorer 3'!F86)," ") | W87: =IFERROR(AVERAGE(T87:V87),"") | X87: =IFERROR(AVERAGE('4a. Scorer 1'!#REF!,'4b. Scorer 2'!M86,'4c. Scorer 3'!#REF!)," ") | Y87: =IFERROR(AVERAGE(X87:X87),"") | Z87: =IFERROR(AVERAGE('4a. Scorer 1'!N86,'4b. Scorer 2'!N86,'4c. Scorer 3'!N86)," ") | AA87: =IFERROR(AVERAGE('4a. Scorer 1'!#REF!,'4b. Scorer 2'!#REF!,'4c. Scorer 3'!#REF!)," ") | AB87: =IFERROR(AVERAGE(Z87:Z87),"") | AF87: =IFERROR(AVERAGE('4a. Scorer 1'!#REF!,'4b. Scorer 2'!S86,'4c. Scorer 3'!S86)," ") | AG87: =IFERROR(AVERAGE(AC87:AF87),"")
L88: =IF(G88="","",IF(AND(G88="Quick win",W88>'7. Scoring criteria'!$C$45,AG88>'7. Scoring criteria'!F122),"Yes",IF(AND(G88="Big bet",W88>'7. Scoring criteria'!$C$46,Y88>'7. Scoring criteria'!$D$46,AB88>'7. Scoring criteria'!$E$46),"Yes",IF(AND(G88="Long shot",Y88>'7. Scoring criteria'!$D$47,AB88>'7. Scoring criteria'!$E$47),"Yes","No")))) | O88: =IFERROR(AVERAGE(R88:W88,X88:X88,Z88:Z88,AC88:AF88),"") | P88: =IFERROR(RANK(O88,$O$14:$O$128,0)+COUNTIF($O$14:O88,#REF!)," ") | R88: =IFERROR(AVERAGE('4a. Scorer 1'!F87,'4b. Scorer 2'!F87,'4c. Scorer 3'!F87)," ") | W88: =IFERROR(AVERAGE(T88:V88),"") | X88: =IFERROR(AVERAGE('4a. Scorer 1'!#REF!,'4b. Scorer 2'!M87,'4c. Scorer 3'!#REF!)," ") | Y88: =IFERROR(AVERAGE(X88:X88),"") | Z88: =IFERROR(AVERAGE('4a. Scorer 1'!N87,'4b. Scorer 2'!N87,'4c. Scorer 3'!N87)," ") | AA88: =IFERROR(AVERAGE('4a. Scorer 1'!#REF!,'4b. Scorer 2'!#REF!,'4c. Scorer 3'!#REF!)," ") | AB88: =IFERROR(AVERAGE(Z88:Z88),"") | AF88: =IFERROR(AVERAGE('4a. Scorer 1'!#REF!,'4b. Scorer 2'!S87,'4c. Scorer 3'!S87)," ") | AG88: =IFERROR(AVERAGE(AC88:AF88),"")
L89: =IF(G89="","",IF(AND(G89="Quick win",W89>'7. Scoring criteria'!$C$45,AG89>'7. Scoring criteria'!F123),"Yes",IF(AND(G89="Big bet",W89>'7. Scoring criteria'!$C$46,Y89>'7. Scoring criteria'!$D$46,AB89>'7. Scoring criteria'!$E$46),"Yes",IF(AND(G89="Long shot",Y89>'7. Scoring criteria'!$D$47,AB89>'7. Scoring criteria'!$E$47),"Yes","No")))) | O89: =IFERROR(AVERAGE(R89:W89,X89:X89,Z89:Z89,AC89:AF89),"") | P89: =IFERROR(RANK(O89,$O$14:$O$128,0)+COUNTIF($O$14:O89,#REF!)," ") | R89: =IFERROR(AVERAGE('4a. Scorer 1'!F88,'4b. Scorer 2'!F88,'4c. Scorer 3'!F88)," ") | W89: =IFERROR(AVERAGE(T89:V89),"") | X89: =IFERROR(AVERAGE('4a. Scorer 1'!#REF!,'4b. Scorer 2'!M88,'4c. Scorer 3'!#REF!)," ") | Y89: =IFERROR(AVERAGE(X89:X89),"") | Z89: =IFERROR(AVERAGE('4a. Scorer 1'!N88,'4b. Scorer 2'!N88,'4c. Scorer 3'!N88)," ") | AA89: =IFERROR(AVERAGE('4a. Scorer 1'!#REF!,'4b. Scorer 2'!#REF!,'4c. Scorer 3'!#REF!)," ") | AB89: =IFERROR(AVERAGE(Z89:Z89),"") | AF89: =IFERROR(AVERAGE('4a. Scorer 1'!#REF!,'4b. Scorer 2'!S88,'4c. Scorer 3'!S88)," ") | AG89: =IFERROR(AVERAGE(AC89:AF89),"")
L90: =IF(G90="","",IF(AND(G90="Quick win",W90>'7. Scoring criteria'!$C$45,AG90>'7. Scoring criteria'!F124),"Yes",IF(AND(G90="Big bet",W90>'7. Scoring criteria'!$C$46,Y90>'7. Scoring criteria'!$D$46,AB90>'7. Scoring criteria'!$E$46),"Yes",IF(AND(G90="Long shot",Y90>'7. Scoring criteria'!$D$47,AB90>'7. Scoring criteria'!$E$47),"Yes","No")))) | O90: =IFERROR(AVERAGE(R90:W90,X90:X90,Z90:Z90,AC90:AF90),"") | P90: =IFERROR(RANK(O90,$O$14:$O$128,0)+COUNTIF($O$14:O90,#REF!)," ") | R90: =IFERROR(AVERAGE('4a. Scorer 1'!F89,'4b. Scorer 2'!F89,'4c. Scorer 3'!F89)," ") | W90: =IFERROR(AVERAGE(T90:V90),"") | X90: =IFERROR(AVERAGE('4a. Scorer 1'!#REF!,'4b. Scorer 2'!M89,'4c. Scorer 3'!#REF!)," ") | Y90: =IFERROR(AVERAGE(X90:X90),"") | Z90: =IFERROR(AVERAGE('4a. Scorer 1'!N89,'4b. Scorer 2'!N89,'4c. Scorer 3'!N89)," ") | AA90: =IFERROR(AVERAGE('4a. Scorer 1'!#REF!,'4b. Scorer 2'!#REF!,'4c. Scorer 3'!#REF!)," ") | AB90: =IFERROR(AVERAGE(Z90:Z90),"") | AF90: =IFERROR(AVERAGE('4a. Scorer 1'!#REF!,'4b. Scorer 2'!S89,'4c. Scorer 3'!S89)," ") | AG90: =IFERROR(AVERAGE(AC90:AF90),"")
L91: =IF(G91="","",IF(AND(G91="Quick win",W91>'7. Scoring criteria'!$C$45,AG91>'7. Scoring criteria'!F125),"Yes",IF(AND(G91="Big bet",W91>'7. Scoring criteria'!$C$46,Y91>'7. Scoring criteria'!$D$46,AB91>'7. Scoring criteria'!$E$46),"Yes",IF(AND(G91="Long shot",Y91>'7. Scoring criteria'!$D$47,AB91>'7. Scoring criteria'!$E$47),"Yes","No")))) | O91: =IFERROR(AVERAGE(R91:W91,X91:X91,Z91:Z91,AC91:AF91),"") | P91: =IFERROR(RANK(O91,$O$14:$O$128,0)+COUNTIF($O$14:O91,#REF!)," ") | R91: =IFERROR(AVERAGE('4a. Scorer 1'!F90,'4b. Scorer 2'!F90,'4c. Scorer 3'!F90)," ") | W91: =IFERROR(AVERAGE(T91:V91),"") | X91: =IFERROR(AVERAGE('4a. Scorer 1'!#REF!,'4b. Scorer 2'!M90,'4c. Scorer 3'!#REF!)," ") | Y91: =IFERROR(AVERAGE(X91:X91),"") | Z91: =IFERROR(AVERAGE('4a. Scorer 1'!N90,'4b. Scorer 2'!N90,'4c. Scorer 3'!N90)," ") | AA91: =IFERROR(AVERAGE('4a. Scorer 1'!#REF!,'4b. Scorer 2'!#REF!,'4c. Scorer 3'!#REF!)," ") | AB91: =IFERROR(AVERAGE(Z91:Z91),"") | AF91: =IFERROR(AVERAGE('4a. Scorer 1'!#REF!,'4b. Scorer 2'!S90,'4c. Scorer 3'!S90)," ") | AG91: =IFERROR(AVERAGE(AC91:AF91),"")
L92: =IF(G92="","",IF(AND(G92="Quick win",W92>'7. Scoring criteria'!$C$45,AG92>'7. Scoring criteria'!F126),"Yes",IF(AND(G92="Big bet",W92>'7. Scoring criteria'!$C$46,Y92>'7. Scoring criteria'!$D$46,AB92>'7. Scoring criteria'!$E$46),"Yes",IF(AND(G92="Long shot",Y92>'7. Scoring criteria'!$D$47,AB92>'7. Scoring criteria'!$E$47),"Yes","No")))) | O92: =IFERROR(AVERAGE(R92:W92,X92:X92,Z92:Z92,AC92:AF92),"") | P92: =IFERROR(RANK(O92,$O$14:$O$128,0)+COUNTIF($O$14:O92,#REF!)," ") | R92: =IFERROR(AVERAGE('4a. Scorer 1'!F91,'4b. Scorer 2'!F91,'4c. Scorer 3'!F91)," ") | W92: =IFERROR(AVERAGE(T92:V92),"") | X92: =IFERROR(AVERAGE('4a. Scorer 1'!#REF!,'4b. Scorer 2'!M91,'4c. Scorer 3'!#REF!)," ") | Y92: =IFERROR(AVERAGE(X92:X92),"") | Z92: =IFERROR(AVERAGE('4a. Scorer 1'!N91,'4b. Scorer 2'!N91,'4c. Scorer 3'!N91)," ") | AA92: =IFERROR(AVERAGE('4a. Scorer 1'!#REF!,'4b. Scorer 2'!#REF!,'4c. Scorer 3'!#REF!)," ") | AB92: =IFERROR(AVERAGE(Z92:Z92),"") | AF92: =IFERROR(AVERAGE('4a. Scorer 1'!#REF!,'4b. Scorer 2'!S91,'4c. Scorer 3'!S91)," ") | AG92: =IFERROR(AVERAGE(AC92:AF92),"")
L93: =IF(G93="","",IF(AND(G93="Quick win",W93>'7. Scoring criteria'!$C$45,AG93>'7. Scoring criteria'!F127),"Yes",IF(AND(G93="Big bet",W93>'7. Scoring criteria'!$C$46,Y93>'7. Scoring criteria'!$D$46,AB93>'7. Scoring criteria'!$E$46),"Yes",IF(AND(G93="Long shot",Y93>'7. Scoring criteria'!$D$47,AB93>'7. Scoring criteria'!$E$47),"Yes","No")))) | O93: =IFERROR(AVERAGE(R93:W93,X93:X93,Z93:Z93,AC93:AF93),"") | P93: =IFERROR(RANK(O93,$O$14:$O$128,0)+COUNTIF($O$14:O93,#REF!)," ") | R93: =IFERROR(AVERAGE('4a. Scorer 1'!F92,'4b. Scorer 2'!F92,'4c. Scorer 3'!F92)," ") | W93: =IFERROR(AVERAGE(T93:V93),"") | X93: =IFERROR(AVERAGE('4a. Scorer 1'!#REF!,'4b. Scorer 2'!M92,'4c. Scorer 3'!#REF!)," ") | Y93: =IFERROR(AVERAGE(X93:X93),"") | Z93: =IFERROR(AVERAGE('4a. Scorer 1'!N92,'4b. Scorer 2'!N92,'4c. Scorer 3'!N92)," ") | AA93: =IFERROR(AVERAGE('4a. Scorer 1'!#REF!,'4b. Scorer 2'!#REF!,'4c. Scorer 3'!#REF!)," ") | AB93: =IFERROR(AVERAGE(Z93:Z93),"") | AF93: =IFERROR(AVERAGE('4a. Scorer 1'!#REF!,'4b. Scorer 2'!S92,'4c. Scorer 3'!S92)," ") | AG93: =IFERROR(AVERAGE(AC93:AF93),"")
L94: =IF(G94="","",IF(AND(G94="Quick win",W94>'7. Scoring criteria'!$C$45,AG94>'7. Scoring criteria'!F128),"Yes",IF(AND(G94="Big bet",W94>'7. Scoring criteria'!$C$46,Y94>'7. Scoring criteria'!$D$46,AB94>'7. Scoring criteria'!$E$46),"Yes",IF(AND(G94="Long shot",Y94>'7. Scoring criteria'!$D$47,AB94>'7. Scoring criteria'!$E$47),"Yes","No")))) | O94: =IFERROR(AVERAGE(R94:W94,X94:X94,Z94:Z94,AC94:AF94),"") | P94: =IFERROR(RANK(O94,$O$14:$O$128,0)+COUNTIF($O$14:O94,#REF!)," ") | R94: =IFERROR(AVERAGE('4a. Scorer 1'!F93,'4b. Scorer 2'!F93,'4c. Scorer 3'!F93)," ") | W94: =IFERROR(AVERAGE(T94:V94),"") | X94: =IFERROR(AVERAGE('4a. Scorer 1'!#REF!,'4b. Scorer 2'!M93,'4c. Scorer 3'!#REF!)," ") | Y94: =IFERROR(AVERAGE(X94:X94),"") | Z94: =IFERROR(AVERAGE('4a. Scorer 1'!N93,'4b. Scorer 2'!N93,'4c. Scorer 3'!N93)," ") | AA94: =IFERROR(AVERAGE('4a. Scorer 1'!#REF!,'4b. Scorer 2'!#REF!,'4c. Scorer 3'!#REF!)," ") | AB94: =IFERROR(AVERAGE(Z94:Z94),"") | AF94: =IFERROR(AVERAGE('4a. Scorer 1'!#REF!,'4b. Scorer 2'!S93,'4c. Scorer 3'!S93)," ") | AG94: =IFERROR(AVERAGE(AC94:AF94),"")
L95: =IF(G95="","",IF(AND(G95="Quick win",W95>'7. Scoring criteria'!$C$45,AG95>'7. Scoring criteria'!F129),"Yes",IF(AND(G95="Big bet",W95>'7. Scoring criteria'!$C$46,Y95>'7. Scoring criteria'!$D$46,AB95>'7. Scoring criteria'!$E$46),"Yes",IF(AND(G95="Long shot",Y95>'7. Scoring criteria'!$D$47,AB95>'7. Scoring criteria'!$E$47),"Yes","No")))) | O95: =IFERROR(AVERAGE(R95:W95,X95:X95,Z95:Z95,AC95:AF95),"") | P95: =IFERROR(RANK(O95,$O$14:$O$128,0)+COUNTIF($O$14:O95,#REF!)," ") | R95: =IFERROR(AVERAGE('4a. Scorer 1'!F94,'4b. Scorer 2'!F94,'4c. Scorer 3'!F94)," ") | W95: =IFERROR(AVERAGE(T95:V95),"") | X95: =IFERROR(AVERAGE('4a. Scorer 1'!#REF!,'4b. Scorer 2'!M94,'4c. Scorer 3'!#REF!)," ") | Y95: =IFERROR(AVERAGE(X95:X95),"") | Z95: =IFERROR(AVERAGE('4a. Scorer 1'!N94,'4b. Scorer 2'!N94,'4c. Scorer 3'!N94)," ") | AA95: =IFERROR(AVERAGE('4a. Scorer 1'!#REF!,'4b. Scorer 2'!#REF!,'4c. Scorer 3'!#REF!)," ") | AB95: =IFERROR(AVERAGE(Z95:Z95),"") | AF95: =IFERROR(AVERAGE('4a. Scorer 1'!#REF!,'4b. Scorer 2'!S94,'4c. Scorer 3'!#REF!)," ") | AG95: =IFERROR(AVERAGE(AC95:AF95),"")
L96: =IF(G96="","",IF(AND(G96="Quick win",W96>'7. Scoring criteria'!$C$45,AG96>'7. Scoring criteria'!F130),"Yes",IF(AND(G96="Big bet",W96>'7. Scoring criteria'!$C$46,Y96>'7. Scoring criteria'!$D$46,AB96>'7. Scoring criteria'!$E$46),"Yes",IF(AND(G96="Long shot",Y96>'7. Scoring criteria'!$D$47,AB96>'7. Scoring criteria'!$E$47),"Yes","No")))) | O96: =IFERROR(AVERAGE(R96:W96,X96:X96,Z96:Z96,AC96:AF96),"") | P96: =IFERROR(RANK(O96,$O$14:$O$128,0)+COUNTIF($O$14:O96,#REF!)," ") | R96: =IFERROR(AVERAGE('4a. Scorer 1'!F95,'4b. Scorer 2'!F95,'4c. Scorer 3'!F95)," ") | W96: =IFERROR(AVERAGE(T96:V96),"") | X96: =IFERROR(AVERAGE('4a. Scorer 1'!#REF!,'4b. Scorer 2'!M95,'4c. Scorer 3'!#REF!)," ") | Y96: =IFERROR(AVERAGE(X96:X96),"") | Z96: =IFERROR(AVERAGE('4a. Scorer 1'!N95,'4b. Scorer 2'!N95,'4c. Scorer 3'!N95)," ") | AA96: =IFERROR(AVERAGE('4a. Scorer 1'!#REF!,'4b. Scorer 2'!#REF!,'4c. Scorer 3'!#REF!)," ") | AB96: =IFERROR(AVERAGE(Z96:Z96),"") | AF96: =IFERROR(AVERAGE('4a. Scorer 1'!#REF!,'4b. Scorer 2'!S95,'4c. Scorer 3'!#REF!)," ") | AG96: =IFERROR(AVERAGE(AC96:AF96),"")
L97: =IF(G97="","",IF(AND(G97="Quick win",W97>'7. Scoring criteria'!$C$45,AG97>'7. Scoring criteria'!F131),"Yes",IF(AND(G97="Big bet",W97>'7. Scoring criteria'!$C$46,Y97>'7. Scoring criteria'!$D$46,AB97>'7. Scoring criteria'!$E$46),"Yes",IF(AND(G97="Long shot",Y97>'7. Scoring criteria'!$D$47,AB97>'7. Scoring criteria'!$E$47),"Yes","No")))) | O97: =IFERROR(AVERAGE(R97:W97,X97:X97,Z97:Z97,AC97:AF97),"") | P97: =IFERROR(RANK(O97,$O$14:$O$128,0)+COUNTIF($O$14:O97,#REF!)," ") | R97: =IFERROR(AVERAGE('4a. Scorer 1'!F96,'4b. Scorer 2'!F96,'4c. Scorer 3'!F96)," ") | W97: =IFERROR(AVERAGE(T97:V97),"") | X97: =IFERROR(AVERAGE('4a. Scorer 1'!#REF!,'4b. Scorer 2'!M96,'4c. Scorer 3'!#REF!)," ") | Y97: =IFERROR(AVERAGE(X97:X97),"") | Z97: =IFERROR(AVERAGE('4a. Scorer 1'!N96,'4b. Scorer 2'!N96,'4c. Scorer 3'!N96)," ") | AA97: =IFERROR(AVERAGE('4a. Scorer 1'!#REF!,'4b. Scorer 2'!#REF!,'4c. Scorer 3'!#REF!)," ") | AB97: =IFERROR(AVERAGE(Z97:Z97),"") | AF97: =IFERROR(AVERAGE('4a. Scorer 1'!#REF!,'4b. Scorer 2'!S96,'4c. Scorer 3'!#REF!)," ") | AG97: =IFERROR(AVERAGE(AC97:AF97),"")
L98: =IF(G98="","",IF(AND(G98="Quick win",W98>'7. Scoring criteria'!$C$45,AG98>'7. Scoring criteria'!F132),"Yes",IF(AND(G98="Big bet",W98>'7. Scoring criteria'!$C$46,Y98>'7. Scoring criteria'!$D$46,AB98>'7. Scoring criteria'!$E$46),"Yes",IF(AND(G98="Long shot",Y98>'7. Scoring criteria'!$D$47,AB98>'7. Scoring criteria'!$E$47),"Yes","No")))) | O98: =IFERROR(AVERAGE(R98:W98,X98:X98,Z98:Z98,AC98:AF98),"") | P98: =IFERROR(RANK(O98,$O$14:$O$128,0)+COUNTIF($O$14:O98,#REF!)," ") | R98: =IFERROR(AVERAGE('4a. Scorer 1'!F97,'4b. Scorer 2'!F97,'4c. Scorer 3'!F97)," ") | W98: =IFERROR(AVERAGE(T98:V98),"") | X98: =IFERROR(AVERAGE('4a. Scorer 1'!#REF!,'4b. Scorer 2'!M97,'4c. Scorer 3'!#REF!)," ") | Y98: =IFERROR(AVERAGE(X98:X98),"") | Z98: =IFERROR(AVERAGE('4a. Scorer 1'!N97,'4b. Scorer 2'!N97,'4c. Scorer 3'!N97)," ") | AA98: =IFERROR(AVERAGE('4a. Scorer 1'!#REF!,'4b. Scorer 2'!#REF!,'4c. Scorer 3'!#REF!)," ") | AB98: =IFERROR(AVERAGE(Z98:Z98),"") | AF98: =IFERROR(AVERAGE('4a. Scorer 1'!#REF!,'4b. Scorer 2'!S97,'4c. Scorer 3'!#REF!)," ") | AG98: =IFERROR(AVERAGE(AC98:AF98),"")
L99: =IF(G99="","",IF(AND(G99="Quick win",W99>'7. Scoring criteria'!$C$45,AG99>'7. Scoring criteria'!F133),"Yes",IF(AND(G99="Big bet",W99>'7. Scoring criteria'!$C$46,Y99>'7. Scoring criteria'!$D$46,AB99>'7. Scoring criteria'!$E$46),"Yes",IF(AND(G99="Long shot",Y99>'7. Scoring criteria'!$D$47,AB99>'7. Scoring criteria'!$E$47),"Yes","No")))) | O99: =IFERROR(AVERAGE(R99:W99,X99:X99,Z99:Z99,AC99:AF99),"") | P99: =IFERROR(RANK(O99,$O$14:$O$128,0)+COUNTIF($O$14:O99,#REF!)," ") | R99: =IFERROR(AVERAGE('4a. Scorer 1'!F98,'4b. Scorer 2'!F98,'4c. Scorer 3'!F98)," ") | W99: =IFERROR(AVERAGE(T99:V99),"") | X99: =IFERROR(AVERAGE('4a. Scorer 1'!#REF!,'4b. Scorer 2'!M98,'4c. Scorer 3'!#REF!)," ") | Y99: =IFERROR(AVERAGE(X99:X99),"") | Z99: =IFERROR(AVERAGE('4a. Scorer 1'!N98,'4b. Scorer 2'!N98,'4c. Scorer 3'!N98)," ") | AA99: =IFERROR(AVERAGE('4a. Scorer 1'!#REF!,'4b. Scorer 2'!#REF!,'4c. Scorer 3'!#REF!)," ") | AB99: =IFERROR(AVERAGE(Z99:Z99),"") | AF99: =IFERROR(AVERAGE('4a. Scorer 1'!#REF!,'4b. Scorer 2'!S98,'4c. Scorer 3'!#REF!)," ") | AG99: =IFERROR(AVERAGE(AC99:AF99),"")
L100: =IF(G100="","",IF(AND(G100="Quick win",W100>'7. Scoring criteria'!$C$45,AG100>'7. Scoring criteria'!F134),"Yes",IF(AND(G100="Big bet",W100>'7. Scoring criteria'!$C$46,Y100>'7. Scoring criteria'!$D$46,AB100>'7. Scoring criteria'!$E$46),"Yes",IF(AND(G100="Long shot",Y100>'7. Scoring criteria'!$D$47,AB100>'7. Scoring criteria'!$E$47),"Yes","No")))) | O100: =IFERROR(AVERAGE(R100:W100,X100:X100,Z100:Z100,AC100:AF100),"") | P100: =IFERROR(RANK(O100,$O$14:$O$128,0)+COUNTIF($O$14:O100,#REF!)," ") | R100: =IFERROR(AVERAGE('4a. Scorer 1'!F99,'4b. Scorer 2'!F99,'4c. Scorer 3'!F99)," ") | W100: =IFERROR(AVERAGE(T100:V100),"") | X100: =IFERROR(AVERAGE('4a. Scorer 1'!#REF!,'4b. Scorer 2'!M99,'4c. Scorer 3'!#REF!)," ") | Y100: =IFERROR(AVERAGE(X100:X100),"") | Z100: =IFERROR(AVERAGE('4a. Scorer 1'!N99,'4b. Scorer 2'!N99,'4c. Scorer 3'!N99)," ") | AA100: =IFERROR(AVERAGE('4a. Scorer 1'!#REF!,'4b. Scorer 2'!#REF!,'4c. Scorer 3'!#REF!)," ") | AB100: =IFERROR(AVERAGE(Z100:Z100),"") | AF100: =IFERROR(AVERAGE('4a. Scorer 1'!#REF!,'4b. Scorer 2'!S99,'4c. Scorer 3'!#REF!)," ") | AG100: =IFERROR(AVERAGE(AC100:AF100),"")
L101: =IF(G101="","",IF(AND(G101="Quick win",W101>'7. Scoring criteria'!$C$45,AG101>'7. Scoring criteria'!F135),"Yes",IF(AND(G101="Big bet",W101>'7. Scoring criteria'!$C$46,Y101>'7. Scoring criteria'!$D$46,AB101>'7. Scoring criteria'!$E$46),"Yes",IF(AND(G101="Long shot",Y101>'7. Scoring criteria'!$D$47,AB101>'7. Scoring criteria'!$E$47),"Yes","No")))) | O101: =IFERROR(AVERAGE(R101:W101,X101:X101,Z101:Z101,AC101:AF101),"") | P101: =IFERROR(RANK(O101,$O$14:$O$128,0)+COUNTIF($O$14:O101,#REF!)," ") | R101: =IFERROR(AVERAGE('4a. Scorer 1'!F100,'4b. Scorer 2'!F100,'4c. Scorer 3'!F100)," ") | W101: =IFERROR(AVERAGE(T101:V101),"") | X101: =IFERROR(AVERAGE('4a. Scorer 1'!#REF!,'4b. Scorer 2'!M100,'4c. Scorer 3'!#REF!)," ") | Y101: =IFERROR(AVERAGE(X101:X101),"") | Z101: =IFERROR(AVERAGE('4a. Scorer 1'!N100,'4b. Scorer 2'!N100,'4c. Scorer 3'!N100)," ") | AA101: =IFERROR(AVERAGE('4a. Scorer 1'!#REF!,'4b. Scorer 2'!#REF!,'4c. Scorer 3'!#REF!)," ") | AB101: =IFERROR(AVERAGE(Z101:Z101),"") | AF101: =IFERROR(AVERAGE('4a. Scorer 1'!#REF!,'4b. Scorer 2'!S100,'4c. Scorer 3'!#REF!)," ") | AG101: =IFERROR(AVERAGE(AC101:AF101),"")
L102: =IF(G102="","",IF(AND(G102="Quick win",W102>'7. Scoring criteria'!$C$45,AG102>'7. Scoring criteria'!F136),"Yes",IF(AND(G102="Big bet",W102>'7. Scoring criteria'!$C$46,Y102>'7. Scoring criteria'!$D$46,AB102>'7. Scoring criteria'!$E$46),"Yes",IF(AND(G102="Long shot",Y102>'7. Scoring criteria'!$D$47,AB102>'7. Scoring criteria'!$E$47),"Yes","No")))) | O102: =IFERROR(AVERAGE(R102:W102,X102:X102,Z102:Z102,AC102:AF102),"") | P102: =IFERROR(RANK(O102,$O$14:$O$128,0)+COUNTIF($O$14:O102,#REF!)," ") | R102: =IFERROR(AVERAGE('4a. Scorer 1'!F101,'4b. Scorer 2'!F101,'4c. Scorer 3'!F101)," ") | W102: =IFERROR(AVERAGE(T102:V102),"") | X102: =IFERROR(AVERAGE('4a. Scorer 1'!#REF!,'4b. Scorer 2'!M101,'4c. Scorer 3'!#REF!)," ") | Y102: =IFERROR(AVERAGE(X102:X102),"") | Z102: =IFERROR(AVERAGE('4a. Scorer 1'!N101,'4b. Scorer 2'!N101,'4c. Scorer 3'!N101)," ") | AA102: =IFERROR(AVERAGE('4a. Scorer 1'!#REF!,'4b. Scorer 2'!#REF!,'4c. Scorer 3'!#REF!)," ") | AB102: =IFERROR(AVERAGE(Z102:Z102),"") | AF102: =IFERROR(AVERAGE('4a. Scorer 1'!#REF!,'4b. Scorer 2'!S101,'4c. Scorer 3'!#REF!)," ") | AG102: =IFERROR(AVERAGE(AC102:AF102),"")
L103: =IF(G103="","",IF(AND(G103="Quick win",W103>'7. Scoring criteria'!$C$45,AG103>'7. Scoring criteria'!F137),"Yes",IF(AND(G103="Big bet",W103>'7. Scoring criteria'!$C$46,Y103>'7. Scoring criteria'!$D$46,AB103>'7. Scoring criteria'!$E$46),"Yes",IF(AND(G103="Long shot",Y103>'7. Scoring criteria'!$D$47,AB103>'7. Scoring criteria'!$E$47),"Yes","No")))) | O103: =IFERROR(AVERAGE(R103:W103,X103:X103,Z103:Z103,AC103:AF103),"") | P103: =IFERROR(RANK(O103,$O$14:$O$128,0)+COUNTIF($O$14:O103,#REF!)," ") | R103: =IFERROR(AVERAGE('4a. Scorer 1'!F102,'4b. Scorer 2'!F102,'4c. Scorer 3'!F102)," ") | W103: =IFERROR(AVERAGE(T103:V103),"") | X103: =IFERROR(AVERAGE('4a. Scorer 1'!#REF!,'4b. Scorer 2'!M102,'4c. Scorer 3'!#REF!)," ") | Y103: =IFERROR(AVERAGE(X103:X103),"") | Z103: =IFERROR(AVERAGE('4a. Scorer 1'!N102,'4b. Scorer 2'!N102,'4c. Scorer 3'!N102)," ") | AA103: =IFERROR(AVERAGE('4a. Scorer 1'!#REF!,'4b. Scorer 2'!#REF!,'4c. Scorer 3'!#REF!)," ") | AB103: =IFERROR(AVERAGE(Z103:Z103),"") | AF103: =IFERROR(AVERAGE('4a. Scorer 1'!#REF!,'4b. Scorer 2'!S102,'4c. Scorer 3'!#REF!)," ") | AG103: =IFERROR(AVERAGE(AC103:AF103),"")
L104: =IF(G104="","",IF(AND(G104="Quick win",W104>'7. Scoring criteria'!$C$45,AG104>'7. Scoring criteria'!F138),"Yes",IF(AND(G104="Big bet",W104>'7. Scoring criteria'!$C$46,Y104>'7. Scoring criteria'!$D$46,AB104>'7. Scoring criteria'!$E$46),"Yes",IF(AND(G104="Long shot",Y104>'7. Scoring criteria'!$D$47,AB104>'7. Scoring criteria'!$E$47),"Yes","No")))) | O104: =IFERROR(AVERAGE(R104:W104,X104:X104,Z104:Z104,AC104:AF104),"") | P104: =IFERROR(RANK(O104,$O$14:$O$128,0)+COUNTIF($O$14:O104,#REF!)," ") | R104: =IFERROR(AVERAGE('4a. Scorer 1'!F103,'4b. Scorer 2'!F103,'4c. Scorer 3'!F103)," ") | W104: =IFERROR(AVERAGE(T104:V104),"") | X104: =IFERROR(AVERAGE('4a. Scorer 1'!#REF!,'4b. Scorer 2'!M103,'4c. Scorer 3'!#REF!)," ") | Y104: =IFERROR(AVERAGE(X104:X104),"") | Z104: =IFERROR(AVERAGE('4a. Scorer 1'!N103,'4b. Scorer 2'!N103,'4c. Scorer 3'!N103)," ") | AA104: =IFERROR(AVERAGE('4a. Scorer 1'!#REF!,'4b. Scorer 2'!#REF!,'4c. Scorer 3'!#REF!)," ") | AB104: =IFERROR(AVERAGE(Z104:Z104),"") | AF104: =IFERROR(AVERAGE('4a. Scorer 1'!#REF!,'4b. Scorer 2'!S103,'4c. Scorer 3'!#REF!)," ") | AG104: =IFERROR(AVERAGE(AC104:AF104),"")
L105: =IF(G105="","",IF(AND(G105="Quick win",W105>'7. Scoring criteria'!$C$45,AG105>'7. Scoring criteria'!F139),"Yes",IF(AND(G105="Big bet",W105>'7. Scoring criteria'!$C$46,Y105>'7. Scoring criteria'!$D$46,AB105>'7. Scoring criteria'!$E$46),"Yes",IF(AND(G105="Long shot",Y105>'7. Scoring criteria'!$D$47,AB105>'7. Scoring criteria'!$E$47),"Yes","No")))) | O105: =IFERROR(AVERAGE(R105:W105,X105:X105,Z105:Z105,AC105:AF105),"") | P105: =IFERROR(RANK(O105,$O$14:$O$128,0)+COUNTIF($O$14:O105,#REF!)," ") | R105: =IFERROR(AVERAGE('4a. Scorer 1'!F104,'4b. Scorer 2'!F104,'4c. Scorer 3'!F104)," ") | W105: =IFERROR(AVERAGE(T105:V105),"") | X105: =IFERROR(AVERAGE('4a. Scorer 1'!#REF!,'4b. Scorer 2'!M104,'4c. Scorer 3'!#REF!)," ") | Y105: =IFERROR(AVERAGE(X105:X105),"") | Z105: =IFERROR(AVERAGE('4a. Scorer 1'!N104,'4b. Scorer 2'!N104,'4c. Scorer 3'!N104)," ") | AA105: =IFERROR(AVERAGE('4a. Scorer 1'!#REF!,'4b. Scorer 2'!#REF!,'4c. Scorer 3'!#REF!)," ") | AB105: =IFERROR(AVERAGE(Z105:Z105),"") | AF105: =IFERROR(AVERAGE('4a. Scorer 1'!#REF!,'4b. Scorer 2'!S104,'4c. Scorer 3'!#REF!)," ") | AG105: =IFERROR(AVERAGE(AC105:AF105),"")
L106: =IF(G106="","",IF(AND(G106="Quick win",W106>'7. Scoring criteria'!$C$45,AG106>'7. Scoring criteria'!F140),"Yes",IF(AND(G106="Big bet",W106>'7. Scoring criteria'!$C$46,Y106>'7. Scoring criteria'!$D$46,AB106>'7. Scoring criteria'!$E$46),"Yes",IF(AND(G106="Long shot",Y106>'7. Scoring criteria'!$D$47,AB106>'7. Scoring criteria'!$E$47),"Yes","No")))) | O106: =IFERROR(AVERAGE(R106:W106,X106:X106,Z106:Z106,AC106:AF106),"") | P106: =IFERROR(RANK(O106,$O$14:$O$128,0)+COUNTIF($O$14:O106,#REF!)," ") | R106: =IFERROR(AVERAGE('4a. Scorer 1'!F105,'4b. Scorer 2'!F105,'4c. Scorer 3'!F105)," ") | W106: =IFERROR(AVERAGE(T106:V106),"") | X106: =IFERROR(AVERAGE('4a. Scorer 1'!#REF!,'4b. Scorer 2'!M105,'4c. Scorer 3'!#REF!)," ") | Y106: =IFERROR(AVERAGE(X106:X106),"") | Z106: =IFERROR(AVERAGE('4a. Scorer 1'!N105,'4b. Scorer 2'!N105,'4c. Scorer 3'!N105)," ") | AA106: =IFERROR(AVERAGE('4a. Scorer 1'!#REF!,'4b. Scorer 2'!#REF!,'4c. Scorer 3'!#REF!)," ") | AB106: =IFERROR(AVERAGE(Z106:Z106),"") | AF106: =IFERROR(AVERAGE('4a. Scorer 1'!#REF!,'4b. Scorer 2'!S105,'4c. Scorer 3'!#REF!)," ") | AG106: =IFERROR(AVERAGE(AC106:AF106),"")
... L130: =IF(G130="","",IF(AND(G130="Quick win",W130>'7. Scoring criteria'!$C$45,AG130>'7. Scoring criteria'!F164),"Yes",IF(AND(G130="Big bet",W130>'7. Scoring criteria'!$C$46,Y130>'7. Scoring criteria'!$D$46,AB130>'7. Scoring criteria'!$E$46),"Yes",IF(AND(G130="Long shot",Y130>'7. Scoring criteria'!$D$47,AB130>'7. Scoring criteria'!$E$47),"Yes","No")))) | O130: =IFERROR(AVERAGE(R130:W130,X130:X130,Z130:Z130,AC130:AF130),"") | P130: =IFERROR(RANK(O130,$O$14:$O$128,0)+COUNTIF($O$14:O130,#REF!)," ") | R130: =IFERROR(AVERAGE('4a. Scorer 1'!F129,'4b. Scorer 2'!F129,'4c. Scorer 3'!F129)," ") | W130: =IFERROR(AVERAGE(T130:V130),"") | X130: =IFERROR(AVERAGE('4a. Scorer 1'!#REF!,'4b. Scorer 2'!M129,'4c. Scorer 3'!#REF!)," ") | Y130: =IFERROR(AVERAGE(X130:X130),"") | Z130: =IFERROR(AVERAGE('4a. Scorer 1'!N129,'4b. Scorer 2'!N129,'4c. Scorer 3'!N129)," ") | AA130: =IFERROR(AVERAGE('4a. Scorer 1'!#REF!,'4b. Scorer 2'!#REF!,'4c. Scorer 3'!#REF!)," ") | AB130: =IFERROR(AVERAGE(Z130:Z130),"") | AF130: =IFERROR(AVERAGE('4a. Scorer 1'!#REF!,'4b. Scorer 2'!S129,'4c. Scorer 3'!#REF!)," ") | AG130: =IFERROR(AVERAGE(AC130:AF130),"")

Sheet 2. VAS comparison
B2: VAS Comparison
B3: VAS comparison against key criteria
B7: COMPARISON OVERVIEW
B39: FILTERS | D39: SCORE BREAKDOWN
B41: Category | C41: Sub category | D41: VAS | E41: Description | F41: ='1. Master scoring '!R9 -> Grow core Business Margin | G41: ='1. Master scoring '!X9 -> Commercial Viability | H41: ='1. Master scoring '!Z9 -> Customer Desirability | I41: ='1. Master scoring '!AC9 -> Execution | J41: Total score | K41: Rank
B42: =IFERROR(VLOOKUP(D42,'1. Master scoring '!C14:F45,3,FALSE),"") -> DigitalAccessAndProtection​ | C42: =IFERROR(VLOOKUP(D42,'1. Master scoring '!C14:F45,4,FALSE),"") -> Practical guides / Prevention information​ | D42: =IF('4. VAS list'!B8="","",'4. VAS list'!B8) -> Telemedicine | E42: =IFERROR(VLOOKUP(D42,'3. NON USARE Master scoring'!$C$14:$AH$130,2,FALSE),"") | F42: ='1. Master scoring '!W14 -> 1.0208333 | G42: ='1. Master scoring '!Y14 -> 4.3333333 | H42: ='1. Master scoring '!AB14 -> 3.75 | I42: ='1. Master scoring '!AG14 -> 2.5 | J42: ='1. Master scoring '!O14 -> 4.2443182 | K42: ='1. Master scoring '!P14 -> 1
B43: =IFERROR(VLOOKUP(D43,'1. Master scoring '!C15:F46,3,FALSE),"") -> Health​ | C43: =IFERROR(VLOOKUP(D43,'1. Master scoring '!C15:F46,4,FALSE),"") -> Medical & health specialist services​ | D43: =IF('4. VAS list'!B9="","",'4. VAS list'!B9) -> ID Theft | E43: =IFERROR(VLOOKUP(D43,'3. NON USARE Master scoring'!$C$14:$AH$130,2,FALSE),"") -> Cover the costs you might incur from being defrauded | F43: ='1. Master scoring '!W15 -> 0.89583333 | G43: ='1. Master scoring '!Y15 -> 4 | H43: ='1. Master scoring '!AB15 -> 3.5 | I43: ='1. Master scoring '!AG15 -> 2.4166667 | J43: ='1. Master scoring '!O15 -> 3.9299242 | K43: ='1. Master scoring '!P15 -> 2
B44: =IFERROR(VLOOKUP(D44,'1. Master scoring '!C16:F47,3,FALSE),"") -> Mobility​ | C44: =IFERROR(VLOOKUP(D44,'1. Master scoring '!C16:F47,4,FALSE),"") -> Mobility assistance (bikes, fines help)​ | D44: =IF('4. VAS list'!B10="","",'4. VAS list'!B10) -> Vehicle Geolocation | E44: =IFERROR(VLOOKUP(D44,'3. NON USARE Master scoring'!$C$14:$AH$130,2,FALSE),"") -> Install an approved GPS tracking device and reduce vehicle insurance premium | F44: ='1. Master scoring '!W16 -> 0.9375 | G44: ='1. Master scoring '!Y16 -> 3.6666667 | H44: ='1. Master scoring '!AB16 -> 3.5 | I44: ='1. Master scoring '!AG16 -> 2.2916667 | J44: ='1. Master scoring '!O16 -> 3.8731061 | K44: ='1. Master scoring '!P16 -> 3
B45: =IFERROR(VLOOKUP(D45,'1. Master scoring '!C17:F48,3,FALSE),"") -> HomeAndFamily​ | C45: =IFERROR(VLOOKUP(D45,'1. Master scoring '!C17:F48,4,FALSE),"") -> Pet care​ | D45: =IF('4. VAS list'!B11="","",'4. VAS list'!B11) -> Pet Care | E45: =IFERROR(VLOOKUP(D45,'3. NON USARE Master scoring'!$C$14:$AH$130,2,FALSE),"") -> Cover the cost of veterinary fees for illnesses or injuries | F45: ='1. Master scoring '!W17 -> 0.89583333 | G45: ='1. Master scoring '!Y17 -> 3.3333333 | H45: ='1. Master scoring '!AB17 -> 3 | I45: ='1. Master scoring '!AG17 -> 2.375 | J45: ='1. Master scoring '!O17 -> 3.7784091 | K45: ='1. Master scoring '!P17 -> 4
B46: =IFERROR(VLOOKUP(D46,'1. Master scoring '!C18:F49,3,FALSE),"") -> Mobility​ | C46: =IFERROR(VLOOKUP(D46,'1. Master scoring '!C18:F49,4,FALSE),"") -> Emergency response​ | D46: =IF('4. VAS list'!B12="","",'4. VAS list'!B12) -> Road Assistance | E46: =IFERROR(VLOOKUP(D46,'3. NON USARE Master scoring'!$C$14:$AH$130,2,FALSE),"") | F46: ='1. Master scoring '!W18 -> 0.875 | G46: ='1. Master scoring '!Y18 -> 3.6666667 | H46: ='1. Master scoring '!AB18 -> 3.5 | I46: ='1. Master scoring '!AG18 -> 1.875 | J46: ='1. Master scoring '!O18 -> 3.4734848 | K46: ='1. Master scoring '!P18 -> 5
B47: =IFERROR(VLOOKUP(D47,'1. Master scoring '!C19:F50,3,FALSE),"") | C47: =IFERROR(VLOOKUP(D47,'1. Master scoring '!C19:F50,4,FALSE),"") | D47: =IF(ISBLANK('4. VAS list'!B13),"",'4. VAS list'!B13) | E47: =IFERROR(VLOOKUP(#REF!,'3. NON USARE Master scoring'!$C$14:$AH$130,2,FALSE),"") | F47: ='1. Master scoring '!W19 | G47: ='1. Master scoring '!Y19 | H47: ='1. Master scoring '!AB19 -> 0 | I47: ='1. Master scoring '!AG19 | J47: ='1. Master scoring '!O19 | K47: ='1. Master scoring '!P19
B48: =IFERROR(VLOOKUP(D48,'1. Master scoring '!C20:F51,3,FALSE),"") | C48: =IFERROR(VLOOKUP(D48,'1. Master scoring '!C20:F51,4,FALSE),"") | D48: =IF(ISBLANK('4. VAS list'!B14),"",'4. VAS list'!B14) | E48: =IFERROR(VLOOKUP(D48,'3. NON USARE Master scoring'!$C$14:$AH$130,2,FALSE),"") | F48: ='1. Master scoring '!W20 | G48: ='1. Master scoring '!Y20 | H48: ='1. Master scoring '!AB20 -> 0 | I48: ='1. Master scoring '!AG20 | J48: ='1. Master scoring '!O20 | K48: ='1. Master scoring '!P20
B49: =IFERROR(VLOOKUP(D49,'1. Master scoring '!C21:F52,3,FALSE),"") | C49: =IFERROR(VLOOKUP(D49,'1. Master scoring '!C21:F52,4,FALSE),"") | D49: =IF(ISBLANK('4. VAS list'!B15),"",'4. VAS list'!B15) | E49: =IFERROR(VLOOKUP(D49,'3. NON USARE Master scoring'!$C$14:$AH$130,2,FALSE),"") | F49: ='1. Master scoring '!W21 | G49: ='1. Master scoring '!Y21 | H49: ='1. Master scoring '!AB21 -> 0 | I49: ='1. Master scoring '!AG21 | J49: ='1. Master scoring '!O21 | K49: ='1. Master scoring '!P21
B50: =IFERROR(VLOOKUP(D50,'1. Master scoring '!C22:F53,3,FALSE),"") | C50: =IFERROR(VLOOKUP(D50,'1. Master scoring '!C22:F53,4,FALSE),"") | D50: =IF(ISBLANK('4. VAS list'!B16),"",'4. VAS list'!B16) | E50: =IFERROR(VLOOKUP(D50,'3. NON USARE Master scoring'!$C$14:$AH$130,2,FALSE),"") | F50: ='1. Master scoring '!W22 | G50: ='1. Master scoring '!Y22 | H50: ='1. Master scoring '!AB22 -> 0 | I50: ='1. Master scoring '!AG22 | J50: ='1. Master scoring '!O22 | K50: ='1. Master scoring '!P22
B51: =IFERROR(VLOOKUP(D51,'1. Master scoring '!C23:F54,3,FALSE),"") | C51: =IFERROR(VLOOKUP(D51,'1. Master scoring '!C23:F54,4,FALSE),"") | D51: =IF(ISBLANK('4. VAS list'!B17),"",'4. VAS list'!B17) | E51: =IFERROR(VLOOKUP(D51,'3. NON USARE Master scoring'!$C$14:$AH$130,2,FALSE),"") | F51: ='1. Master scoring '!W23 | G51: ='1. Master scoring '!Y23 | H51: ='1. Master scoring '!AB23 -> 0 | I51: ='1. Master scoring '!AG23 | J51: ='1. Master scoring '!O23 | K51: ='1. Master scoring '!P23
B52: =IFERROR(VLOOKUP(D52,'1. Master scoring '!C24:F55,3,FALSE),"") | C52: =IFERROR(VLOOKUP(D52,'1. Master scoring '!C24:F55,4,FALSE),"") | D52: =IF(ISBLANK('4. VAS list'!B18),"",'4. VAS list'!B18) | E52: =IFERROR(VLOOKUP(D52,'3. NON USARE Master scoring'!$C$14:$AH$130,2,FALSE),"") | F52: ='1. Master scoring '!W24 | G52: ='1. Master scoring '!Y24 | H52: ='1. Master scoring '!AB24 -> 0 | I52: ='1. Master scoring '!AG24 | J52: ='1. Master scoring '!O24 | K52: ='1. Master scoring '!P24
B53: =IFERROR(VLOOKUP(D53,'1. Master scoring '!C25:F56,3,FALSE),"") | C53: =IFERROR(VLOOKUP(D53,'1. Master scoring '!C25:F56,4,FALSE),"") | D53: =IF(ISBLANK('4. VAS list'!B19),"",'4. VAS list'!B19) | E53: =IFERROR(VLOOKUP(D53,'3. NON USARE Master scoring'!$C$14:$AH$130,2,FALSE),"") | F53: ='1. Master scoring '!W25 | G53: ='1. Master scoring '!Y25 | H53: ='1. Master scoring '!AB25 -> 0 | I53: ='1. Master scoring '!AG25 | J53: ='1. Master scoring '!O25 | K53: ='1. Master scoring '!P25
B54: =IFERROR(VLOOKUP(D54,'1. Master scoring '!C26:F57,3,FALSE),"") | C54: =IFERROR(VLOOKUP(D54,'1. Master scoring '!C26:F57,4,FALSE),"") | D54: =IF(ISBLANK('4. VAS list'!B20),"",'4. VAS list'!B20) | E54: =IFERROR(VLOOKUP(D54,'3. NON USARE Master scoring'!$C$14:$AH$130,2,FALSE),"") | F54: ='1. Master scoring '!W26 | G54: ='1. Master scoring '!Y26 | H54: ='1. Master scoring '!AB26 -> 0 | I54: ='1. Master scoring '!AG26 | J54: ='1. Master scoring '!O26 | K54: ='1. Master scoring '!P26
B55: =IFERROR(VLOOKUP(D55,'1. Master scoring '!C27:F58,3,FALSE),"") | C55: =IFERROR(VLOOKUP(D55,'1. Master scoring '!C27:F58,4,FALSE),"") | D55: =IF(ISBLANK('4. VAS list'!B21),"",'4. VAS list'!B21) | E55: =IFERROR(VLOOKUP(D55,'3. NON USARE Master scoring'!$C$14:$AH$130,2,FALSE),"") | F55: ='1. Master scoring '!W27 | G55: ='1. Master scoring '!Y27 | H55: ='1. Master scoring '!AB27 -> 0 | I55: ='1. Master scoring '!AG27 | J55: ='1. Master scoring '!O27 | K55: ='1. Master scoring '!P27
B56: =IFERROR(VLOOKUP(D56,'1. Master scoring '!C28:F59,3,FALSE),"") | C56: =IFERROR(VLOOKUP(D56,'1. Master scoring '!C28:F59,4,FALSE),"") | D56: =IF(ISBLANK('4. VAS list'!B22),"",'4. VAS list'!B22) | E56: =IFERROR(VLOOKUP(D56,'3. NON USARE Master scoring'!$C$14:$AH$130,2,FALSE),"") | F56: ='1. Master scoring '!W28 | G56: ='1. Master scoring '!Y28 | H56: ='1. Master scoring '!AB28 -> 0 | I56: ='1. Master scoring '!AG28 | J56: ='1. Master scoring '!O28 | K56: ='1. Master scoring '!P28
B57: =IFERROR(VLOOKUP(D57,'1. Master scoring '!C29:F60,3,FALSE),"") | C57: =IFERROR(VLOOKUP(D57,'1. Master scoring '!C29:F60,4,FALSE),"") | D57: =IF(ISBLANK('4. VAS list'!B23),"",'4. VAS list'!B23) | E57: =IFERROR(VLOOKUP(D57,'3. NON USARE Master scoring'!$C$14:$AH$130,2,FALSE),"") | F57: ='1. Master scoring '!W29 | G57: ='1. Master scoring '!Y29 | H57: ='1. Master scoring '!AB29 -> 0 | I57: ='1. Master scoring '!AG29 | J57: ='1. Master scoring '!O29 | K57: ='1. Master scoring '!P29

Sheet 3. VAS deep dive (2)
B2: VAS deep-dive
B3: View business cases for the highest value VAS
C4: ]
B7: VAS ANALYSIS | S7: SCORING
AH9: ='1. Master scoring '!S14
C10: VAS | H10: SELLING APPROACH | N10: AREAS OF IMPROVEMENT
C11: Telemedicine | H11: =VLOOKUP(C11,REPOSITORY!$A$3:$AL$34,9,FALSE) -> Bundle | J11: =VLOOKUP($C$11,REPOSITORY!$A$3:$AL$34,10,FALSE) -> Hidden
N12: {=_xlfn.IFS($C$32="Implement",Intelligence!H10,$C$32="Kill","No Go",$C$32="Validate",Intelligence!I16,$C$32="Do not touch","Go")} -> VALUE PROPOSITION | P12: {=_xlfn.IFS($C$32="Implement",Intelligence!H11,$C$32="Kill","No Go",$C$32="Validate",Intelligence!I16,$C$32="Do not touch","Go")} -> SELLING APPROACH
H14: SALES CHANNELS
N15: GTM SUGGESTIONS | AE15: Grow core Business Margin | AF15: Core Business Sales | AG15: ='1. Master scoring '!R14 -> 5
H16: =VLOOKUP($C$11,REPOSITORY!$A$3:$AL$34,11,FALSE) -> Third parties | J16: =VLOOKUP($C$11,REPOSITORY!$A$3:$AL$34,12,FALSE) -> Physical | AE16: Grow core Business Margin | AF16: Customer base | AG16: 6
N17: Evaluate these actions
N19: {=_xlfn.IFS(N12="No Go", "The overall score for this VAS is too low. Evaluate its usefullness or eliminate the service",N12="Go On", "This VAS is XXXX",TRUE,Intelligence!G10)} -> - Customize the service: By customizing the service to meet the specific needs of the customer, you can increase its perceived value. This can be done by offering personalized recommendations, tailored solutions or by creating a personalized service plan to meet the unique needs of the customer. | P19: {=_xlfn.IFS(P12="No Go", "The overall score for this VAS is too low. Evaluate its usefullness or eliminate the service",P12="Go On", "This VAS is XXXX",TRUE,Intelligence!G11)} -> - Customize the service: By customizing the service to meet the specific needs of the customer, you can increase its perceived value. This can be done by offering personalized recommendations, tailored solutions or by creating a personalized service plan to meet the unique needs of the customer. | AE19: Grow core Business Margin | AF19: Customer acquisition costs | AG19: ='1. Master scoring '!T14 -> 4
K20: =IFERROR(VLOOKUP(C$11,'5. Input GTM Strategy '!$B$13:$O$159,15,FALSE),"") | AE20: Grow core Business Margin | AF20: Multiproduct Percentage | AG20: ='1. Master scoring '!U$14 -> 5
AE21: Grow core Business Margin | AF21: Claim costs | AG21: ='1. Master scoring '!V$14 -> 2.3333333
C22: CATEGORY | AE22: Commercial Viability | AF22: Business Risk | AG22: ='1. Master scoring '!W$14 -> 1.0208333
C23: =VLOOKUP(C11,REPOSITORY!$A$3:$AL$34,4,FALSE) -> Practical guides / Prevention information​ | H23: COMMUNICATION CHANNEL | AE23: Customer Desirability | AF23: Perceived Value | AG23: ='1. Master scoring '!X$14 -> 4.3333333
AE24: Customer Desirability | AF24: Potential Reach | AG24: 3
C25: LOB | H25: PAID | I25: =VLOOKUP($C$11,REPOSITORY!$A$3:$AL$34,13,FALSE) -> Third parties | K25: =VLOOKUP($C$11,REPOSITORY!$A$3:$AL$34,14,FALSE) -> Physical | AE25: Execution | AF25: Improve NPS | AG25: ='1. Master scoring '!Z$14 -> 5
C26: =VLOOKUP(C11,REPOSITORY!$A$3:$AL$34,3,FALSE) -> DigitalAccessAndProtection​ | H26: =IFERROR(VLOOKUP($C$11,'5. Input GTM Strategy '!$B$13:$O$159,33,FALSE),"") | K26: =IFERROR(VLOOKUP($C$11,'5. Input GTM Strategy '!$B$13:$O$159,37,FALSE),"") | AE26: Execution | AF26: Retention | AG26: ='1. Master scoring '!AA$14 -> 5
H27: ORGANIC | I27: =VLOOKUP($C$11,REPOSITORY!$A$3:$AL$34,15,FALSE) -> 2 | K27: =VLOOKUP($C$11,REPOSITORY!$A$3:$AL$34,16,FALSE) -> Radio | AE27: Execution | AF27: Increase customers' interactions (TP) | AG27: 0
C28: OVERALL SCORE | E28: OVERALL RANK | H28: =IFERROR(VLOOKUP($C$11,'5. Input GTM Strategy '!$B$13:$O$159,35,FALSE),"") | K28: =IFERROR(VLOOKUP($C$11,'5. Input GTM Strategy '!$B$13:$O$159,39,FALSE),"") | AE28: Execution | AF28: Differentiation | AG28: ='1. Master scoring '!AC$14 -> 5
C29: =Z37 -> 4.2443182 | E29: =IFERROR(VLOOKUP($S$37,'1. Master scoring '!C14:AG31,14,FALSE),"") -> 1 | H29: OWNED | I29: =VLOOKUP($C$11,REPOSITORY!$A$3:$AL$34,17,FALSE) -> 2 | K29: =VLOOKUP($C$11,REPOSITORY!$A$3:$AL$34,18,FALSE) -> Social Media | AE29: Execution | AF29: Regulation | AG29: 1
C31: OUR RECOMMENDATION | H31: CUSTOMER RATIONALE
C32: {=_xlfn.IFS(C29<4,"Kill",C29>11,"Continue",4,"Implement",AND(C29>4,C29<11),"Validate")} -> Implement | H32: Target profiled | I32: =VLOOKUP($C$11,REPOSITORY!$A$3:$AL$34,21,FALSE) -> High profilation
H35: Competitive Advantage | I35: =VLOOKUP($C$11,REPOSITORY!$A$3:$AL$34,19,FALSE) -> Medium Importance | S35: BREAKDOWN
U36: Grow Core Business Margin | V36: Commercial viability | W36: Customer desirability | X36: Execution | Z36: ='3. NON USARE Master scoring'!M10 -> Overall Score
I37: =IFERROR(VLOOKUP($C$11,'5. Input GTM Strategy '!$B$13:$O$159,44,FALSE),"") | S37: =C11 -> Telemedicine | U37: =IFERROR(VLOOKUP(S37,'1. Master scoring '!C14:W31,21,FALSE),"") -> 1.0208333 | V37: =IFERROR(VLOOKUP(S37,'1. Master scoring '!C14:Y31,23,FALSE),"") -> 4.3333333 | W37: =IFERROR(VLOOKUP(S37,'1. Master scoring '!C14:AB31,26,FALSE),"") -> 3.75 | X37: =IFERROR(VLOOKUP(S37,'1. Master scoring '!C14:AG31,32,FALSE),"") | Z37: =IFERROR(VLOOKUP(S37,'1. Master scoring '!C14:AG31,13,FALSE),"") -> 4.2443182
U38: =IFERROR(VLOOKUP(S37,'1. Master scoring '!C14:M31,20,FALSE),"") | V38: =IFERROR(VLOOKUP(T38,'1. Master scoring '!D15:X32,20,FALSE),"") | W38: =IFERROR(VLOOKUP(U38,'1. Master scoring '!E15:Y32,20,FALSE),"") | X38: =IFERROR(VLOOKUP(V38,'1. Master scoring '!F15:Z32,20,FALSE),"") | Z38: =IFERROR(VLOOKUP(S37,'[1]1'!$C$14:$AH$118,11,FALSE),"")

Sheet 3. VAS deep dive
B2: VAS deep-dive
B3: View business cases for the highest value VAS
C4: ]
B7: VAS ANALYSIS | S7: SCORING
AH9: ='1. Master scoring '!S14
C10: VAS | H10: PRICE VS COSTS | N10: AREAS OF IMPROVEMENT
C11: Telemedicine | H11: Price of the insurance for the customer | J11: Cost of the insurance for the company
H12: =VLOOKUP(C11,'1. Master scoring '!C14:AI33,32,FALSE) -> 2.6666667 | J12: =VLOOKUP(C11,'1. Master scoring '!C14:AI33,33,FALSE) -> 4 | N12: {=_xlfn.IFS($C$26="Implement",Intelligence!H10,$C$26="Revise","No Go",$C$26="Validate",Intelligence!I16,$C$26="Do not touch","Go")} -> VALUE PROPOSITION | P12: {=_xlfn.IFS($C$26="Implement",Intelligence!H11,$C$26="Revise","No Go",$C$26="Validate",Intelligence!I16,$C$26="Do not touch","Go")} -> SELLING APPROACH
H14: SELLING APPROACH
H15: =VLOOKUP(C11,REPOSITORY!$A$3:$AL$34,9,FALSE) -> Bundle | J15: =VLOOKUP($C$11,REPOSITORY!$A$3:$AL$34,10,FALSE) -> Hidden | N15: GTM SUGGESTIONS | AE15: Grow core Business Margin | AF15: Core Business Sales | AG15: ='1. Master scoring '!R14 -> 5
C16: CATEGORY | AE16: Grow core Business Margin | AF16: Customer base | AG16: 6
C17: =VLOOKUP(C11,REPOSITORY!$A$3:$AL$34,4,FALSE) -> Practical guides / Prevention information​ | N17: Evaluate these actions
H18: SALES CHANNELS
C19: LOB | N19: {=_xlfn.IFS(N12="No Go", "The overall score for this VAS is too low. Evaluate its usefullness or eliminate the service",N12="Go On", "This VAS is XXXX",TRUE,Intelligence!G10)} -> - Customize the service: By customizing the service to meet the specific needs of the customer, you can increase its perceived value. This can be done by offering personalized recommendations, tailored solutions or by creating a personalized service plan to meet the unique needs of the customer. | P19: {=_xlfn.IFS(P12="No Go", "The overall score for this VAS is too low. Evaluate its usefullness or eliminate the service",P12="Go On", "This VAS is XXXX",TRUE,Intelligence!G11)} -> - Customize the service: By customizing the service to meet the specific needs of the customer, you can increase its perceived value. This can be done by offering personalized recommendations, tailored solutions or by creating a personalized service plan to meet the unique needs of the customer. | AE19: Grow core Business Margin | AF19: Customer acquisition costs | AG19: ='1. Master scoring '!T14 -> 4
C20: =VLOOKUP(C11,REPOSITORY!$A$3:$AL$34,3,FALSE) -> DigitalAccessAndProtection​ | H20: =VLOOKUP($C$11,REPOSITORY!$A$3:$AL$34,11,FALSE) -> Third parties | J20: =VLOOKUP($C$11,REPOSITORY!$A$3:$AL$34,12,FALSE) -> Physical | AE20: Grow core Business Margin | AF20: Multiproduct Percentage | AG20: ='1. Master scoring '!U$14 -> 5
AE21: Grow core Business Margin | AF21: Claim costs | AG21: ='1. Master scoring '!V$14 -> 2.3333333
C22: OVERALL SCORE | E22: OVERALL RANK | AE22: Commercial Viability | AF22: Business Risk | AG22: ='1. Master scoring '!W$14 -> 1.0208333
C23: =Z37 -> 4.2443182 | E23: =IFERROR(VLOOKUP($S$37,'1. Master scoring '!C14:AG31,14,FALSE),"") -> 1 | H23: COMMUNICATION CHANNEL | AE23: Customer Desirability | AF23: Perceived Value | AG23: ='1. Master scoring '!X$14 -> 4.3333333
AE24: Customer Desirability | AF24: Potential Reach | AG24: 3
C25: OUR RECOMMENDATION | H25: PAID | I25: =VLOOKUP($C$11,REPOSITORY!$A$3:$AL$34,13,FALSE) -> Third parties | K25: =VLOOKUP($C$11,REPOSITORY!$A$3:$AL$34,14,FALSE) -> Physical | AE25: Execution | AF25: Improve NPS | AG25: ='1. Master scoring '!Z$14 -> 5
C26: {=_xlfn.IFS(C23<4,"Revise",C23>11,"Continue",4,"Implement",AND(C23>4,C23<11),"Validate")} -> Implement | H26: =IFERROR(VLOOKUP($C$11,'5. Input GTM Strategy '!$B$13:$O$159,33,FALSE),"") | K26: =IFERROR(VLOOKUP($C$11,'5. Input GTM Strategy '!$B$13:$O$159,37,FALSE),"") | AE26: Execution | AF26: Retention | AG26: ='1. Master scoring '!AA$14 -> 5
H27: ORGANIC | I27: =VLOOKUP($C$11,REPOSITORY!$A$3:$AL$34,15,FALSE) -> 2 | K27: =VLOOKUP($C$11,REPOSITORY!$A$3:$AL$34,16,FALSE) -> Radio | AE27: Execution | AF27: Increase customers' interactions (TP) | AG27: 0
H28: =IFERROR(VLOOKUP($C$11,'5. Input GTM Strategy '!$B$13:$O$159,35,FALSE),"") | K28: =IFERROR(VLOOKUP($C$11,'5. Input GTM Strategy '!$B$13:$O$159,39,FALSE),"") | AE28: Execution | AF28: Differentiation | AG28: ='1. Master scoring '!AC$14 -> 5
H29: OWNED | I29: =VLOOKUP($C$11,REPOSITORY!$A$3:$AL$34,17,FALSE) -> 2 | K29: =VLOOKUP($C$11,REPOSITORY!$A$3:$AL$34,18,FALSE) -> Social Media | AE29: Execution | AF29: Regulation | AG29: 1
H31: CUSTOMER RATIONALE
H32: Target profiled | I32: =VLOOKUP($C$11,REPOSITORY!$A$3:$AL$34,21,FALSE) -> High profilation
H35: C | I35: =VLOOKUP($C$11,REPOSITORY!$A$3:$AL$34,19,FALSE) -> Medium Importance | S35: BREAKDOWN
U36: Grow Core Business Margin | V36: Commercial viability | W36: Customer desirability | X36: Execution | Z36: ='3. NON USARE Master scoring'!M10 -> Overall Score
I37: =IFERROR(VLOOKUP($C$11,'5. Input GTM Strategy '!$B$13:$O$159,44,FALSE),"") | S37: =C11 -> Telemedicine | U37: =IFERROR(VLOOKUP(S37,'1. Master scoring '!C14:W31,21,FALSE),"") -> 1.0208333 | V37: =IFERROR(VLOOKUP(S37,'1. Master scoring '!C14:Y31,23,FALSE),"") -> 4.3333333 | W37: =IFERROR(VLOOKUP(S37,'1. Master scoring '!C14:AB31,26,FALSE),"") -> 3.75 | X37: =IFERROR(VLOOKUP(S37,'1. Master scoring '!C14:AG31,31,FALSE),"") -> 2.5 | Z37: =IFERROR(VLOOKUP(S37,'1. Master scoring '!C14:AG31,13,FALSE),"") -> 4.2443182
U38: =IFERROR(VLOOKUP(S37,'1. Master scoring '!C14:M31,20,FALSE),"") | V38: =IFERROR(VLOOKUP(T38,'1. Master scoring '!D15:X32,20,FALSE),"") | W38: =IFERROR(VLOOKUP(U38,'1. Master scoring '!E15:Y32,20,FALSE),"") | X38: =IFERROR(VLOOKUP(V38,'1. Master scoring '!F15:Z32,20,FALSE),"") | Z38: =IFERROR(VLOOKUP(S37,'[1]1'!$C$14:$AH$118,11,FALSE),"")

Sheet 3. VAS deep dive OLD
B2: VAS deep-dive
B3: View business cases for the highest value VAS
C4: ]
B7: VAS ANALYSIS | S7: SCORING
C10: VAS | H10: SELLING APPROACH | N10: AREAS OF IMPROVEMENT
C11: ID Theft | H11: Boundle | J11: Hide
N12: VALUE PROPOSITION | P12: COMMUNICATION CHANNEL
H14: SALES CHANNELS
C15: =IFERROR(VLOOKUP(C11,'5. Input GTM Strategy '!$B$13:$O$159,2,FALSE),"") -> Cover the costs you might incur from being defrauded | N15: GTM SUGGESTIONS
H16: Third parties | J16: Phygital
N17: Provide education and resources: By providing customers with education and resources, you can help them better understand the value of your value added services, and how they can benefit from them. This can be done by creating educational materials, such as guides, webinars, or video tutorials, that explain the benefits of the services. | P17: Create a niche market: By creating a niche market for your value added service, you can differentiate it from competitors and create a stronger position in the market. This can be done by identifying a specific customer segment or problem that your service addresses better than others, and positioning your service as the best solution in that niche
K18: =IFERROR(VLOOKUP(C$11,'5. Input GTM Strategy '!$B$13:$O$159,15,FALSE),"")
C20: CATEGORY
C21: Pet Care | H21: COMMUNICATION CHANNEL
C23: LOB | H23: PAID | I23: TV | K23: 2
C24: Home Improvement | H24: =IFERROR(VLOOKUP($C$11,'5. Input GTM Strategy '!$B$13:$O$159,33,FALSE),"") | K24: =IFERROR(VLOOKUP($C$11,'5. Input GTM Strategy '!$B$13:$O$159,37,FALSE),"")
H25: ORGANIC | I25: Social Media | K25: 1
C26: OVERALL SCORE | E26: OVERALL RANK | H26: =IFERROR(VLOOKUP($C$11,'5. Input GTM Strategy '!$B$13:$O$159,35,FALSE),"") | K26: =IFERROR(VLOOKUP($C$11,'5. Input GTM Strategy '!$B$13:$O$159,39,FALSE),"")
C27: 3 | E27: =IFERROR(VLOOKUP(C11,'5. Input GTM Strategy '!B13:O159,5,FALSE),"") -> Visible | H27: OWNED | I27: eMailing | K27: 3 or more
C29: OUR RECOMMENDATION | H29: CUSTOMER RATIONALE
C30: Validate | H30: Target profiled | I30: High
H33: Importance to stay competitive | I33: Low | S33: BREAKDOWN
U34: Grow Core Business Margin | V34: Commercial viability | W34: Customer desirability | X34: Execution | Y34: ='3. NON USARE Master scoring'!M10 -> Overall Score
I35: =IFERROR(VLOOKUP($C$11,'5. Input GTM Strategy '!$B$13:$O$159,44,FALSE),"") | S35: =C11 -> ID Theft | U35: =IFERROR(VLOOKUP(S35,'1. Master scoring '!C14:W31,20,FALSE),"") -> 2.3333333 | V35: =IFERROR(VLOOKUP(S35,'1. Master scoring '!C14:Y31,21,FALSE),"") -> 0.89583333 | W35: =IFERROR(VLOOKUP(S35,'1. Master scoring '!C14:AB31,24,FALSE),"") -> 4.6666667 | X35: =IFERROR(VLOOKUP(S35,'1. Master scoring '!C14:AG31,30,FALSE),"") -> 4.3333333 | Y35: =IFERROR(VLOOKUP(S35,'3. NON USARE Master scoring'!$C$14:$AH$118,11,FALSE),"") -> 4.1666667
U36: =IFERROR(VLOOKUP(S35,'1. Master scoring '!C14:M31,20,FALSE),"") | V36: =IFERROR(VLOOKUP(T36,'1. Master scoring '!D15:X32,20,FALSE),"") | W36: =IFERROR(VLOOKUP(U36,'1. Master scoring '!E15:Y32,20,FALSE),"") | X36: =IFERROR(VLOOKUP(V36,'1. Master scoring '!F15:Z32,20,FALSE),"")

Sheet Intelligence OLD
C2: GTM
C3: Log list of VAS w/description
C4: \
B7: VAS | C7: KPIs | D7: Business Objectives | E7: GTM Elements
E8: VALUE PROPOSITION | F8: SELLING APPROACH | G8: SALES CHANNEL | H8: COMMUNICATION CHANNELS | I8: MARKET POSITIONING | J8: TARGET
E9: Evaluate these actions: - Improve the service quality: By improving the quality of the service, you can increase its perceived value to the customer, making it more attractive and compelling. This can be done by investing in employee training, enhancing the service delivery process, and gathering customer feedback to continuously improve the service. - Provide education and resources: By providing customers with education and resources, you can help them better understand the value of your value added services, and how they can benefit from them. This can be done by creating educational materials, such as guides, webinars, or video tutorials, that explain the benefits of the services. - Customize the service: By customizing the service to meet the specific needs of the customer, you can increase its perceived value. This can be done by offering personalized recommendations, tailored solutions or by creating a personalized service plan to meet the unique needs of the customer. | F9: Evaluate these actions: - Offer flexible pricing options: By offering flexible pricing options, such as usage-based pricing, pay-as-you-go pricing, or tiered pricing, you can make your products and services more accessible to a wider range of customers; - Offer guarantees: By offering guarantees on your value added services, you can increase the perceived value and build trust with customers. This can be done by offering a money-back guarantee, a satisfaction guarantee, or by providing a warranty on the service; - Review boundling approach: Bundling value added services with core insurance products can be an effective way to sell them as it allows you to offer a more comprehensive package to customers, making it more convenient for them to purchase additional services they might need. Standalone approach can be used when the value added service is not related to the core insurance product or is a service that can be used independently from the core insurance product. Additionally, you can also offer the value added services as an option to the customers, giving them the choice to purchase them separately or as a bundle. This approach can help you cater to different customer needs and preferences. | G9: Evaluate these actions: - Develop a strong distribution network: By building a strong distribution network, you can reach more potential customers and increase the visibility of your value added services. This can be done by partnering with other companies, such as insurance brokers or financial advisors, who can help promote and sell your services. - Offer flexible pricing and packaging options: By offering flexible pricing and packaging options, you can make your value added services more accessible to a wider range of customers, which can help increase sales. - Implement a digital sales channel: By implementing a digital sales channel, such as an online platform or mobile app, you can make it easier for customers to access and purchase your value added services, which can help increase sales. Additionally, this will enable you to reach more customers and make the sales process more efficient. | H9: Evaluate these actions: ATL: Use a mix of traditional and digital channels, such as television and social media advertising, to reach a wider audience and create a consistent message across different touchpoints. This can help increase the visibility of the value added service and create a positive image for the insurance company. Or use more targeted and relevant advertising campaigns, such as social media advertising and native advertising, to reach specific customer segments more effectively. This can help increase the relevance of the message and the chances of it being seen by the target audience. TTL: Leverage influencer marketing and customer testimonials to create more authentic and credible messages. This can help increase the perceived value of the service and create a deeper connection with the target audience. BTL: Use more sophisticated segmentation and personalization techniques to target specific customer segments and deliver more relevant messages. This can help increase the chances of converting leads into sales. Additionally, you could also measure the effectiveness of each channel and make adjustments accordingly. A/B testing can be used to measure the effectiveness of different approaches and to make data-driven decisions | I9: Evaluate these actions: - Conduct a competitive analysis: By conducting a competitive analysis, you can gain a deeper understanding of the strengths and weaknesses of your competitors and identify areas where your value added service can differentiate itself. This can help inform your positioning strategy and ensure that your service is well-positioned in the market. - Leverage your unique assets: By leveraging your unique assets, such as proprietary technology, a strong brand, or a wide distribution network, you can differentiate your value added service from competitors and create a stronger position in the market. - Create a niche market: By creating a niche market for your value added service, you can differentiate it from competitors and create a stronger position in the market. This can be done by identifying a specific customer segment or problem that your service addresses better than others, and positioning your service as the best solution in that niche | J9: Evaluate these actions: - Identify and segment your target market: By identifying and segmenting your target market, you can create a more targeted and effective value proposition, and tailor your sales and marketing efforts to specific customer segments. This can help increase the chances of success for your value added service. - Align your value added service with the customer's needs: By aligning your value added service with the customer's needs, you can increase the perceived value of the service and make it more attractive to potential customers. This can be done by identifying the problems that the customer is facing and positioning your service as the best solution. - Measure and continuously improve: By measuring and continuously improving your value added service, you can ensure that it stays relevant and continues to meet the needs of your target market. This can be done by gathering customer feedback, analyzing usage data, and using that information to make improvements and adjustments to the service.
C10: Core Business Sales | D10: Grow core Business Margin | E10: x
C11: Customer base | D11: Grow core Business Margin | E11: x | J11: x
C12: Customer acquisition costs | D12: Grow core Business Margin | F12: x | G12: x | H12: x
C13: Multiproduct Percentage | D13: Grow core Business Margin | F13: x
C14: Claim costs | D14: Grow core Business Margin | E14: x
C15: Business Risk | D15: Commercial Viability | E15: x
C16: Perceived Value | D16: Customer Desirability | G16: x | H16: x | I16: x | J16: x
C17: Potential Reach | D17: Customer Desirability | E17: x | H17: x
C18: Improve NPS | D18: Execution | E18: x | J18: x
C19: Retention | D19: Execution | H19: x
C20: Increase customers' interactions (TP) | D20: Execution | E20: x | F20: x | G20: x | H20: x
C21: Differentiation | D21: Execution | I21: x
C22: Regulation | D22: Execution | E22: x
D24: A | E24: - Improve the service quality: By improving the quality of the service, you can increase its perceived value to the customer, making it more attractive and compelling. This can be done by investing in employee training, enhancing the service delivery process, and gathering customer feedback to continuously improve the service. | F24: - Offer flexible pricing options: By offering flexible pricing options, such as usage-based pricing, pay-as-you-go pricing, or tiered pricing, you can make your products and services more accessible to a wider range of customers; | G24: - Develop a strong distribution network: By building a strong distribution network, you can reach more potential customers and increase the visibility of your value added services. This can be done by partnering with other companies, such as insurance brokers or financial advisors, who can help promote and sell your services. | H24: Use a mix of traditional and digital channels, such as television and social media advertising, to reach a wider audience and create a consistent message across different touchpoints. This can help increase the visibility of the value added service and create a positive image for the insurance company. Or use more targeted and relevant advertising campaigns, such as social media advertising and native advertising, to reach specific customer segments more effectively. This can help increase the relevance of the message and the chances of it being seen by the target audience. | I24: - Conduct a competitive analysis: By conducting a competitive analysis, you can gain a deeper understanding of the strengths and weaknesses of your competitors and identify areas where your value added service can differentiate itself. This can help inform your positioning strategy and ensure that your service is well-positioned in the market. | J24: - Identify and segment your target market: By identifying and segmenting your target market, you can create a more targeted and effective value proposition, and tailor your sales and marketing efforts to specific customer segments. This can help increase the chances of success for your value added service.
D25: B | E25: - Provide education and resources: By providing customers with education and resources, you can help them better understand the value of your value added services, and how they can benefit from them. This can be done by creating educational materials, such as guides, webinars, or video tutorials, that explain the benefits of the services. | F25: - Offer guarantees: By offering guarantees on your value added services, you can increase the perceived value and build trust with customers. This can be done by offering a money-back guarantee, a satisfaction guarantee, or by providing a warranty on the service; | G25: - Offer flexible pricing and packaging options: By offering flexible pricing and packaging options, you can make your value added services more accessible to a wider range of customers, which can help increase sales. | H25: Leverage influencer marketing and customer testimonials to create more authentic and credible messages. This can help increase the perceived value of the service and create a deeper connection with the target audience. | I25: - Leverage your unique assets: By leveraging your unique assets, such as proprietary technology, a strong brand, or a wide distribution network, you can differentiate your value added service from competitors and create a stronger position in the market. | J25: - Align your value added service with the customer's needs: By aligning your value added service with the customer's needs, you can increase the perceived value of the service and make it more attractive to potential customers. This can be done by identifying the problems that the customer is facing and positioning your service as the best solution.
D26: C | E26: - Customize the service: By customizing the service to meet the specific needs of the customer, you can increase its perceived value. This can be done by offering personalized recommendations, tailored solutions or by creating a personalized service plan to meet the unique needs of the customer. | F26: - Review boundling approach: Bundling value added services with core insurance products can be an effective way to sell them as it allows you to offer a more comprehensive package to customers, making it more convenient for them to purchase additional services they might need. Standalone approach can be used when the value added service is not related to the core insurance product or is a service that can be used independently from the core insurance product. Additionally, you can also offer the value added services as an option to the customers, giving them the choice to purchase them separately or as a bundle. This approach can help you cater to different customer needs and preferences. | G26: - Implement a digital sales channel: By implementing a digital sales channel, such as an online platform or mobile app, you can make it easier for customers to access and purchase your value added services, which can help increase sales. Additionally, this will enable you to reach more customers and make the sales process more efficient. | H26: Use more sophisticated segmentation and personalization techniques to target specific customer segments and deliver more relevant messages. This can help increase the chances of converting leads into sales. | I26: - Create a niche market: By creating a niche market for your value added service, you can differentiate it from competitors and create a stronger position in the market. This can be done by identifying a specific customer segment or problem that your service addresses better than others, and positioning your service as the best solution in that niche | J26: - Measure and continuously improve: By measuring and continuously improving your value added service, you can ensure that it stays relevant and continues to meet the needs of your target market. This can be done by gathering customer feedback, analyzing usage data, and using that information to make improvements and adjustments to the service.

Sheet 3. NON USARE Master scoring
B2: Master scoring
B3: Add and evaluate new VAS
C6: 1 | D6: =C6+1 -> 2 | E6: =D6+1 -> 3 | F6: =E6+1 -> 4 | G6: =F6+1 -> 5 | H6: =G6+1 -> 6 | I6: =H6+1 -> 7 | J6: =I6+1 -> 8 | K6: =J6+1 -> 9 | ... V6: =U6+1 -> 20 | X6: =V6+1 -> 21 | Y6: =X6+1 -> 22 | Z6: =Y6+1 -> 23 | AA6: =Z6+1 -> 24 | AC6: =AA6+1 -> 25 | AD6: =AC6+1 -> 26 | AE6: =AD6+1 -> 27 | AF6: =AE6+1 -> 28 | AG6: =AF6+1 -> 29 | AH6: =AG6+1 -> 30
C7: MANUAL INPUT | I7: MANUAL/AUTOMATED INPUT. | M7: AUTOMATED. | P7: AUTOMATED - DO NOT TOUCH.
C8: OVERVIEW | I8: Status | M8: Score | P8: Scoring criteria (av.)
M9: Scoring | P9: Grow Revenues | U9: Commercial Viability: is it financially significant? | Y9: Customer Desirability: will customers value it? | AD9: Execution Feasibility: how able are we to deliver it? | AJ9: EXTRA INFORMATION | AL9: Resources
C10: VAS | D10: Description | E10: Category | F10: Subcategory | G10: Type | I10: Scored | J10: Meets requirements? | K10: Status | M10: Overall Score | N10: Rank | P10: Improve Sales | Q10: Profit margin | R10: LOB Revenues VS Target | S10: Financial risk | T10: TOTAL | U10: Reach | V10: Revenue | W10: Acquisition | X10: TOTAL | Y10: Clarity | Z10: Value | AA10: Pain point | AB10: Usage | AC10: TOTAL | AD10: Capability gap | AE10: Partnership Availability | AF10: Speed to market | AG10: Regulation | AH10: TOTAL | AJ10: Additional notes | AL10: Are there relevant research materials?
M11: =IFERROR(AVERAGEIF($C14:$C130,"<>",M14:M130),"") -> 4.1259259 | N11: - | P11: =IFERROR(AVERAGEIF($C14:$C130,"<>",P14:P130),"") -> 4.7333333 | Q11: =IFERROR(AVERAGEIF($C14:$C130,"<>",Q14:Q130),"") -> 2.7333333 | R11: =IFERROR(AVERAGEIF($C14:$C130,"<>",R14:R130),"") -> 4.4666667 | S11: =IFERROR(AVERAGEIF($C14:$C130,"<>",S14:S130),"") -> 3 | T11: =IFERROR(AVERAGEIF($C14:$C130,"<>",T14:T130),"") -> 3.7333333 | U11: =IFERROR(AVERAGEIF($C14:$C130,"<>",U14:U130),"") | V11: =IFERROR(AVERAGEIF($C14:$C130,"<>",V14:V130),"") | W11: =IFERROR(AVERAGEIF($C14:$C130,"<>",W14:W130),"") -> 3.8 | ... AA11: =IFERROR(AVERAGEIF($C14:$C130,"<>",AA14:AA130),"") | AC11: =IFERROR(AVERAGEIF($C14:$C130,"<>",AC14:AC130),"") -> 4.6 | AD11: =IFERROR(AVERAGEIF($C14:$C130,"<>",AD14:AD130),"") -> 4.6 | AE11: =IFERROR(AVERAGEIF($F15:$F131,"<>",AE15:AE131),"") -> 4.6666667 | AF11: =IFERROR(AVERAGEIF($C14:$C130,"<>",AF14:AF130),"") -> 4.6 | AG11: =IFERROR(AVERAGEIF($C14:$C130,"<>",AG14:AG130),"") | AH11: =IFERROR(AVERAGEIF($C14:$C130,"<>",AH14:AH130),"") -> 4.6
C12: What is the name of the VAS? | D12: Brief description of VAS | E12: Which strategic pillar does this VAS fall under? | F12: If 'Net new', can the feature be grouped into a broader area or pain point? | G12: How ambitious is it for us to deliver this VAS? | I12: Has this feature been assessed by all scorers? | J12: Does this feature meet the requirements for its opportunity type? See 'Scoring criteria' for minimum requirement details | K12: What is the final status? | M12: Overall score. | N12: Rank | P12: How are these revenues contributing to the company performance | Q12: How much profit we make on revenues before expenses | R12: How much is this VAS contributing to the department performance | S12: How exposed are we financially when delivering this VAS? | U12: What is the total number of customers (i.e. market size) we could realistically offer this feature to? | V12: How much would we make on each customer through this VAS, each year? | W12: How valuable is this VAS in attracting new customers to our? | X12: Commercial viability overall score. | Y12: How clear is the need for this feature from customers? | Z12: How much value would this feature deliver to customers? | AA12: How well is the customer need currently being served by competitors? | AC12: Overall customer desirability score. | AD12: What capabilities do we have to deliver this feature? (across TPW and LG) | AE12: If the initiative would benefit from partnership, how strong are the options for possible partners? | AF12: How quickly could we launch this feature in market (either through building or partnering) | AG12: How complex or restrictive is the regulatory environment for this VAS? | AH12: Overall execution feasibility score. | AJ12: What was the outcome of review? Are there agreed next steps to be aware of? | AL12: Materials #1 | AM12: Materials #2 | AN12: Materials #3
G13: - Quick win - Big bet - Long shot | I13: Automated. | J13: Manual. | K13: Manual. | M13: Automated. | P13: - Very high value - High value - Some value - Low value - No value | Q13: - 5: Market leader - 4: Highly differentiated - 3: Differentiated - 2: Some differentiation - 1: Hygiene | R13: - 5: No risk - 4: Litte risk - 3: Some risk - 2: Risky - 1: Very risky | S13: - 5: No exposure - 4: Minimal exposure - 3: Some exposure - 2: High exposure - 1: Very high exposure | T13: Automated. | U13: - 5: Mass market - 4: Large reach - 3: Solid reach - 2: Niche segment - 1: Very niche segment | V13: -5: >£100 -4: <£100 -3: <£50 -2:<£25 -1: <£10 | W13: - Very large hook - Large hook - Solid hook - Small hook - No hook | X13: Automated. | Y13: - 5: Very clear - 4: Clear - 3: Some clarity - 2: Low clarity - 1: No clarity | Z13: - Very high value - High value - Some value - Low value - No value | AA13: - 5: Very large pain point - 4: Large pain point - 3: Some pain - 2: Low pain point - 1: No pain point | AC13: Automated. | AD13: - 5: No gap - 4: Small gap - 3: Acceptable gap - 2: Large gap - 1: Very large gap | AE13: - 5: Extremely Strong / not required at all - 4: Strong - 3: Acceptable - 2: Weak - 1: Extremely Weak | AF13: - 5: Very fast - 4: Fast - 3: Quite fast - 2: Slow - 1: Very slow | AG13: - No red tape - Low regulation - Some regulation - Highly regulated - Very highly regulated | AH13: Automated. | AJ13: Manual | AL13: Manual | AM13: Manual | AN13: Manual
C14: Medical assistance | D14: Cover the costs of private healthcare, from diagnosis to treatment | E14: Damage Limitation | F14: Health | G14: Quick win | J14: =IF(G14="","",IF(AND(G14="Quick win",T14>='7. Scoring criteria'!$C$45,AH14>='7. Scoring criteria'!$F$45),"Yes",IF(AND(G14="Big bet",T14>='7. Scoring criteria'!$C$46,X14>='7. Scoring criteria'!$D$46),"Yes",IF(AND(G14="Big bet",T14>='7. Scoring criteria'!$C$46,AC14>='7. Scoring criteria'!$E$46),"Yes",IF(AND(G14="Long shot",X14>='7. Scoring criteria'!$D$47,AC14>='7. Scoring criteria'!$E$47),"Yes","No"))))) -> Yes | K14: Live | M14: =IFERROR(AVERAGE(P14:S14,U14:W14,Y14:AA14,AD14:AG14),"") -> 4.5185185 | N14: =IFERROR(RANK(M14,$M$14:$M$128,0)+COUNTIF($M$14:M14,#REF!)," ") -> 1 | P14: =IFERROR(AVERAGE('4a. Scorer 1'!F13,'4b. Scorer 2'!F13,'4c. Scorer 3'!F13)," ") -> 5 | Q14: =IFERROR(AVERAGE('4a. Scorer 1'!H13,'4b. Scorer 2'!H13,'4c. Scorer 3'!H13)," ") -> 4 | R14: =IFERROR(AVERAGE('4a. Scorer 1'!I13,'4b. Scorer 2'!I13,'4c. Scorer 3'!I13)," ") -> 5 | S14: =IFERROR(AVERAGE('4a. Scorer 1'!J13,'4b. Scorer 2'!J13,'4c. Scorer 3'!J13)," ") -> 2.3333333 | T14: =IFERROR(AVERAGE(P14:S14),"") -> 4.0833333 | U14: =IFERROR(AVERAGE('4a. Scorer 1'!#REF!,'4b. Scorer 2'!#REF!,'4c. Scorer 3'!#REF!)," ") | V14: =IFERROR(AVERAGE('4a. Scorer 1'!#REF!,'4b. Scorer 2'!#REF!,'4c. Scorer 3'!#REF!)," ") | W14: =IFERROR(AVERAGE('4a. Scorer 1'!L13,'4b. Scorer 2'!L13,'4c. Scorer 3'!L13)," ") -> 4.3333333 | X14: =IFERROR(AVERAGE(U14:W14),"") -> 4.3333333 | Y14: =IFERROR(AVERAGE('4a. Scorer 1'!#REF!,'4b. Scorer 2'!#REF!,'4c. Scorer 3'!#REF!)," ") | Z14: =IFERROR(AVERAGE('4a. Scorer 1'!N13,'4b. Scorer 2'!N13,'4c. Scorer 3'!N13)," ") -> 5 | AA14: =IFERROR(AVERAGE('4a. Scorer 1'!#REF!,'4b. Scorer 2'!#REF!,'4c. Scorer 3'!#REF!)," ") | AC14: =IFERROR(AVERAGE(Y14:AA14),"") -> 5 | AD14: =IFERROR(AVERAGE('4a. Scorer 1'!Q13,'4b. Scorer 2'!P13,'4c. Scorer 3'!P13)," ") -> 5 | AE14: =IFERROR(AVERAGE('4a. Scorer 1'!R13,'4b. Scorer 2'!Q13,'4c. Scorer 3'!Q13)," ") -> 5 | AF14: =IFERROR(AVERAGE('4a. Scorer 1'!S13,'4b. Scorer 2'!R13,'4c. Scorer 3'!R13)," ") -> 5 | AG14: =IFERROR(AVERAGE('4a. Scorer 1'!#REF!,'4b. Scorer 2'!S13,'4c. Scorer 3'!S13)," ") | AH14: =IFERROR(AVERAGE(AD14:AG14),"") -> 5
C15: ID Theft | D15: Cover the costs you might incur from being defrauded | E15: Repair & Support | F15: Digital Access & Protection | G15: Long shot | J15: =IF(G15="","",IF(AND(G15="Quick win",T15>='7. Scoring criteria'!$C$45,AH15>='7. Scoring criteria'!$F$45),"Yes",IF(AND(G15="Big bet",T15>='7. Scoring criteria'!$C$46,X15>='7. Scoring criteria'!$D$46),"Yes",IF(AND(G15="Big bet",T15>='7. Scoring criteria'!$C$46,AC15>='7. Scoring criteria'!$E$46),"Yes",IF(AND(G15="Long shot",X15>='7. Scoring criteria'!$D$47,AC15>='7. Scoring criteria'!$E$47),"Yes","No"))))) -> Yes | K15: Live | M15: =IFERROR(AVERAGE(P15:S15,U15:W15,Y15:AA15,AD15:AG15),"") -> 4.1666667 | N15: =IFERROR(RANK(M15,$M$14:$M$128,0)+COUNTIF($M$14:M15,#REF!)," ") -> 2 | P15: =IFERROR(AVERAGE('4a. Scorer 1'!F14,'4b. Scorer 2'!F14,'4c. Scorer 3'!F14)," ") -> 5 | Q15: =IFERROR(AVERAGE('4a. Scorer 1'!H14,'4b. Scorer 2'!H14,'4c. Scorer 3'!H14)," ") -> 2 | R15: =IFERROR(AVERAGE('4a. Scorer 1'!I14,'4b. Scorer 2'!I14,'4c. Scorer 3'!I14)," ") -> 5 | S15: =IFERROR(AVERAGE('4a. Scorer 1'!J14,'4b. Scorer 2'!J14,'4c. Scorer 3'!J14)," ") -> 2.3333333 | T15: =IFERROR(AVERAGE(P15:S15),"") -> 3.5833333 | U15: =IFERROR(AVERAGE('4a. Scorer 1'!#REF!,'4b. Scorer 2'!#REF!,'4c. Scorer 3'!#REF!)," ") | V15: =IFERROR(AVERAGE('4a. Scorer 1'!#REF!,'4b. Scorer 2'!#REF!,'4c. Scorer 3'!#REF!)," ") | W15: =IFERROR(AVERAGE('4a. Scorer 1'!L14,'4b. Scorer 2'!L14,'4c. Scorer 3'!L14)," ") -> 4 | X15: =IFERROR(AVERAGE(U15:W15),"") -> 4 | Y15: =IFERROR(AVERAGE('4a. Scorer 1'!#REF!,'4b. Scorer 2'!#REF!,'4c. Scorer 3'!#REF!)," ") | Z15: =IFERROR(AVERAGE('4a. Scorer 1'!N14,'4b. Scorer 2'!N14,'4c. Scorer 3'!N14)," ") -> 4.6666667 | AA15: =IFERROR(AVERAGE('4a. Scorer 1'!#REF!,'4b. Scorer 2'!#REF!,'4c. Scorer 3'!#REF!)," ") | AC15: =IFERROR(AVERAGE(Y15:AA15),"") -> 4.6666667 | AD15: =IFERROR(AVERAGE('4a. Scorer 1'!Q14,'4b. Scorer 2'!P14,'4c. Scorer 3'!P14)," ") -> 4.5 | AE15: =IFERROR(AVERAGE('4a. Scorer 1'!R14,'4b. Scorer 2'!Q14,'4c. Scorer 3'!Q14)," ") -> 5 | AF15: =IFERROR(AVERAGE('4a. Scorer 1'!S14,'4b. Scorer 2'!R14,'4c. Scorer 3'!R14)," ") -> 5 | AG15: =IFERROR(AVERAGE('4a. Scorer 1'!#REF!,'4b. Scorer 2'!S14,'4c. Scorer 3'!S14)," ") | AH15: =IFERROR(AVERAGE(AD15:AG15),"") -> 4.8333333
C16: Vehicle Geolocation | D16: Install an approved GPS tracking device and reduce vehicle insurance premium | E16: Information | F16: Mobility | G16: Quick win | J16: =IF(G16="","",IF(AND(G16="Quick win",T16>='7. Scoring criteria'!$C$45,AH16>='7. Scoring criteria'!$F$45),"Yes",IF(AND(G16="Big bet",T16>='7. Scoring criteria'!$C$46,X16>='7. Scoring criteria'!$D$46),"Yes",IF(AND(G16="Big bet",T16>='7. Scoring criteria'!$C$46,AC16>='7. Scoring criteria'!$E$46),"Yes",IF(AND(G16="Long shot",X16>='7. Scoring criteria'!$D$47,AC16>='7. Scoring criteria'!$E$47),"Yes","No"))))) -> Yes | K16: Approved for implementation | M16: =IFERROR(AVERAGE(P16:S16,U16:W16,Y16:AA16,AD16:AG16),"") -> 4.0925926 | N16: =IFERROR(RANK(M16,$M$14:$M$128,0)+COUNTIF($M$14:M16,#REF!)," ") -> 3 | P16: =IFERROR(AVERAGE('4a. Scorer 1'!F15,'4b. Scorer 2'!F15,'4c. Scorer 3'!F15)," ") -> 5 | Q16: =IFERROR(AVERAGE('4a. Scorer 1'!H15,'4b. Scorer 2'!H15,'4c. Scorer 3'!H15)," ") -> 2.6666667 | R16: =IFERROR(AVERAGE('4a. Scorer 1'!I15,'4b. Scorer 2'!I15,'4c. Scorer 3'!I15)," ") -> 4.3333333 | S16: =IFERROR(AVERAGE('4a. Scorer 1'!J15,'4b. Scorer 2'!J15,'4c. Scorer 3'!J15)," ") -> 3 | T16: =IFERROR(AVERAGE(P16:S16),"") -> 3.75 | U16: =IFERROR(AVERAGE('4a. Scorer 1'!#REF!,'4b. Scorer 2'!#REF!,'4c. Scorer 3'!#REF!)," ") | V16: =IFERROR(AVERAGE('4a. Scorer 1'!#REF!,'4b. Scorer 2'!#REF!,'4c. Scorer 3'!#REF!)," ") | W16: =IFERROR(AVERAGE('4a. Scorer 1'!L15,'4b. Scorer 2'!L15,'4c. Scorer 3'!L15)," ") -> 3.6666667 | X16: =IFERROR(AVERAGE(U16:W16),"") -> 3.6666667 | Y16: =IFERROR(AVERAGE('4a. Scorer 1'!#REF!,'4b. Scorer 2'!#REF!,'4c. Scorer 3'!#REF!)," ") | Z16: =IFERROR(AVERAGE('4a. Scorer 1'!N15,'4b. Scorer 2'!N15,'4c. Scorer 3'!N15)," ") -> 4.6666667 | AA16: =IFERROR(AVERAGE('4a. Scorer 1'!#REF!,'4b. Scorer 2'!#REF!,'4c. Scorer 3'!#REF!)," ") | AC16: =IFERROR(AVERAGE(Y16:AA16),"") -> 4.6666667 | AD16: =IFERROR(AVERAGE('4a. Scorer 1'!Q15,'4b. Scorer 2'!P15,'4c. Scorer 3'!P15)," ") -> 4.8333333 | AE16: =IFERROR(AVERAGE('4a. Scorer 1'!R15,'4b. Scorer 2'!Q15,'4c. Scorer 3'!Q15)," ") -> 4 | AF16: =IFERROR(AVERAGE('4a. Scorer 1'!S15,'4b. Scorer 2'!R15,'4c. Scorer 3'!R15)," ") -> 4.6666667 | AG16: =IFERROR(AVERAGE('4a. Scorer 1'!#REF!,'4b. Scorer 2'!S15,'4c. Scorer 3'!S15)," ") | AH16: =IFERROR(AVERAGE(AD16:AG16),"") -> 4.5
C17: Pet Care | D17: Cover the cost of veterinary fees for illnesses or injuries | E17: Prevention/Wellness | F17: Home & Family | G17: Big bet | J17: =IF(G17="","",IF(AND(G17="Quick win",T17>='7. Scoring criteria'!$C$45,AH17>='7. Scoring criteria'!$F$45),"Yes",IF(AND(G17="Big bet",T17>='7. Scoring criteria'!$C$46,X17>='7. Scoring criteria'!$D$46),"Yes",IF(AND(G17="Big bet",T17>='7. Scoring criteria'!$C$46,AC17>='7. Scoring criteria'!$E$46),"Yes",IF(AND(G17="Long shot",X17>='7. Scoring criteria'!$D$47,AC17>='7. Scoring criteria'!$E$47),"Yes","No"))))) -> Yes | K17: Live | M17: =IFERROR(AVERAGE(P17:S17,U17:W17,Y17:AA17,AD17:AG17),"") -> 4.0740741 | N17: =IFERROR(RANK(M17,$M$14:$M$128,0)+COUNTIF($M$14:M17,#REF!)," ") -> 4 | P17: =IFERROR(AVERAGE('4a. Scorer 1'!F16,'4b. Scorer 2'!F16,'4c. Scorer 3'!F16)," ") -> 4.6666667 | Q17: =IFERROR(AVERAGE('4a. Scorer 1'!H16,'4b. Scorer 2'!H16,'4c. Scorer 3'!H16)," ") -> 2.3333333 | R17: =IFERROR(AVERAGE('4a. Scorer 1'!I16,'4b. Scorer 2'!I16,'4c. Scorer 3'!I16)," ") -> 4.3333333 | S17: =IFERROR(AVERAGE('4a. Scorer 1'!J16,'4b. Scorer 2'!J16,'4c. Scorer 3'!J15)," ") -> 3.6666667 | T17: =IFERROR(AVERAGE(P17:S17),"") -> 3.75 | U17: =IFERROR(AVERAGE('4a. Scorer 1'!#REF!,'4b. Scorer 2'!#REF!,'4c. Scorer 3'!#REF!)," ") | V17: =IFERROR(AVERAGE('4a. Scorer 1'!#REF!,'4b. Scorer 2'!#REF!,'4c. Scorer 3'!#REF!)," ") | W17: =IFERROR(AVERAGE('4a. Scorer 1'!L16,'4b. Scorer 2'!L16,'4c. Scorer 3'!L16)," ") -> 3.3333333 | X17: =IFERROR(AVERAGE(U17:W17),"") -> 3.3333333 | Y17: =IFERROR(AVERAGE('4a. Scorer 1'!#REF!,'4b. Scorer 2'!#REF!,'4c. Scorer 3'!#REF!)," ") | Z17: =IFERROR(AVERAGE('4a. Scorer 1'!N16,'4b. Scorer 2'!N16,'4c. Scorer 3'!N16)," ") -> 4 | AA17: =IFERROR(AVERAGE('4a. Scorer 1'!#REF!,'4b. Scorer 2'!#REF!,'4c. Scorer 3'!#REF!)," ") | AC17: =IFERROR(AVERAGE(Y17:AA17),"") -> 4 | AD17: =IFERROR(AVERAGE('4a. Scorer 1'!Q16,'4b. Scorer 2'!P16,'4c. Scorer 3'!P16)," ") -> 4.3333333 | AE17: =IFERROR(AVERAGE('4a. Scorer 1'!R16,'4b. Scorer 2'!Q16,'4c. Scorer 3'!Q16)," ") -> 5 | AF17: =IFERROR(AVERAGE('4a. Scorer 1'!S16,'4b. Scorer 2'!R16,'4c. Scorer 3'!R16)," ") -> 5 | AG17: =IFERROR(AVERAGE('4a. Scorer 1'!#REF!,'4b. Scorer 2'!S16,'4c. Scorer 3'!S16)," ") | AH17: =IFERROR(AVERAGE(AD17:AG17),"") -> 4.7777778
C18: Fixed rate roaming | D18: Pay a flat fee to get a set number of miles at all/some public charge points (requires multiple CPO partnerships or a fin-tech partnership) | E18: Net new | G18: Big bet | J18: =IF(G18="","",IF(AND(G18="Quick win",T18>='7. Scoring criteria'!$C$45,AH18>='7. Scoring criteria'!$F$45),"Yes",IF(AND(G18="Big bet",T18>='7. Scoring criteria'!$C$46,X18>='7. Scoring criteria'!$D$46),"Yes",IF(AND(G18="Big bet",T18>='7. Scoring criteria'!$C$46,AC18>='7. Scoring criteria'!$E$46),"Yes",IF(AND(G18="Long shot",X18>='7. Scoring criteria'!$D$47,AC18>='7. Scoring criteria'!$E$47),"Yes","No"))))) -> Yes | K18: Paused | M18: =IFERROR(AVERAGE(P18:S18,U18:W18,Y18:AA18,AD18:AG18),"") -> 3.7777778 | N18: =IFERROR(RANK(M18,$M$14:$M$128,0)+COUNTIF($M$14:M18,#REF!)," ") -> 5 | P18: =IFERROR(AVERAGE('4a. Scorer 1'!F17,'4b. Scorer 2'!F17,'4c. Scorer 3'!F17)," ") -> 4 | Q18: =IFERROR(AVERAGE('4a. Scorer 1'!H17,'4b. Scorer 2'!H17,'4c. Scorer 3'!H17)," ") -> 2.6666667 | R18: =IFERROR(AVERAGE('4a. Scorer 1'!I17,'4b. Scorer 2'!I17,'4c. Scorer 3'!I17)," ") -> 3.6666667 | S18: =IFERROR(AVERAGE('4a. Scorer 1'!J17,'4b. Scorer 2'!J17,'4c. Scorer 3'!J17)," ") -> 3.6666667 | T18: =IFERROR(AVERAGE(P18:S18),"") -> 3.5 | U18: =IFERROR(AVERAGE('4a. Scorer 1'!#REF!,'4b. Scorer 2'!#REF!,'4c. Scorer 3'!#REF!)," ") | V18: =IFERROR(AVERAGE('4a. Scorer 1'!#REF!,'4b. Scorer 2'!#REF!,'4c. Scorer 3'!#REF!)," ") | W18: =IFERROR(AVERAGE('4a. Scorer 1'!L17,'4b. Scorer 2'!L17,'4c. Scorer 3'!L17)," ") -> 3.6666667 | X18: =IFERROR(AVERAGE(U18:W18),"") -> 3.6666667 | Y18: =IFERROR(AVERAGE('4a. Scorer 1'!#REF!,'4b. Scorer 2'!#REF!,'4c. Scorer 3'!#REF!)," ") | Z18: =IFERROR(AVERAGE('4a. Scorer 1'!N17,'4b. Scorer 2'!N17,'4c. Scorer 3'!N17)," ") -> 4.6666667 | AA18: =IFERROR(AVERAGE('4a. Scorer 1'!#REF!,'4b. Scorer 2'!#REF!,'4c. Scorer 3'!#REF!)," ") | AC18: =IFERROR(AVERAGE(Y18:AA18),"") -> 4.6666667 | AD18: =IFERROR(AVERAGE('4a. Scorer 1'!Q17,'4b. Scorer 2'!P17,'4c. Scorer 3'!P17)," ") -> 4.3333333 | AE18: =IFERROR(AVERAGE('4a. Scorer 1'!R17,'4b. Scorer 2'!Q17,'4c. Scorer 3'!Q17)," ") -> 4 | AF18: =IFERROR(AVERAGE('4a. Scorer 1'!S17,'4b. Scorer 2'!R17,'4c. Scorer 3'!R17)," ") -> 3.3333333 | AG18: =IFERROR(AVERAGE('4a. Scorer 1'!#REF!,'4b. Scorer 2'!S17,'4c. Scorer 3'!S17)," ") | AH18: =IFERROR(AVERAGE(AD18:AG18),"") -> 3.8888889
C19: 48 hour repair and replace | D19: On site support within two days of finding an issue with your charger | E19: Support | F19: - | G19: Quick win | J19: =IF(G19="","",IF(AND(G19="Quick win",T19>='7. Scoring criteria'!$C$45,AH19>='7. Scoring criteria'!$F$45),"Yes",IF(AND(G19="Big bet",T19>='7. Scoring criteria'!$C$46,X19>='7. Scoring criteria'!$D$46),"Yes",IF(AND(G19="Big bet",T19>='7. Scoring criteria'!$C$46,AC19>='7. Scoring criteria'!$E$46),"Yes",IF(AND(G19="Long shot",X19>='7. Scoring criteria'!$D$47,AC19>='7. Scoring criteria'!$E$47),"Yes","No"))))) -> Yes | K19: Live | M19: =IFERROR(AVERAGE(P19:S19,U19:W19,Y19:AA19,AD19:AG19),"") | N19: =IFERROR(RANK(M19,$M$14:$M$128,0)+COUNTIF($M$14:M19,#REF!)," ") | P19: =IFERROR(AVERAGE('4a. Scorer 1'!F18,'4b. Scorer 2'!F18,'4c. Scorer 3'!F18)," ") | Q19: =IFERROR(AVERAGE('4a. Scorer 1'!H18,'4b. Scorer 2'!H18,'4c. Scorer 3'!H18)," ") | R19: =IFERROR(AVERAGE('4a. Scorer 1'!I18,'4b. Scorer 2'!I18,'4c. Scorer 3'!I18)," ") | S19: =IFERROR(AVERAGE('4a. Scorer 1'!J18,'4b. Scorer 2'!J18,'4c. Scorer 3'!J18)," ") | T19: =IFERROR(AVERAGE(P19:S19),"") | U19: =IFERROR(AVERAGE('4a. Scorer 1'!#REF!,'4b. Scorer 2'!#REF!,'4c. Scorer 3'!#REF!)," ") | V19: =IFERROR(AVERAGE('4a. Scorer 1'!#REF!,'4b. Scorer 2'!#REF!,'4c. Scorer 3'!#REF!)," ") | W19: =IFERROR(AVERAGE('4a. Scorer 1'!L18,'4b. Scorer 2'!L18,'4c. Scorer 3'!L18)," ") | X19: =IFERROR(AVERAGE(U19:W19),"") | Y19: =IFERROR(AVERAGE('4a. Scorer 1'!#REF!,'4b. Scorer 2'!#REF!,'4c. Scorer 3'!#REF!)," ") | Z19: =IFERROR(AVERAGE('4a. Scorer 1'!N18,'4b. Scorer 2'!N18,'4c. Scorer 3'!N18)," ") | AA19: =IFERROR(AVERAGE('4a. Scorer 1'!#REF!,'4b. Scorer 2'!#REF!,'4c. Scorer 3'!#REF!)," ") | AC19: =IFERROR(AVERAGE(Y19:AA19),"") | AD19: =IFERROR(AVERAGE('4a. Scorer 1'!Q18,'4b. Scorer 2'!P18,'4c. Scorer 3'!P18)," ") | AE19: =IFERROR(AVERAGE('4a. Scorer 1'!R18,'4b. Scorer 2'!Q18,'4c. Scorer 3'!Q18)," ") | AF19: =IFERROR(AVERAGE('4a. Scorer 1'!S18,'4b. Scorer 2'!R18,'4c. Scorer 3'!R18)," ") | AG19: =IFERROR(AVERAGE('4a. Scorer 1'!#REF!,'4b. Scorer 2'!S18,'4c. Scorer 3'!S18)," ") | AH19: =IFERROR(AVERAGE(AD19:AG19),"")
C20: Roaming charge card | D20: Access 1000s of charge points on the go through our charge pass, pay as you go | E20: Net new | F20: Public charging | G20: Big bet | J20: =IF(G20="","",IF(AND(G20="Quick win",T20>='7. Scoring criteria'!$C$45,AH20>='7. Scoring criteria'!$F$45),"Yes",IF(AND(G20="Big bet",T20>='7. Scoring criteria'!$C$46,X20>='7. Scoring criteria'!$D$46),"Yes",IF(AND(G20="Big bet",T20>='7. Scoring criteria'!$C$46,AC20>='7. Scoring criteria'!$E$46),"Yes",IF(AND(G20="Long shot",X20>='7. Scoring criteria'!$D$47,AC20>='7. Scoring criteria'!$E$47),"Yes","No"))))) -> Yes | K20: Awaiting leadership review | M20: =IFERROR(AVERAGE(P20:S20,U20:W20,Y20:AA20,AD20:AG20),"") | N20: =IFERROR(RANK(M20,$M$14:$M$128,0)+COUNTIF($M$14:M20,#REF!)," ") | P20: =IFERROR(AVERAGE('4a. Scorer 1'!F19,'4b. Scorer 2'!F19,'4c. Scorer 3'!F19)," ") | Q20: =IFERROR(AVERAGE('4a. Scorer 1'!H19,'4b. Scorer 2'!H19,'4c. Scorer 3'!H19)," ") | R20: =IFERROR(AVERAGE('4a. Scorer 1'!I19,'4b. Scorer 2'!I19,'4c. Scorer 3'!I19)," ") | S20: =IFERROR(AVERAGE('4a. Scorer 1'!J19,'4b. Scorer 2'!J19,'4c. Scorer 3'!J19)," ") | T20: =IFERROR(AVERAGE(P20:S20),"") | U20: =IFERROR(AVERAGE('4a. Scorer 1'!#REF!,'4b. Scorer 2'!#REF!,'4c. Scorer 3'!#REF!)," ") | V20: =IFERROR(AVERAGE('4a. Scorer 1'!#REF!,'4b. Scorer 2'!#REF!,'4c. Scorer 3'!#REF!)," ") | W20: =IFERROR(AVERAGE('4a. Scorer 1'!L19,'4b. Scorer 2'!L19,'4c. Scorer 3'!L19)," ") | X20: =IFERROR(AVERAGE(U20:W20),"") | Y20: =IFERROR(AVERAGE('4a. Scorer 1'!#REF!,'4b. Scorer 2'!#REF!,'4c. Scorer 3'!#REF!)," ") | Z20: =IFERROR(AVERAGE('4a. Scorer 1'!N19,'4b. Scorer 2'!N19,'4c. Scorer 3'!N19)," ") | AA20: =IFERROR(AVERAGE('4a. Scorer 1'!#REF!,'4b. Scorer 2'!#REF!,'4c. Scorer 3'!#REF!)," ") | AC20: =IFERROR(AVERAGE(Y20:AA20),"") | AD20: =IFERROR(AVERAGE('4a. Scorer 1'!Q19,'4b. Scorer 2'!P19,'4c. Scorer 3'!P19)," ") | AE20: =IFERROR(AVERAGE('4a. Scorer 1'!R19,'4b. Scorer 2'!Q19,'4c. Scorer 3'!Q19)," ") | AF20: =IFERROR(AVERAGE('4a. Scorer 1'!S19,'4b. Scorer 2'!R19,'4c. Scorer 3'!R19)," ") | AG20: =IFERROR(AVERAGE('4a. Scorer 1'!#REF!,'4b. Scorer 2'!S19,'4c. Scorer 3'!S19)," ") | AH20: =IFERROR(AVERAGE(AD20:AG20),"") | AJ20: Deprioritised based on lack of clear customer need/potential partners
C21: Discounted roaming | D21: Get access to cheaper rates on public charge points when joining our service | E21: Net new | F21: Public charging | G21: Big bet | J21: =IF(G21="","",IF(AND(G21="Quick win",T21>='7. Scoring criteria'!$C$45,AH21>='7. Scoring criteria'!$F$45),"Yes",IF(AND(G21="Big bet",T21>='7. Scoring criteria'!$C$46,X21>='7. Scoring criteria'!$D$46),"Yes",IF(AND(G21="Big bet",T21>='7. Scoring criteria'!$C$46,AC21>='7. Scoring criteria'!$E$46),"Yes",IF(AND(G21="Long shot",X21>='7. Scoring criteria'!$D$47,AC21>='7. Scoring criteria'!$E$47),"Yes","No"))))) -> Yes | K21: Paused | M21: =IFERROR(AVERAGE(P21:S21,U21:W21,Y21:AA21,AD21:AG21),"") | N21: =IFERROR(RANK(M21,$M$14:$M$128,0)+COUNTIF($M$14:M21,#REF!)," ") | P21: =IFERROR(AVERAGE('4a. Scorer 1'!F20,'4b. Scorer 2'!F20,'4c. Scorer 3'!F20)," ") | Q21: =IFERROR(AVERAGE('4a. Scorer 1'!H20,'4b. Scorer 2'!H20,'4c. Scorer 3'!H20)," ") | R21: =IFERROR(AVERAGE('4a. Scorer 1'!I20,'4b. Scorer 2'!I20,'4c. Scorer 3'!I20)," ") | S21: =IFERROR(AVERAGE('4a. Scorer 1'!J20,'4b. Scorer 2'!J20,'4c. Scorer 3'!J20)," ") | T21: =IFERROR(AVERAGE(P21:S21),"") | U21: =IFERROR(AVERAGE('4a. Scorer 1'!#REF!,'4b. Scorer 2'!#REF!,'4c. Scorer 3'!#REF!)," ") | V21: =IFERROR(AVERAGE('4a. Scorer 1'!#REF!,'4b. Scorer 2'!M20,'4c. Scorer 3'!#REF!)," ") | W21: =IFERROR(AVERAGE('4a. Scorer 1'!L20,'4b. Scorer 2'!L20,'4c. Scorer 3'!L20)," ") | X21: =IFERROR(AVERAGE(U21:W21),"") | Y21: =IFERROR(AVERAGE('4a. Scorer 1'!#REF!,'4b. Scorer 2'!N20,'4c. Scorer 3'!#REF!)," ") | Z21: =IFERROR(AVERAGE('4a. Scorer 1'!N20,'4b. Scorer 2'!N20,'4c. Scorer 3'!N20)," ") | AA21: =IFERROR(AVERAGE('4a. Scorer 1'!#REF!,'4b. Scorer 2'!#REF!,'4c. Scorer 3'!#REF!)," ") | AC21: =IFERROR(AVERAGE(Y21:AA21),"") | AD21: =IFERROR(AVERAGE('4a. Scorer 1'!Q20,'4b. Scorer 2'!P20,'4c. Scorer 3'!P20)," ") | AE21: =IFERROR(AVERAGE('4a. Scorer 1'!R20,'4b. Scorer 2'!Q20,'4c. Scorer 3'!Q20)," ") | AF21: =IFERROR(AVERAGE('4a. Scorer 1'!S20,'4b. Scorer 2'!R20,'4c. Scorer 3'!R20)," ") | AG21: =IFERROR(AVERAGE('4a. Scorer 1'!#REF!,'4b. Scorer 2'!S20,'4c. Scorer 3'!S20)," ") | AH21: =IFERROR(AVERAGE(AD21:AG21),"")
C22: Customise your charger | D22: Control over the form of your charger (size, colour, shape, personalised details) | E22: Hardware | F22: - | G22: Quick win | J22: =IF(G22="","",IF(AND(G22="Quick win",T22>='7. Scoring criteria'!$C$45,AH22>='7. Scoring criteria'!$F$45),"Yes",IF(AND(G22="Big bet",T22>='7. Scoring criteria'!$C$46,X22>='7. Scoring criteria'!$D$46),"Yes",IF(AND(G22="Big bet",T22>='7. Scoring criteria'!$C$46,AC22>='7. Scoring criteria'!$E$46),"Yes",IF(AND(G22="Long shot",X22>='7. Scoring criteria'!$D$47,AC22>='7. Scoring criteria'!$E$47),"Yes","No"))))) -> Yes | K22: Approved for implementation | M22: =IFERROR(AVERAGE(P22:S22,U22:W22,Y22:AA22,AD22:AG22),"") | N22: =IFERROR(RANK(M22,$M$14:$M$128,0)+COUNTIF($M$14:M22,#REF!)," ") | P22: =IFERROR(AVERAGE('4a. Scorer 1'!F21,'4b. Scorer 2'!F21,'4c. Scorer 3'!F21)," ") | Q22: =IFERROR(AVERAGE('4a. Scorer 1'!H21,'4b. Scorer 2'!H21,'4c. Scorer 3'!H21)," ") | R22: =IFERROR(AVERAGE('4a. Scorer 1'!I21,'4b. Scorer 2'!I21,'4c. Scorer 3'!I21)," ") | S22: =IFERROR(AVERAGE('4a. Scorer 1'!J21,'4b. Scorer 2'!J21,'4c. Scorer 3'!J21)," ") | T22: =IFERROR(AVERAGE(P22:S22),"") | U22: =IFERROR(AVERAGE('4a. Scorer 1'!#REF!,'4b. Scorer 2'!#REF!,'4c. Scorer 3'!#REF!)," ") | V22: =IFERROR(AVERAGE('4a. Scorer 1'!#REF!,'4b. Scorer 2'!M21,'4c. Scorer 3'!#REF!)," ") | W22: =IFERROR(AVERAGE('4a. Scorer 1'!L21,'4b. Scorer 2'!L21,'4c. Scorer 3'!L21)," ") | X22: =IFERROR(AVERAGE(U22:W22),"") | Y22: =IFERROR(AVERAGE('4a. Scorer 1'!#REF!,'4b. Scorer 2'!N21,'4c. Scorer 3'!#REF!)," ") | Z22: =IFERROR(AVERAGE('4a. Scorer 1'!N21,'4b. Scorer 2'!N21,'4c. Scorer 3'!N21)," ") | AA22: =IFERROR(AVERAGE('4a. Scorer 1'!#REF!,'4b. Scorer 2'!#REF!,'4c. Scorer 3'!#REF!)," ") | AC22: =IFERROR(AVERAGE(Y22:AA22),"") | AD22: =IFERROR(AVERAGE('4a. Scorer 1'!Q21,'4b. Scorer 2'!P21,'4c. Scorer 3'!P21)," ") | AE22: =IFERROR(AVERAGE('4a. Scorer 1'!R21,'4b. Scorer 2'!Q21,'4c. Scorer 3'!Q21)," ") | AF22: =IFERROR(AVERAGE('4a. Scorer 1'!S21,'4b. Scorer 2'!R21,'4c. Scorer 3'!R21)," ") | AG22: =IFERROR(AVERAGE('4a. Scorer 1'!#REF!,'4b. Scorer 2'!S21,'4c. Scorer 3'!S21)," ") | AH22: =IFERROR(AVERAGE(AD22:AG22),"")
C23: Two box charger | D23: Allow customers to charge and receive information about their energy usage in home | E23: Hardware | F23: - | G23: Big bet | J23: =IF(G23="","",IF(AND(G23="Quick win",T23>='7. Scoring criteria'!$C$45,AH23>='7. Scoring criteria'!$F$45),"Yes",IF(AND(G23="Big bet",T23>='7. Scoring criteria'!$C$46,X23>='7. Scoring criteria'!$D$46),"Yes",IF(AND(G23="Big bet",T23>='7. Scoring criteria'!$C$46,AC23>='7. Scoring criteria'!$E$46),"Yes",IF(AND(G23="Long shot",X23>='7. Scoring criteria'!$D$47,AC23>='7. Scoring criteria'!$E$47),"Yes","No"))))) -> Yes | K23: Approved for implementation | M23: =IFERROR(AVERAGE(P23:S23,U23:W23,Y23:AA23,AD23:AG23),"") | N23: =IFERROR(RANK(M23,$M$14:$M$128,0)+COUNTIF($M$14:M23,#REF!)," ") | P23: =IFERROR(AVERAGE('4a. Scorer 1'!F22,'4b. Scorer 2'!F22,'4c. Scorer 3'!F22)," ") | Q23: =IFERROR(AVERAGE('4a. Scorer 1'!H22,'4b. Scorer 2'!H22,'4c. Scorer 3'!H22)," ") | R23: =IFERROR(AVERAGE('4a. Scorer 1'!I22,'4b. Scorer 2'!I22,'4c. Scorer 3'!I22)," ") | S23: =IFERROR(AVERAGE('4a. Scorer 1'!J22,'4b. Scorer 2'!J22,'4c. Scorer 3'!J22)," ") | T23: =IFERROR(AVERAGE(P23:S23),"") | U23: =IFERROR(AVERAGE('4a. Scorer 1'!#REF!,'4b. Scorer 2'!#REF!,'4c. Scorer 3'!#REF!)," ") | V23: =IFERROR(AVERAGE('4a. Scorer 1'!#REF!,'4b. Scorer 2'!M22,'4c. Scorer 3'!#REF!)," ") | W23: =IFERROR(AVERAGE('4a. Scorer 1'!L22,'4b. Scorer 2'!L22,'4c. Scorer 3'!L22)," ") | X23: =IFERROR(AVERAGE(U23:W23),"") | Y23: =IFERROR(AVERAGE('4a. Scorer 1'!#REF!,'4b. Scorer 2'!N22,'4c. Scorer 3'!#REF!)," ") | Z23: =IFERROR(AVERAGE('4a. Scorer 1'!N22,'4b. Scorer 2'!N22,'4c. Scorer 3'!N22)," ") | AA23: =IFERROR(AVERAGE('4a. Scorer 1'!#REF!,'4b. Scorer 2'!#REF!,'4c. Scorer 3'!#REF!)," ") | AC23: =IFERROR(AVERAGE(Y23:AA23),"") | AD23: =IFERROR(AVERAGE('4a. Scorer 1'!Q22,'4b. Scorer 2'!P22,'4c. Scorer 3'!P22)," ") | AE23: =IFERROR(AVERAGE('4a. Scorer 1'!R22,'4b. Scorer 2'!Q22,'4c. Scorer 3'!Q22)," ") | AF23: =IFERROR(AVERAGE('4a. Scorer 1'!S22,'4b. Scorer 2'!R22,'4c. Scorer 3'!R22)," ") | AG23: =IFERROR(AVERAGE('4a. Scorer 1'!#REF!,'4b. Scorer 2'!S22,'4c. Scorer 3'!S22)," ") | AH23: =IFERROR(AVERAGE(AD23:AG23),"")
C24: Energy credit | D24: Sign up to our subscription and get £50 credit on your energy tariff (i.e. OVO) | E24: Net new | F24: Home energy | G24: Quick win | J24: =IF(G24="","",IF(AND(G24="Quick win",T24>='7. Scoring criteria'!$C$45,AH24>='7. Scoring criteria'!$F$45),"Yes",IF(AND(G24="Big bet",T24>='7. Scoring criteria'!$C$46,X24>='7. Scoring criteria'!$D$46),"Yes",IF(AND(G24="Big bet",T24>='7. Scoring criteria'!$C$46,AC24>='7. Scoring criteria'!$E$46),"Yes",IF(AND(G24="Long shot",X24>='7. Scoring criteria'!$D$47,AC24>='7. Scoring criteria'!$E$47),"Yes","No"))))) -> Yes | K24: Awaiting business case review | M24: =IFERROR(AVERAGE(P24:S24,U24:W24,Y24:AA24,AD24:AG24),"") | N24: =IFERROR(RANK(M24,$M$14:$M$128,0)+COUNTIF($M$14:M24,#REF!)," ") | P24: =IFERROR(AVERAGE('4a. Scorer 1'!F23,'4b. Scorer 2'!F23,'4c. Scorer 3'!F23)," ") | Q24: =IFERROR(AVERAGE('4a. Scorer 1'!H23,'4b. Scorer 2'!H23,'4c. Scorer 3'!H23)," ") | R24: =IFERROR(AVERAGE('4a. Scorer 1'!I23,'4b. Scorer 2'!I23,'4c. Scorer 3'!I23)," ") | S24: =IFERROR(AVERAGE('4a. Scorer 1'!J23,'4b. Scorer 2'!J23,'4c. Scorer 3'!J23)," ") | T24: =IFERROR(AVERAGE(P24:S24),"") | U24: =IFERROR(AVERAGE('4a. Scorer 1'!#REF!,'4b. Scorer 2'!#REF!,'4c. Scorer 3'!#REF!)," ") | V24: =IFERROR(AVERAGE('4a. Scorer 1'!#REF!,'4b. Scorer 2'!M23,'4c. Scorer 3'!#REF!)," ") | W24: =IFERROR(AVERAGE('4a. Scorer 1'!L23,'4b. Scorer 2'!L23,'4c. Scorer 3'!L23)," ") | X24: =IFERROR(AVERAGE(U24:W24),"") | Y24: =IFERROR(AVERAGE('4a. Scorer 1'!#REF!,'4b. Scorer 2'!N23,'4c. Scorer 3'!#REF!)," ") | Z24: =IFERROR(AVERAGE('4a. Scorer 1'!N23,'4b. Scorer 2'!N23,'4c. Scorer 3'!N23)," ") | AA24: =IFERROR(AVERAGE('4a. Scorer 1'!#REF!,'4b. Scorer 2'!#REF!,'4c. Scorer 3'!#REF!)," ") | AC24: =IFERROR(AVERAGE(Y24:AA24),"") | AD24: =IFERROR(AVERAGE('4a. Scorer 1'!Q23,'4b. Scorer 2'!P23,'4c. Scorer 3'!P23)," ") | AE24: =IFERROR(AVERAGE('4a. Scorer 1'!R23,'4b. Scorer 2'!Q23,'4c. Scorer 3'!Q23)," ") | AF24: =IFERROR(AVERAGE('4a. Scorer 1'!S23,'4b. Scorer 2'!R23,'4c. Scorer 3'!R23)," ") | AG24: =IFERROR(AVERAGE('4a. Scorer 1'!#REF!,'4b. Scorer 2'!S23,'4c. Scorer 3'!S23)," ") | AH24: =IFERROR(AVERAGE(AD24:AG24),"") | AJ24: Progressed for business casing
C25: Public charging incentives | D25: Receive a set amount (i.e. £30) of public charging credit when you sign up to our service (i.e. for ESB energy pre-pay service) | E25: Net new | F25: Public charging | G25: Quick win | J25: =IF(G25="","",IF(AND(G25="Quick win",T25>='7. Scoring criteria'!$C$45,AH25>='7. Scoring criteria'!$F$45),"Yes",IF(AND(G25="Big bet",T25>='7. Scoring criteria'!$C$46,X25>='7. Scoring criteria'!$D$46),"Yes",IF(AND(G25="Big bet",T25>='7. Scoring criteria'!$C$46,AC25>='7. Scoring criteria'!$E$46),"Yes",IF(AND(G25="Long shot",X25>='7. Scoring criteria'!$D$47,AC25>='7. Scoring criteria'!$E$47),"Yes","No"))))) -> Yes | K25: De-prioritised | M25: =IFERROR(AVERAGE(P25:S25,U25:W25,Y25:AA25,AD25:AG25),"") | N25: =IFERROR(RANK(M25,$M$14:$M$128,0)+COUNTIF($M$14:M25,#REF!)," ") | P25: =IFERROR(AVERAGE('4a. Scorer 1'!F24,'4b. Scorer 2'!F24,'4c. Scorer 3'!F24)," ") | Q25: =IFERROR(AVERAGE('4a. Scorer 1'!H24,'4b. Scorer 2'!H24,'4c. Scorer 3'!H24)," ") | R25: =IFERROR(AVERAGE('4a. Scorer 1'!I24,'4b. Scorer 2'!I24,'4c. Scorer 3'!I24)," ") | S25: =IFERROR(AVERAGE('4a. Scorer 1'!J24,'4b. Scorer 2'!J24,'4c. Scorer 3'!J24)," ") | T25: =IFERROR(AVERAGE(P25:S25),"") | U25: =IFERROR(AVERAGE('4a. Scorer 1'!#REF!,'4b. Scorer 2'!#REF!,'4c. Scorer 3'!#REF!)," ") | V25: =IFERROR(AVERAGE('4a. Scorer 1'!#REF!,'4b. Scorer 2'!M24,'4c. Scorer 3'!#REF!)," ") | W25: =IFERROR(AVERAGE('4a. Scorer 1'!L24,'4b. Scorer 2'!L24,'4c. Scorer 3'!L24)," ") | X25: =IFERROR(AVERAGE(U25:W25),"") | Y25: =IFERROR(AVERAGE('4a. Scorer 1'!#REF!,'4b. Scorer 2'!N24,'4c. Scorer 3'!#REF!)," ") | Z25: =IFERROR(AVERAGE('4a. Scorer 1'!N24,'4b. Scorer 2'!N24,'4c. Scorer 3'!N24)," ") | AA25: =IFERROR(AVERAGE('4a. Scorer 1'!#REF!,'4b. Scorer 2'!#REF!,'4c. Scorer 3'!#REF!)," ") | AC25: =IFERROR(AVERAGE(Y25:AA25),"") | AD25: =IFERROR(AVERAGE('4a. Scorer 1'!Q24,'4b. Scorer 2'!P24,'4c. Scorer 3'!P24)," ") | AE25: =IFERROR(AVERAGE('4a. Scorer 1'!R24,'4b. Scorer 2'!Q24,'4c. Scorer 3'!Q24)," ") | AF25: =IFERROR(AVERAGE('4a. Scorer 1'!S24,'4b. Scorer 2'!R24,'4c. Scorer 3'!R24)," ") | AG25: =IFERROR(AVERAGE('4a. Scorer 1'!#REF!,'4b. Scorer 2'!S24,'4c. Scorer 3'!S24)," ") | AH25: =IFERROR(AVERAGE(AD25:AG25),"")
C26: Exclusive energy tariff(s) | D26: Get access to exclusive energy tariff deals if you switch to one of our affiliated providers (i.e. OVO) | E26: Net new | F26: Home energy | G26: Big bet | J26: =IF(G26="","",IF(AND(G26="Quick win",T26>='7. Scoring criteria'!$C$45,AH26>='7. Scoring criteria'!$F$45),"Yes",IF(AND(G26="Big bet",T26>='7. Scoring criteria'!$C$46,X26>='7. Scoring criteria'!$D$46),"Yes",IF(AND(G26="Big bet",T26>='7. Scoring criteria'!$C$46,AC26>='7. Scoring criteria'!$E$46),"Yes",IF(AND(G26="Long shot",X26>='7. Scoring criteria'!$D$47,AC26>='7. Scoring criteria'!$E$47),"Yes","No"))))) -> Yes | K26: Awaiting business case review | M26: =IFERROR(AVERAGE(P26:S26,U26:W26,Y26:AA26,AD26:AG26),"") | N26: =IFERROR(RANK(M26,$M$14:$M$128,0)+COUNTIF($M$14:M26,#REF!)," ") | P26: =IFERROR(AVERAGE('4a. Scorer 1'!F25,'4b. Scorer 2'!F25,'4c. Scorer 3'!F25)," ") | Q26: =IFERROR(AVERAGE('4a. Scorer 1'!H25,'4b. Scorer 2'!H25,'4c. Scorer 3'!H25)," ") | R26: =IFERROR(AVERAGE('4a. Scorer 1'!I25,'4b. Scorer 2'!I25,'4c. Scorer 3'!I25)," ") | S26: =IFERROR(AVERAGE('4a. Scorer 1'!J25,'4b. Scorer 2'!J25,'4c. Scorer 3'!J25)," ") | T26: =IFERROR(AVERAGE(P26:S26),"") | U26: =IFERROR(AVERAGE('4a. Scorer 1'!#REF!,'4b. Scorer 2'!#REF!,'4c. Scorer 3'!#REF!)," ") | V26: =IFERROR(AVERAGE('4a. Scorer 1'!#REF!,'4b. Scorer 2'!M25,'4c. Scorer 3'!#REF!)," ") | W26: =IFERROR(AVERAGE('4a. Scorer 1'!L25,'4b. Scorer 2'!L25,'4c. Scorer 3'!L25)," ") | X26: =IFERROR(AVERAGE(U26:W26),"") | Y26: =IFERROR(AVERAGE('4a. Scorer 1'!#REF!,'4b. Scorer 2'!N25,'4c. Scorer 3'!#REF!)," ") | Z26: =IFERROR(AVERAGE('4a. Scorer 1'!N25,'4b. Scorer 2'!N25,'4c. Scorer 3'!N25)," ") | AA26: =IFERROR(AVERAGE('4a. Scorer 1'!#REF!,'4b. Scorer 2'!#REF!,'4c. Scorer 3'!#REF!)," ") | AC26: =IFERROR(AVERAGE(Y26:AA26),"") | AD26: =IFERROR(AVERAGE('4a. Scorer 1'!Q25,'4b. Scorer 2'!P25,'4c. Scorer 3'!P25)," ") | AE26: =IFERROR(AVERAGE('4a. Scorer 1'!R25,'4b. Scorer 2'!Q25,'4c. Scorer 3'!Q25)," ") | AF26: =IFERROR(AVERAGE('4a. Scorer 1'!S25,'4b. Scorer 2'!R25,'4c. Scorer 3'!R25)," ") | AG26: =IFERROR(AVERAGE('4a. Scorer 1'!#REF!,'4b. Scorer 2'!S25,'4c. Scorer 3'!S25)," ") | AH26: =IFERROR(AVERAGE(AD26:AG26),"")
C27: 100% uptime guarantee | D27: Money back if your charger is down for more than 24 hours | E27: Support | F27: - | G27: Big bet | J27: =IF(G27="","",IF(AND(G27="Quick win",T27>='7. Scoring criteria'!$C$45,AH27>='7. Scoring criteria'!$F$45),"Yes",IF(AND(G27="Big bet",T27>='7. Scoring criteria'!$C$46,X27>='7. Scoring criteria'!$D$46),"Yes",IF(AND(G27="Big bet",T27>='7. Scoring criteria'!$C$46,AC27>='7. Scoring criteria'!$E$46),"Yes",IF(AND(G27="Long shot",X27>='7. Scoring criteria'!$D$47,AC27>='7. Scoring criteria'!$E$47),"Yes","No"))))) -> Yes | K27: De-prioritised | M27: =IFERROR(AVERAGE(P27:S27,U27:W27,Y27:AA27,AD27:AG27),"") | N27: =IFERROR(RANK(M27,$M$14:$M$128,0)+COUNTIF($M$14:M27,#REF!)," ") | P27: =IFERROR(AVERAGE('4a. Scorer 1'!F26,'4b. Scorer 2'!F26,'4c. Scorer 3'!F26)," ") | Q27: =IFERROR(AVERAGE('4a. Scorer 1'!H26,'4b. Scorer 2'!H26,'4c. Scorer 3'!H26)," ") | R27: =IFERROR(AVERAGE('4a. Scorer 1'!I26,'4b. Scorer 2'!I26,'4c. Scorer 3'!I26)," ") | S27: =IFERROR(AVERAGE('4a. Scorer 1'!J26,'4b. Scorer 2'!J26,'4c. Scorer 3'!J26)," ") | T27: =IFERROR(AVERAGE(P27:S27),"") | U27: =IFERROR(AVERAGE('4a. Scorer 1'!#REF!,'4b. Scorer 2'!#REF!,'4c. Scorer 3'!#REF!)," ") | V27: =IFERROR(AVERAGE('4a. Scorer 1'!#REF!,'4b. Scorer 2'!M26,'4c. Scorer 3'!#REF!)," ") | W27: =IFERROR(AVERAGE('4a. Scorer 1'!L26,'4b. Scorer 2'!L26,'4c. Scorer 3'!L26)," ") | X27: =IFERROR(AVERAGE(U27:W27),"") | Y27: =IFERROR(AVERAGE('4a. Scorer 1'!#REF!,'4b. Scorer 2'!N26,'4c. Scorer 3'!#REF!)," ") | Z27: =IFERROR(AVERAGE('4a. Scorer 1'!N26,'4b. Scorer 2'!N26,'4c. Scorer 3'!N26)," ") | AA27: =IFERROR(AVERAGE('4a. Scorer 1'!#REF!,'4b. Scorer 2'!#REF!,'4c. Scorer 3'!#REF!)," ") | AC27: =IFERROR(AVERAGE(Y27:AA27),"") | AD27: =IFERROR(AVERAGE('4a. Scorer 1'!Q26,'4b. Scorer 2'!P26,'4c. Scorer 3'!P26)," ") | AE27: =IFERROR(AVERAGE('4a. Scorer 1'!R26,'4b. Scorer 2'!Q26,'4c. Scorer 3'!Q26)," ") | AF27: =IFERROR(AVERAGE('4a. Scorer 1'!S26,'4b. Scorer 2'!R26,'4c. Scorer 3'!R26)," ") | AG27: =IFERROR(AVERAGE('4a. Scorer 1'!#REF!,'4b. Scorer 2'!S26,'4c. Scorer 3'!S26)," ") | AH27: =IFERROR(AVERAGE(AD27:AG27),"") | AJ27: Previously assessed; depriortised based on financial risk/lack of clear upside
